Workbook

Sheet Readme
A1: Description
A2: Date for creation of this file: 20th February 2024
A4: This excel sheet includes data on GHG intensities obtained with EXIOBASE v3.8-beta1 hybrid
A6: Database | B6: EXIOBASE v3.8-beta1 hybrid
B7: Date EXIOBASE version: 30th June 2023
B8: Webpage: https://lca.aau.dk/
B9: Exiobase v3.8-beta1 hybrid has been created as part of: https://lca-net.com/clubs/exiobase-update/. The development of the workflow and IPCC models are obtained from: https://www.en.plan.aau.dk/research/the-danish-centre-for-environmental-assessment/getting-the-data-right
B10: Year: 2016
A12: Methods | B12: > All GHG intensities in this file are presented as tonne CO2-eq. per unit (the uit is specified in column D in the GHG intensity sheets)
B13: > Land use changes: iLUC is modelled using the iLUC model version 4.3 (https://lca-net.com/clubs/iluc/). The framework of the model is described here: Schmidt J, Weidema B P, Brandão M (2015). A framework for modelling indirect land use changes in life cycle assessment. Journal of Cleaner Production 99:230‑238
B14: The implmentation of the iLUC model in EXIOBASE is described here: Schmidt J, De Rosa M (2018). Enhancing Land Use Change modelling with IO data. Presentation at the SETAC Europe 28th Annual Meeting, Rome, 13-17 May 2018. https://lca-net.com/p/3036
B15: > Electricity model: The electricity model is using the method described here: Muñoz I, Schmidt J, de Saxcé M, Dalgaard R, Merciai S (2015). Inventory of country specific electricity in LCA – consequential scenarios. Version 3.0. Report of the 2.-0 LCA Energy Club. 2.-0 LCA consultants, Aalborg https://lca-net.com/p/3935
B16: This model is implemented in EXIOBASE following the methods described here: Merciai S and Schmidt J (2017). Land use change and electricity models in a multi-regional hybrid input output framework. Paper 25th IIOA Conference in Atlantic City, 19-23 June 2017, USA. https://lca-net.com/p/4513
B17: > Investments: It should be noted that investments, which are typically kept as a final demand category in IO-tables, are integrated in the core IO-table. This corresponds to including capital goods in LCA.
B18: > LCIA method: GHG emissions are calculated using IPCC (2013), i.e. the characterisation factors for CH4 biogenic, CH4 fossil and N2O are: 27.75 kg CO2-eq/kg, 30.5 kg CO2.eq/kg and 265 kg CO2-eq/kg respectively.
B19: On the difference between CH4 from biogenic vs. fossil sources see Muñoz I, Schmidt J (2016). Methane oxidation, biogenic carbon, and the IPCC’s emission metrics. Proposal for a consistent greenhouse-gas accounting. International Journal of Life Cycle Assessment 21:1069–1075
A21: License | B21: https://www.exiobase.eu/index.php/terms-of-use
A23: Data are extracted and provided by 2.-0 LCA consultants
B24: Stefano Merciai
B25: Jannick Schmidt
B26: Valentin Starlinger
A29: Description of the sheets in this excel sheet
B30: GHG production - hybrid | C30: Products at producer (basic price): GHG emissions (tonne CO2-eq.) per unit (units are specified in column D)
B31: GHG market_hybrid | C31: Products at market (basic price*): GHG emissions (tonne CO2-eq.) per unit (units are specified in column D)
B32: GHG market_monetary | C32: Products at market (purchasers price): GHG emissions (tonne CO2-eq.) per MEUR2016
C33: * the product markets in hybrid units are currently provided per basic prices, i.e. inputs of transport and trade margins and product taxes are currently not included. This will be included in the next version.
A35: Country abbreviations
B36: Austria | C36: AT
B37: Australia | C37: AU
B38: Belgium | C38: BE
B39: Bulgaria | C39: BG
B40: Brazil | C40: BR
B41: Canada | C41: CA
B42: Switzerland | C42: CH
B43: China | C43: CN
B44: Cyprus | C44: CY
B45: CzechRepublic | C45: CZ
B46: Germany | C46: DE
B47: Denmark | C47: DK
... B83: RoW Middle East | C83: WM

Sheet GHG production - hybrid
A1: GHG intensities: tonne CO2-eq. per unit
A2: No | B2: EXIOBASE product code | C2: Nace rev1 code | D2: Nace rev2 code | E2: Description | F2: Unit | G2: AT | H2: AU | I2: BE | J2: BG | K2: BR | L2: CA | M2: CH | N2: CN | O2: CY | P2: CZ | Q2: DE | R2: DK | S2: EE | T2: ES | U2: FI | V2: FR | W2: GB | X2: GR | Y2: Global | Z2: HR | AA2: HU | AB2: ID | AC2: IE | AD2: IN | AE2: IT | AF2: JP | AG2: KR | AH2: LT | AI2: LU | AJ2: LV | AK2: MT | AL2: MX | AM2: NL | AN2: NO | AO2: PL | AP2: PT | AQ2: RO | AR2: RU | AS2: SE | AT2: SI | AU2: SK | AV2: TR | AW2: TW | AX2: US | AY2: WA | AZ2: WE | BA2: WF | BB2: WL | BC2: WM | BD2: ZA
A3: 1 | B3: A_Ricey | C3: 01.a | D3: 01.12 | E3: Rice, paddy | F3: tonnes | H3: 1.6835463 | J3: 2.5416114 | K3: 1.8238444 | N3: 2.7750217 | T3: 1.9451067 | V3: 2.9573407 | X3: 1.4806261 | AA3: 3.3970557 | AB3: 2.8331631 | AD3: 2.92581 | AE3: 2.4153112 | AF3: 2.8048108 | AG3: 2.4831094 | AL3: 1.8897061 | AP3: 2.3485249 | AQ3: 3.1466578 | AR3: 2.9874298 | AV3: 2.013476 | AW3: 0.25796814 | AX3: 2.1455835 | AY3: 2.5470732 | AZ3: 3.1357905 | BA3: 2.8487079 | BB3: 2.7146871 | BC3: 2.3546642 | BD3: 5.3670517
A4: 2 | B4: A_Germt | C4: 01.b | D4: 01.11 | E4: Germ, wheat | F4: tonnes | G4: 0.31305153 | H4: 0.5963983 | I4: 0.5100138 | J4: 5.5544416 | L4: 0.63287242 | M4: 0.078950728 | N4: 0.47784702 | P4: 0.42436935 | Q4: 0.091454024 | R4: 0.47913582 | S4: 0.36881215 | U4: 0.30928218 | V4: 0.63555972 | W4: 1.859407 | X4: 0.067564321 | Z4: 0.31847515 | AA4: 0.4324414 | AB4: 0.06519764 | AD4: 0.21673568 | AE4: 0.77982362 | AH4: 0.25518267 | AI4: 0.71527125 | AJ4: 0.37326971 | AK4: 1.2905931 | AL4: 0.46017257 | AM4: 1.0199355 | AN4: 0.4202087 | AO4: 1.1798221 | AP4: 0.55251887 | AQ4: 0.21177208 | AT4: 0.53051063 | AU4: 0.39016231 | AV4: 0.38704371 | AW4: 0.080091649 | AY4: 0.23602916 | AZ4: 1.7221771 | BA4: 0.17931421 | BB4: 12.101768 | BC4: 0.55018917 | BD4: 0.80375356
A5: 3 | B5: A_Wheat | C5: 01.b | D5: 01.11 | E5: Wheat | F5: tonnes | G5: 1.0158941 | H5: 1.5706298 | I5: 1.0550358 | J5: 1.0819611 | K5: 2.2115047 | L5: 1.3301612 | M5: 1.4016494 | N5: 1.6635407 | O5: 6.1007307 | P5: 1.0867337 | Q5: 0.89655488 | R5: 0.89346551 | S5: 1.9011236 | T5: 1.0600968 | U5: 1.4720206 | V5: 1.2158198 | W5: 1.0602858 | X5: 1.1083778 | Z5: 1.0620761 | AA5: 0.90607301 | AC5: 0.75906046 | AD5: 1.1733537 | AE5: 1.4673143 | AF5: 2.2199265 | AG5: 2.9518287 | AH5: 1.2008405 | AI5: 1.2342033 | AJ5: 1.5599049 | AK5: 1.0023983 | AL5: 1.2034598 | AM5: 0.96432676 | AN5: 1.2853748 | AO5: 1.2355217 | AP5: 2.1627005 | AQ5: 1.0017564 | AR5: 1.5636974 | AS5: 1.087857 | AT5: 1.2328978 | AU5: 0.96987868 | AV5: 1.3305209 | AW5: 0.43768903 | AX5: 1.4950269 | AY5: 1.684082 | AZ5: 1.3875875 | BA5: 0.96049038 | BB5: 1.4271157 | BC5: 0.85510963 | BD5: 1.2050141
A6: 4 | B6: A_Barly | C6: 01.c | D6: 01.11 | E6: Barley | F6: tonnes | G6: 0.89899706 | H6: 1.4127067 | I6: 0.97296628 | J6: 0.8823726 | K6: 1.2155577 | L6: 1.221067 | M6: 1.1549523 | N6: 1.9735238 | O6: 27.303776 | P6: 1.1976576 | Q6: 0.87369142 | R6: 0.93195472 | S6: 2.0444894 | T6: 1.1149706 | U6: 1.6781558 | V6: 1.1180305 | W6: 0.93329819 | X6: 0.9168824 | Z6: 1.2433907 | AA6: 0.97144085 | AC6: 0.82049638 | AD6: 1.1305888 | AE6: 1.850449 | AF6: 3.303923 | AG6: 4.9373372 | AH6: 1.5033846 | AI6: 1.5479304 | AJ6: 2.3766655 | AK6: 1.1608903 | AL6: 2.1732905 | AM6: 1.2635867 | AN6: 1.3847448 | AO6: 1.6246124 | AP6: 2.4932435 | AQ6: 0.95502515 | AR6: 1.5093343 | AS6: 1.1361303 | AT6: 1.427817 | AU6: 1.0526354 | AV6: 1.2585613 | AX6: 1.185371 | AY6: 1.0065297 | AZ6: 1.3843303 | BA6: 0.79264041 | BB6: 0.95849923 | BC6: 1.0627825 | BD6: 1.0534656
A7: 5 | B7: A_Buckt | C7: 01.c | D7: 01.11 | E7: Buckwheat | F7: tonnes | K7: 4.0674208 | L7: 5.7591317 | N7: 7.3427042 | P7: 2.3674473 | S7: 4.6345311 | V7: 1.9362754 | Z7: 4.0208896 | AA7: 2.7451907 | AF7: 14.444259 | AG7: 15.520316 | AH7: 3.6462958 | AJ7: 4.7224884 | AO7: 3.3806927 | AR7: 2.6699547 | AT7: 5.5801454 | AU7: 3.6963602 | AX7: 3.8175678 | AY7: 3.2242016 | AZ7: 3.7216892 | BA7: 0.63133218 | BD7: 7.400577
A8: 6 | B8: A_Ceres | C8: 01.c | D8: 01.11 | E8: Cereals nes | F8: tonnes | G8: 0.7581836 | J8: 1.1709949 | M8: 1.2545403 | N8: 1.0512789 | P8: 1.8317571 | T8: 1.0317493 | U8: 1.8908809 | V8: 0.9111749 | X8: 0.67622691 | Z8: 1.0123985 | AA8: 0.85019431 | AC8: 1.5442021 | AE8: 1.0120593 | AG8: 2.0398257 | AH8: 3.1094474 | AI8: 0.88630423 | AL8: 1.7069821 | AO8: 2.4242201 | AQ8: 1.294674 | AR8: 3.2196856 | AT8: 0.78903095 | AU8: 2.7064776 | AW8: 0.00405261 | AY8: 0.33808187 | AZ8: 1.1552352 | BA8: 0.34514706 | BB8: 1.863225 | BC8: 0.67493639 | BD8: 2.87495
A9: 7 | B9: A_Fonio | C9: 01.c | D9: 01.29 | E9: Fonio | F9: tonnes | BA9: 0.73777327
A10: 8 | B10: A_Germe | C10: 01.c | D10: 01.19 | E10: Germ, maize | F10: tonnes | G10: 0.13474685 | H10: 0.27855964 | I10: 0.25653074 | J10: 0.090897451 | K10: 0.081852026 | L10: 0.24100217 | M10: 0.13992504 | N10: 0.26482589 | P10: 0.190177 | Q10: 0.020620239 | R10: 0.17088832 | S10: 0.14033322 | T10: 0.21525299 | V10: 0.16831849 | W10: 0.095049486 | X10: 0.035925701 | Z10: 0.16503327 | AA10: 0.15609013 | AB10: 0.097884761 | AC10: 0.14233831 | AD10: 0.17381903 | AE10: 0.36823297 | AF10: 0.93099884 | AG10: 0.36137993 | AI10: 0.39788865 | AL10: 0.20733822 | AM10: 0.49479114 | AO10: 0.28033881 | AP10: 0.2875305 | AQ10: 0.091671947 | AR10: 0.22661518 | AT10: 0.23104698 | AU10: 0.089363713 | AV10: 0.20931038 | AW10: 0.003796279 | AX10: 0.12902104 | AY10: 0.16077272 | AZ10: 0.1158057 | BA10: 0.04896206 | BB10: 0.19678793 | BC10: 0.37280586 | BD10: 0.38419237
A11: 9 | B11: A_Graid | C11: 01.c | D11: 01.11 | E11: Grain, mixed | F11: tonnes | G11: 1.4245817 | I11: 2.2833932 | L11: 1.5959109 | M11: 1.3888519 | P11: 1.9780996 | Q11: 1.545814 | R11: 1.3180183 | S11: 2.3820904 | T11: 2.0259459 | U11: 2.2803206 | V11: 1.8323745 | W11: 0.98182083 | X11: 1.0516042 | Z11: 2.0517847 | AH11: 2.1900199 | AI11: 1.6195268 | AJ11: 4.5676422 | AO11: 2.0808295 | AS11: 1.6982206 | AT11: 1.7502795 | AV11: 1.879883 | AY11: 0.30968825 | AZ11: 1.7537997
A12: 10 | B12: A_Hops | C12: 01.c | D12: 01.28 | E12: Hops | F12: tonnes | G12: 2.2808578 | H12: 3.3236086 | I12: 2.4550339 | J12: 3.0277805 | M12: 2.5018215 | N12: 4.3808676 | P12: 4.6084639 | Q12: 2.3457835 | T12: 1.8802939 | V12: 2.401673 | W12: 1.5176245 | AC12: 3.6971892 | AF12: 4.641288 | AO12: 2.845321 | AP12: 2.0513612 | AQ12: 3.0803559 | AR12: 4.2003442 | AT12: 2.8449703 | AU12: 2.5638225 | AX12: 2.9702254 | AY12: 6.5166172 | AZ12: 6.8413129 | BA12: 1.010452 | BB12: 2.6120801 | BD12: 5.0609295
A13: 11 | B13: A_Maize | C13: 01.c | D13: 01.11 | E13: Maize | F13: tonnes | G13: 0.44499803 | H13: 0.39871261 | I13: 0.50860852 | J13: 1.0445062 | K13: 1.3025598 | L13: 0.5647714 | M13: 0.71425898 | N13: 1.0637186 | P13: 0.69443414 | Q13: 0.63095436 | R13: 0.57881045 | T13: 0.28991091 | V13: 0.73727147 | X13: 0.25124159 | Z13: 0.60679881 | AA13: 0.49163581 | AB13: 1.170071 | AD13: 1.1472343 | AE13: 0.58557063 | AF13: 2.7545454 | AG13: 2.3688858 | AH13: 0.69122936 | AI13: 0.89591725 | AL13: 1.3027345 | AM13: 0.634765 | AO13: 0.72396803 | AP13: 0.63845058 | AQ13: 0.74456349 | AR13: 0.70086529 | AT13: 0.64078941 | AU13: 0.55009685 | AV13: 0.53353668 | AW13: 0.011809271 | AX13: 0.54769838 | AY13: 0.66301015 | AZ13: 0.75288081 | BA13: 0.64399872 | BB13: 0.72113396 | BC13: 0.5198617 | BD13: 0.87090244
A14: 12 | B14: A_Maizn | C14: 01.c | D14: 01.11 | E14: Maize, green | F14: tonnes | G14: 0.51243403 | H14: 0.56144915 | J14: 0.73187634 | L14: 0.75303668 | M14: 1.867575 | N14: 1.8575192 | V14: 0.54145053 | X14: 0.20510721 | Z14: 0.43187487 | AA14: 0.47900765 | AB14: 1.1984902 | AF14: 1.9193448 | AL14: 0.64024565 | AN14: 1.1762774 | AO14: 0.68701563 | AQ14: 0.95672361 | AU14: 0.55297616 | AX14: 0.507278 | AY14: 1.00273 | AZ14: 0.49643021 | BA14: 0.45367571 | BB14: 0.5495202 | BC14: 0.71866882 | BD14: 0.88841251
A15: 13 | B15: A_Millt | C15: 01.c | D15: 01.11 | E15: Millet | F15: tonnes | G15: 0.98652121 | H15: 1.9792628 | J15: 2.0157205 | M15: 2.5614814 | N15: 2.1748921 | P15: 4.3413213 | T15: 1.1842634 | V15: 1.6700558 | X15: 0.87614921 | Z15: 2.9083428 | AA15: 1.9110035 | AD15: 2.0034801 | AF15: 8.4489779 | AG15: 7.776312 | AL15: 2.9994061 | AO15: 2.2454809 | AR15: 1.6482232 | AT15: 2.8962664 | AU15: 2.1118269 | AV15: 1.2412715 | AW15: 0.015338158 | AX15: 1.0695428 | AY15: 1.5609403 | AZ15: 2.1280036 | BA15: 0.92011329 | BB15: 1.6649592 | BC15: 2.3204272 | BD15: 4.7808463
A16: 14 | B16: A_Mushs | C16: 01.c | D16: 01.13 | E16: Mushrooms and truffles | F16: tonnes | G16: 0.24783209 | H16: 0.69895078 | I16: 0.39519699 | J16: 0.30498055 | L16: 0.58867666 | M16: 0.65828128 | N16: 0.67387846 | O16: 1.4185048 | P16: 0.64090546 | Q16: 0.21205906 | R16: 0.62716685 | T16: 0.33639326 | U16: 1.827661 | V16: 0.24312877 | W16: 0.18216872 | X16: 0.36171447 | AA16: 0.222718 | AB16: 0.15901673 | AC16: 0.27359235 | AD16: 0.36382057 | AE16: 1.1882888 | AF16: 1.0031903 | AG16: 0.4838874 | AH16: 0.2264364 | AI16: 1.5011617 | AJ16: 0.20876039 | AK16: 1.9433845 | AM16: 0.68255222 | AO16: 0.40949356 | AP16: 0.68827798 | AQ16: 0.19490291 | AR16: 3.5122167 | AU16: 0.33322075 | AV16: 0.33157168 | AW16: 0.008144248 | AX16: 0.19065716 | AY16: 0.52086665 | AZ16: 0.28079595 | BA16: 0.6849349 | BC16: 1.5848043 | BD16: 0.64640004
A17: 15 | B17: A_Oatss | C17: 01.c | D17: 01.11 | E17: Oats | F17: tonnes | G17: 0.96085381 | H17: 1.5943332 | I17: 0.97337425 | J17: 1.6928572 | K17: 1.7481866 | L17: 1.1165231 | M17: 1.405244 | N17: 1.6781754 | O17: 5.8183011 | P17: 1.5596403 | Q17: 1.0720653 | R17: 0.81762992 | S17: 2.0696583 | T17: 1.4316973 | U17: 1.4359457 | V17: 1.0458681 | W17: 0.81424269 | X17: 1.0370686 | Z17: 1.446278 | AA17: 1.2858545 | AC17: 0.59251754 | AE17: 2.1359891 | AF17: 3.1489531 | AH17: 1.9035581 | AI17: 1.0782137 | AJ17: 2.5290544 | AL17: 2.5446326 | AM17: 1.0373633 | AN17: 1.0672253 | AO17: 1.8401383 | AP17: 2.7581323 | AQ17: 1.3231208 | AR17: 1.585374 | AS17: 1.0899427 | AT17: 1.5389942 | AU17: 1.636274 | AV17: 1.1400184 | AX17: 1.4530724 | AY17: 0.9814956 | AZ17: 1.8636639 | BA17: 0.59398521 | BB17: 1.1581133 | BC17: 3.7284634 | BD17: 1.6215587
A18: 16 | B18: A_Poppd | C18: 01.c | D18: 01.11 | E18: Poppy seed | F18: tonnes | G18: 4.7209697 | J18: 3.9363762 | P18: 5.2230868 | Q18: 7.0597624 | T18: 2.5019518 | V18: 4.3090725 | Z18: 3.8838064 | AA18: 3.5513765 | AM18: 4.8759873 | AQ18: 5.4298774 | AU18: 3.6371794 | AV18: 3.8430714 | AZ18: 4.0601268 | BC18: 1.0488131
A19: 17 | B19: A_Quina | C19: 01.c | D19: 01.11 | E19: Quinoa | F19: tonnes | BB19: 3.5709595
A20: 18 | B20: A_Ryee | C20: 01.c | D20: 01.11 | E20: Rye | F20: tonnes | G20: 0.76780763 | H20: 3.7112335 | I20: 1.2622164 | J20: 1.5683942 | K20: 2.8865676 | L20: 0.90338784 | M20: 1.2941089 | N20: 1.174409 | P20: 1.0591514 | Q20: 0.85342902 | R20: 0.68518205 | S20: 1.6648294 | T20: 1.3278074 | U20: 1.4232904 | V20: 1.3473251 | W20: 2.343954 | X20: 1.0258756 | Z20: 1.2385606 | AA20: 1.156921 | AC20: 1.3497808 | AE20: 1.5935075 | AG20: 5.0663692 | AH20: 1.6938246 | AI20: 1.0762495 | AJ20: 1.4341063 | AL20: 3.8006533 | AM20: 1.2677508 | AN20: 0.92481362 | AO20: 1.5134129 | AP20: 4.8212748 | AQ20: 1.159266 | AR20: 1.220755 | AS20: 0.78622919 | AT20: 1.2479528 | AU20: 1.1428017 | AV20: 0.95708275 | AX20: 1.9190777 | AY20: 1.4114616 | AZ20: 2.0404893 | BA20: 0.87539411 | BB20: 2.0032279 | BC20: 0.96258241 | BD20: 2.2884193
A21: 19 | B21: A_Sorgm | C21: 01.c | D21: 01.11 | E21: Sorghum | F21: tonnes | G21: 0.60662086 | H21: 0.97449152 | J21: 1.3612259 | K21: 2.4602849 | N21: 1.2442087 | T21: 0.76314253 | V21: 0.83432121 | X21: 0.87137743 | Z21: 2.5010815 | AA21: 0.92149909 | AD21: 3.2566168 | AE21: 0.93081489 | AG21: 5.4765329 | AL21: 1.5899838 | AQ21: 0.91496615 | AR21: 1.6451113 | AU21: 1.475055 | AV21: 0.99918419 | AW21: 0.010756127 | AX21: 1.0100739 | AY21: 1.5496188 | AZ21: 0.99947916 | BA21: 0.67949733 | BB21: 1.1024008 | BC21: 1.0145184 | BD21: 1.9088948
A22: 20 | B22: A_Trite | C22: 01.c | D22: 01.11 | E22: Triticale | F22: tonnes | G22: 0.98283601 | H22: 1.7983672 | I22: 1.1249117 | J22: 1.0861399 | K22: 1.9437693 | L22: 1.2801775 | M22: 1.3096407 | N22: 2.5031481 | P22: 1.3147799 | Q22: 0.84178535 | R22: 0.92811737 | S22: 1.5554779 | T22: 1.4433016 | V22: 1.0486494 | W22: 1.1439157 | X22: 0.96110096 | Z22: 1.1918899 | AA22: 1.043772 | AE22: 1.3424884 | AH22: 1.3214181 | AI22: 1.3999026 | AJ22: 1.8566197 | AL22: 1.6392117 | AM22: 1.3757926 | AO22: 1.479695 | AP22: 2.9508768 | AQ22: 0.8830897 | AR22: 1.0439639 | AS22: 1.0520392 | AT22: 1.2495428 | AU22: 1.124256 | AV22: 0.9591728 | AY22: 0.90403937 | AZ22: 1.9228022 | BA22: 0.34601534 | BB22: 0.69624016
A23: 21 | B23: A_Almol | C23: 01.d | D23: 01.25 | E23: Almonds, with shell | F23: tonnes | H23: 1.4014871 | J23: 4.4885108 | N23: 2.3754537 | O23: 23.984564 | T23: 7.2356956 | V23: 4.0525128 | X23: 1.0129926 | Z23: 6.4860488 | AA23: 5.8020351 | AE23: 3.1668748 | AL23: 2.5876676 | AP23: 11.02374 | AT23: 8.6085988 | AV23: 1.4653028 | AX23: 1.2765559 | AY23: 1.8597224 | AZ23: 2.5301972 | BA23: 3.2543657 | BB23: 2.0390894 | BC23: 1.6912087
A24: 22 | B24: A_Anisr | C24: 01.d | D24: 01.28 | E24: Anise, badian, fennel, coriander | F24: tonnes | H24: 6.8625532 | J24: 4.9526581 | L24: 5.0020591 | N24: 7.0385094 | R24: 8.5914327 | T24: 3.9063568 | X24: 2.2297088 | AA24: 2.5242361 | AD24: 3.2137556 | AH24: 3.7041852 | AL24: 0.71765311 | AM24: 4.0842025 | AQ24: 2.0572997 | AR24: 4.6770775 | AU24: 3.1378561 | AV24: 6.6343216 | AY24: 5.7969311 | AZ24: 4.3093128 | BA24: 1.2108951 | BB24: 3.5830762 | BC24: 2.218139
A25: 23 | B25: A_Appls | C25: 01.d | D25: 01.22 | E25: Apples | F25: tonnes | G25: 0.10521374 | H25: 0.73274228 | I25: 0.36004453 | J25: 0.49462153 | K25: 0.2723925 | L25: 0.39899317 | M25: 0.34010221 | N25: 0.64079045 | O25: 1.0839377 | P25: 0.46342656 | Q25: 0.21480538 | R25: 0.33257781 | S25: 1.7730803 | T25: 0.31787769 | U25: 0.76296509 | V25: 0.31907019 | W25: 0.26763473 | X25: 0.1895325 | Z25: 0.70418871 | AA25: 0.34988868 | AC25: 0.41058206 | AD25: 0.35663854 | AE25: 0.43942103 | AF25: 1.2684399 | AG25: 0.7502713 | AH25: 0.72667069 | AI25: 1.4946405 | AJ25: 1.2804679 | AK25: 0.82833108 | AL25: 0.67635755 | AM25: 0.66895996 | AN25: 1.058485 | AO25: 0.41611842 | AP25: 0.61288661 | AQ25: 0.42769601 | AR25: 0.49730918 | AS25: 0.40641752 | AT25: 0.43240714 | AU25: 0.46684623 | AV25: 0.40674145 | AW25: 0.01195996 | AX25: 0.34088852 | AY25: 0.56363744 | AZ25: 0.45677349 | BA25: 0.37552899 | BB25: 0.7267016 | BC25: 0.42037716 | BD25: 1.0345263
A26: 24 | B26: A_Apris | C26: 01.d | D26: 01.24 | E26: Apricots | F26: tonnes | G26: 0.86027778 | H26: 2.5317203 | J26: 0.77719932 | L26: 0.69566335 | M26: 0.61158976 | N26: 3.264977 | O26: 1.5818198 | P26: 6.3061089 | Q26: 1.1122031 | T26: 0.57401314 | V26: 0.30602464 | X26: 0.27694605 | Z26: 1.9115231 | AA26: 0.77982149 | AD26: 1.1604467 | AE26: 0.67761679 | AF26: 2.2569039 | AK26: 0.61887821 | AL26: 1.2949622 | AO26: 1.6511938 | AP26: 1.185752 | AQ26: 0.31287249 | AR26: 0.61152025 | AT26: 0.5624773 | AU26: 2.3135959 | AV26: 0.79120032 | AW26: 0.01287192 | AX26: 0.60894446 | AY26: 0.72593954 | AZ26: 0.59556168 | BA26: 0.42747163 | BB26: 0.96941423 | BC26: 0.60245541 | BD26: 1.3578906
A27: 25 | B27: A_Arecs | C27: 01.d | D27: 01.25 | E27: Areca nuts | F27: tonnes | AB27: 10.028466 | AD27: 1.7562436 | AW27: 0.01592993 | AY27: 2.8983561
A28: 26 | B28: A_Artis | C28: 01.d | D28: 01.13 | E28: Artichokes | F28: tonnes | M28: 6.8135004 | N28: 2.557272 | O28: 0.43968492 | T28: 0.29957394 | V28: 1.0287362 | X28: 0.37656684 | AE28: 0.72039633 | AH28: 0.42763218 | AK28: 0.35029665 | AL28: 0.67920971 | AQ28: 0.30699922 | AV28: 0.60377992 | AX28: 0.46716795 | AY28: 0.37325535 | BA28: 0.14236938 | BB28: 0.78175358 | BC28: 0.26685196
A29: 27 | B29: A_Aspas | C29: 01.d | D29: 01.13 | E29: Asparagus | F29: tonnes | G29: 1.7529745 | H29: 1.1271144 | I29: 0.77971551 | J29: 0.99424536 | L29: 1.0217904 | M29: 3.7672536 | N29: 1.9072446 | P29: 2.0872985 | Q29: 1.3321939 | R29: 2.5097727 | T29: 0.73576934 | U29: 9.9884098 | V29: 1.3839301 | W29: 2.642839 | X29: 0.66501349 | AA29: 1.0005048 | AE29: 0.94817498 | AF29: 2.1879735 | AH29: 0.76883313 | AL29: 0.80959283 | AM29: 1.6689279 | AO29: 0.80917114 | AT29: 1.5522767 | AU29: 1.2687256 | AV29: 1.4537214 | AW29: 0.019470391 | AX29: 1.5467269 | AY29: 0.63161828 | AZ29: 1.2833056 | BA29: 0.2731771 | BB29: 0.84940025 | BC29: 0.58908423 | BD29: 1.0603829
A30: 28 | B30: A_Avocs | C30: 01.d | D30: 01.22 | E30: Avocados | F30: tonnes | H30: 1.4175468 | K30: 0.45756791 | N30: 2.06172 | O30: 1.060977 | T30: 0.6146006 | V30: 0.78573033 | X30: 0.54201191 | AB30: 0.57523914 | AL30: 1.02052 | AV30: 1.1415041 | AX30: 1.3218736 | AY30: 0.85709621 | AZ30: 1.5083695 | BA30: 0.41463669 | BB30: 0.97116465 | BC30: 0.69674409 | BD30: 1.6371209
A31: 29 | B31: A_Bambs | C31: 01.d | D31: 01.25 | E31: Bambara beans | F31: tonnes | BA31: 1.0026368
A32: 30 | B32: A_Banas | C32: 01.d | D32: 01.22 | E32: Bananas | F32: tonnes | H32: 0.66748959 | K32: 0.4942036 | N32: 0.73994839 | O32: 0.75600757 | T32: 0.26087235 | X32: 0.19889412 | AB32: 0.17522361 | AD32: 0.21953292 | AE32: 0.55554385 | AF32: 2.7955897 | AL32: 0.47142492 | AP32: 0.52781481 | AV32: 0.308418 | AW32: 0.014595514 | AX32: 0.6163705 | AY32: 0.34279993 | BA32: 0.35687435 | BB32: 0.42220557 | BC32: 0.41460094 | BD32: 1.0220347
A33: 31 | B33: A_Beann | C33: 01.d | D33: 01.25 | E33: Beans, green | F33: tonnes | G33: 0.29413745 | H33: 0.97166425 | I33: 0.5122089 | J33: 0.40216524 | L33: 0.5977879 | M33: 0.6614645 | N33: 0.27987276 | O33: 0.23676571 | P33: 1.9135718 | Q33: 0.40276295 | T33: 0.2391732 | U33: 1.8916992 | V33: 1.116575 | W33: 0.55933738 | X33: 0.35162551 | Z33: 1.0838057 | AA33: 0.30938892 | AB33: 0.59894554 | AC33: 0.71519664 | AD33: 0.88809388 | AE33: 0.52866883 | AH33: 0.99720969 | AI33: 2.6447731 | AL33: 0.40670928 | AM33: 0.98594025 | AN33: 0.9107746 | AO33: 0.34094271 | AP33: 0.51468701 | AQ33: 0.44915119 | AT33: 0.73466477 | AU33: 5.4371664 | AV33: 0.24215576 | AW33: 0.014803221 | AX33: 1.3296093 | AY33: 0.2953289 | AZ33: 1.6887253 | BA33: 0.13087105 | BB33: 0.96960255 | BC33: 0.29959441 | BD33: 1.0769279
A34: 32 | B34: A_Beany | C34: 01.d | D34: 01.25 | E34: Beans, dry | F34: tonnes | H34: 3.7970497 | I34: 1.4008768 | J34: 2.424865 | K34: 3.3127233 | L34: 2.0010848 | N34: 1.9427868 | O34: 1.6535701 | S34: 1.4936347 | T34: 2.0172167 | V34: 3.5000421 | X34: 1.3037065 | Z34: 3.9612014 | AA34: 1.7515279 | AB34: 3.7059512 | AD34: 5.0317338 | AE34: 2.5336898 | AF34: 3.9067863 | AG34: 4.0423458 | AH34: 1.1335493 | AJ34: 1.4629383 | AK34: 1.04559 | AL34: 4.3585647 | AM34: 1.6541194 | AO34: 1.7926337 | AP34: 4.883273 | AQ34: 2.0523072 | AR34: 1.3209164 | AT34: 2.4861178 | AU34: 1.9931612 | AV34: 1.0125904 | AW34: 0.11117788 | AX34: 2.2786509 | AY34: 0.73876917 | AZ34: 1.658774 | BA34: 0.63636175 | BB34: 3.1869649 | BC34: 0.88455064 | BD34: 3.1683083
A35: 33 | B35: A_Berrs | C35: 01.d | D35: 01.25 | E35: Berries nes | F35: tonnes | G35: 0.99421916 | H35: 1.6286171 | I35: 1.2697385 | J35: 3.3861357 | M35: 1.4136058 | N35: 1.3001406 | P35: 2.6519918 | Q35: 1.90605 | S35: 10.25015 | T35: 0.60078034 | U35: 5.3163685 | W35: 0.54265398 | X35: 0.86864404 | Z35: 5.0667859 | AC35: 1.5577426 | AD35: 0.56285724 | AE35: 0.90701933 | AH35: 3.9218419 | AJ35: 4.3616093 | AK35: 1.183854 | AL35: 0.54827465 | AM35: 1.5225477 | AN35: 2.1494696 | AO35: 1.2382582 | AP35: 0.47723374 | AQ35: 0.44834676 | AR35: 0.75123926 | AS35: 4.517985 | AT35: 1.253472 | AU35: 0.58869863 | AV35: 0.76977514 | AX35: 0.73632476 | AY35: 0.73934301 | AZ35: 1.6297755 | BA35: 0.51835355 | BB35: 2.176964 | BC35: 0.95769812 | BD35: 1.5873471
A36: 34 | B36: A_Blues | C36: 01.d | D36: 01.25 | E36: Blueberries | F36: tonnes | H36: 1.2134059 | J36: 0.61896826 | L36: 0.82552157 | M36: 1.2829942 | Q36: 1.5466234 | R36: 7.1075523 | T36: 0.45525162 | V36: 1.8082176 | AE36: 0.84127717 | AH36: 2.8788175 | AJ36: 3.1910373 | AL36: 0.70736733 | AM36: 2.7583851 | AN36: 9.2026448 | AO36: 2.1298812 | AP36: 0.76502722 | AQ36: 1.1833274 | AR36: 0.57378541 | AS36: 1.7679426 | AX36: 0.77354092 | AY36: 1.934143 | AZ36: 1.2654139 | BA36: 0.87727354 | BB36: 0.93777848
A37: 35 | B37: A_Brazl | C37: 01.d | D37: 01.25 | E37: Brazil nuts, with shell | F37: tonnes | K37: 0.24929691 | BB37: 1.7652138
A38: 36 | B38: A_Broay | C38: 01.d | D38: 01.25 | E38: Broad beans, horse beans, dry | F38: tonnes | G38: 1.3684187 | H38: 2.555036 | I38: 0.85819434 | J38: 1.7450466 | K38: 17.449567 | M38: 1.4460928 | N38: 2.2332532 | O38: 1.3617646 | P38: 2.3829769 | Q38: 0.82179475 | T38: 2.5570139 | V38: 2.6640964 | W38: 0.7518969 | X38: 1.23838 | AA38: 1.3060092 | AC38: 0.12460846 | AE38: 2.1978175 | AF38: 3.8932369 | AI38: 2.4647179 | AK38: 0.92999734 | AL38: 1.9930799 | AM38: 1.2577049 | AO38: 1.875876 | AP38: 0.65522755 | AR38: 1.79489 | AS38: 0.84284627 | AT38: 1.1537723 | AU38: 2.5806124 | AV38: 0.94547804 | AY38: 0.54988678 | AZ38: 1.3641048 | BA38: 0.44951768 | BB38: 1.7858033 | BC38: 0.82083633
A39: 37 | B39: A_Cabbs | C39: 01.d | D39: 01.13 | E39: Cabbages and other brassicas | F39: tonnes | G39: 0.12170342 | H39: 0.39401449 | I39: 0.2892412 | J39: 0.24007122 | L39: 0.27915216 | M39: 0.39525684 | N39: 0.32980723 | O39: 0.18594289 | P39: 0.20940701 | Q39: 0.12849469 | R39: 0.16299727 | S39: 0.16324528 | T39: 0.13538757 | U39: 0.22263202 | V39: 0.26870801 | W39: 0.25106063 | X39: 0.15699634 | Z39: 0.23595323 | AA39: 0.20305945 | AB39: 0.30409136 | AC39: 0.24401994 | AD39: 0.14508583 | AE39: 0.36178881 | AF39: 0.55273365 | AG39: 0.28670681 | AH39: 0.16733797 | AI39: 0.5191407 | AJ39: 0.18703348 | AK39: 0.22856737 | AL39: 0.28636224 | AM39: 0.29434446 | AN39: 0.69436713 | AO39: 0.14412946 | AP39: 0.31544658 | AQ39: 0.17330232 | AR39: 0.17990621 | AS39: 0.20724159 | AT39: 0.23386953 | AU39: 0.11769874 | AV39: 0.21472488 | AW39: 0.01188246 | AX39: 0.25367081 | AY39: 0.16948581 | AZ39: 0.18549107 | BA39: 0.13177006 | BB39: 0.75271314 | BC39: 0.18200372 | BD39: 0.17264258
A40: 38 | B40: A_Carrs | C40: 01.d | D40: 01.13 | E40: Carrots and turnips | F40: tonnes | G40: 0.12707717 | H40: 0.38232305 | I40: 0.17668745 | J40: 0.16476763 | L40: 0.26238233 | M40: 0.37700048 | N40: 0.21728181 | O40: 0.24056147 | P40: 0.24831581 | Q40: 0.13072543 | R40: 0.18417554 | S40: 0.17895294 | T40: 0.093525496 | U40: 0.26210329 | V40: 0.1816563 | W40: 0.15762645 | X40: 0.15473326 | Z40: 0.2683751 | AA40: 0.13437836 | AB40: 0.37885693 | AC40: 0.16919302 | AD40: 0.21739613 | AE40: 0.23294146 | AF40: 0.60642149 | AG40: 0.41714927 | AH40: 0.21148543 | AI40: 0.77192224 | AJ40: 0.22685608 | AK40: 0.16929677 | AL40: 0.31675174 | AM40: 0.26207269 | AN40: 0.66801104 | AO40: 0.15906778 | AP40: 0.25318192 | AQ40: 0.263091 | AR40: 0.19505939 | AS40: 0.16131609 | AT40: 0.33820589 | AU40: 0.14973086 | AV40: 0.087804958 | AW40: 0.011588648 | AX40: 0.29960779 | AY40: 0.098470535 | AZ40: 0.20329464 | BA40: 0.10230076 | BB40: 0.39411094 | BC40: 0.17164671 | BD40: 0.32277431
A41: 39 | B41: A_Cashe | C41: 01.d | D41: 01.22 | E41: Cashewapple | F41: tonnes | K41: 2.0349691 | BA41: 0.7351175 | BB41: 0.98469586
A42: 40 | B42: A_Cashl | C42: 01.d | D42: 01.25 | E42: Cashew nuts, with shell | F42: tonnes | K42: 28.14421 | N42: 5.1520269 | AB42: 16.380091 | AD42: 3.3512558 | AL42: 1.6517833 | AY42: 1.7081782 | BA42: 3.6344458 | BB42: 6.024475
A43: 41 | B43: A_Cassa | C43: 01.d | D43: 01.13 | E43: Cassava | F43: tonnes | K43: 0.31766409 | N43: 0.51250279 | AB43: 0.25036419 | AD43: 0.20290573 | AL43: 0.49618094 | AW43: 0.011243012 | AY43: 0.14926259 | BA43: 0.18589872 | BB43: 0.46635223
A44: 42 | B44: A_Cauli | C44: 01.d | D44: 01.13 | E44: Cauliflowers and broccoli | F44: tonnes | G44: 0.25960793 | H44: 0.58913974 | I44: 0.36998917 | J44: 0.42126731 | L44: 0.38516872 | M44: 0.74980315 | N44: 0.55798616 | O44: 0.33724039 | P44: 0.64086475 | Q44: 0.27105974 | R44: 0.64103004 | S44: 0.41009645 | T44: 0.20394979 | U44: 0.75443482 | V44: 0.35960596 | W44: 0.63094499 | X44: 0.22622914 | Z44: 0.45297827 | AA44: 0.23499697 | AB44: 0.5256504 | AC44: 0.4879098 | AD44: 0.16480162 | AE44: 0.31535938 | AF44: 1.0608382 | AG44: 1.0271873 | AH44: 0.63713722 | AI44: 4.044222 | AJ44: 0.8750235 | AK44: 0.18676837 | AL44: 0.46468377 | AM44: 0.72150738 | AN44: 0.88755643 | AO44: 0.25818224 | AP44: 0.48532617 | AQ44: 0.26784207 | AR44: 0.47471999 | AS44: 0.5983929 | AT44: 0.45134599 | AU44: 0.35335811 | AV44: 0.27216848 | AW44: 0.013759293 | AX44: 0.40991405 | AY44: 0.20596502 | AZ44: 0.35254046 | BA44: 0.087451575 | BB44: 0.91747746 | BC44: 0.20441774 | BD44: 1.02279
A45: 43 | B45: A_Cherr | C45: 01.d | D45: 01.24 | E45: Cherries, sour | F45: tonnes | G45: 1.0485474 | J45: 1.4200211 | L45: 0.78996397 | P45: 1.0334004 | Q45: 0.74588247 | R45: 1.0543382 | T45: 0.96194061 | X45: 0.39742886 | Z45: 1.3465437 | AA45: 0.69214438 | AE45: 1.3866467 | AO45: 0.80013868 | AP45: 1.8290715 | AR45: 0.6382168 | AS45: 0.81733613 | AT45: 1.0834388 | AU45: 2.0458024 | AV45: 0.60852763 | AX45: 0.70798148 | AY45: 0.70762503 | AZ45: 0.73842923 | BB45: 1.5669183 | BC45: 0.65354665
A46: 44 | B46: A_Chers | C46: 01.d | D46: 01.24 | E46: Cherries | F46: tonnes | G46: 1.1731241 | H46: 1.3047067 | I46: 1.2523976 | J46: 1.0170898 | L46: 0.71963599 | M46: 0.76132035 | N46: 3.1555181 | O46: 2.7190168 | P46: 2.0512495 | Q46: 0.9840715 | R46: 1.6595169 | S46: 7.0215059 | T46: 0.93482184 | V46: 1.2303 | W46: 1.7361965 | X46: 0.60529625 | Z46: 2.8906628 | AA46: 0.86593697 | AD46: 0.79969589 | AE46: 1.7857057 | AF46: 3.6016816 | AH46: 2.8011708 | AI46: 3.0524527 | AJ46: 6.4994048 | AL46: 1.7326219 | AM46: 10.203328 | AN46: 2.1017999 | AO46: 1.0122475 | AP46: 1.9479737 | AQ46: 0.36268679 | AR46: 0.74728278 | AT46: 0.58251374 | AU46: 0.96064859 | AV46: 0.73058127 | AX46: 0.78937094 | AY46: 0.76953858 | AZ46: 1.0529417 | BA46: 1.130754 | BB46: 1.4546412 | BC46: 0.7644837 | BD46: 3.077974
A47: 45 | B47: A_Chest | C47: 01.d | D47: 01.25 | E47: Chestnut | F47: tonnes | J47: 1.2662175 | M47: 0.35488372 | N47: 1.6671137 | T47: 5.6905381 | V47: 4.0241444 | X47: 0.84518223 | AA47: 5.5752265 | AE47: 2.2384425 | AF47: 5.5086179 | AG47: 3.1753396 | AP47: 4.6880587 | AQ47: 0.63951785 | AT47: 1.1047405 | AU47: 9.5366027 | AV47: 2.1388634 | AY47: 1.941265 | AZ47: 2.407691 | BA47: 1.2790799 | BB47: 2.6298144
A48: 46 | B48: A_Chick | C48: 01.d | D48: 01.11 | E48: Chick peas | F48: tonnes | H48: 2.8835099 | J48: 1.9772192 | L48: 2.0549718 | N48: 0.70307793 | O48: 2.3311417 | T48: 2.3984229 | X48: 1.5395272 | AA48: 1.2978045 | AD48: 2.4382058 | AE48: 2.2560125 | AL48: 1.5886969 | AP48: 3.5614053 | AQ48: 1.7675799 | AR48: 2.1598075 | AU48: 4.0830797 | AV48: 1.7627393 | AX48: 2.3518834 | AY48: 1.1114761 | AZ48: 1.149175 | BA48: 0.50297203 | BB48: 1.8633117 | BC48: 1.9325835
A49: 47 | B49: A_Chics | C49: 01.d | D49: 01.13 | E49: Chicory roots | F49: tonnes | I49: 0.34316684 | T49: 0.28826415 | V49: 0.28249704 | Z49: 0.41628104 | AM49: 0.86540732 | AO49: 0.39372621 | AU49: 0.54707844 | AY49: 0.25930556 | AZ49: 0.3131873 | BA49: 0.058423281 | BB49: 0.60461389 | BC49: 0.34304067 | BD49: 1.1207936
A50: 48 | B50: A_Clovs | C50: 01.d | D50: 01.28 | E50: Cloves | F50: tonnes | N50: 7.9811196 | AB50: 23.707399 | AY50: 3.5842682 | BA50: 6.6984856 | BB50: 0.65710209
A51: 49 | B51: A_Cocon | C51: 01.d | D51: 01.26 | E51: Coconuts | F51: tonnes | K51: 0.44952998 | N51: 0.84236804 | V51: 0.88576504 | AB51: 0.7977054 | AD51: 0.47251886 | AL51: 1.1996066 | AW51: 0.011337473 | AY51: 0.6805843 | BA51: 0.89595888 | BB51: 1.0146875
A52: 50 | B52: A_Cowpea | C52: 01.d | D52: 01.11 | E52: Cow peas, dry | F52: tonnes | N52: 5.1693766 | O52: 2.4928572 | Z52: 1.384697 | AA52: 1.5857676 | AX52: 2.5268011 | AY52: 0.83293004 | AZ52: 1.1255307 | BA52: 1.3195609 | BB52: 2.5462608 | BC52: 0.80104872 | BD52: 5.901631
A53: 51 | B53: A_Crans | C53: 01.d | D53: 01.25 | E53: Cranberries | F53: tonnes | J53: 3.4100967 | L53: 0.38883052 | AJ53: 2.327656 | AQ53: 0.47626106 | AV53: 0.24179276 | AX53: 0.38239598 | AY53: 1.2889508 | AZ53: 1.0746842 | BA53: 0.75551967
A54: 52 | B54: A_Cucus | C54: 01.d | D54: 01.13 | E54: Cucumbers and gherkins | F54: tonnes | G54: 0.12433086 | H54: 0.52161438 | I54: 0.13196604 | J54: 0.16485341 | L54: 0.30548024 | M54: 0.32627826 | N54: 0.42677701 | O54: 0.26097085 | P54: 0.38808023 | Q54: 0.16974185 | R54: 0.30253825 | S54: 0.19847144 | T54: 0.097282632 | U54: 0.29858483 | V54: 0.24820815 | W54: 0.16831818 | X54: 0.12275676 | Z54: 0.28028943 | AA54: 0.12854699 | AB54: 0.60796366 | AC54: 0.31227659 | AD54: 0.42640671 | AE54: 0.27428514 | AF54: 0.76372522 | AG54: 0.56123961 | AH54: 0.31703454 | AI54: 0.75005166 | AJ54: 0.16648049 | AK54: 0.13767223 | AL54: 0.31864849 | AM54: 0.35542869 | AN54: 0.61227114 | AO54: 0.17689476 | AP54: 0.30998933 | AQ54: 0.23268098 | AR54: 0.22411957 | AS54: 0.25537074 | AT54: 0.30991094 | AU54: 0.13057377 | AV54: 0.22794595 | AW54: 0.011952073 | AX54: 0.43057379 | AY54: 0.20968855 | AZ54: 0.23619154 | BA54: 0.49101733 | BB54: 0.89264048 | BC54: 0.21239607 | BD54: 0.96942968
A55: 53 | B55: A_Currs | C55: 01.d | D55: 01.25 | E55: Currants | F55: tonnes | G55: 0.73324185 | H55: 0.95084991 | I55: 0.6243069 | J55: 0.07006041 | M55: 0.66676518 | P55: 2.1833866 | Q55: 0.89985248 | R55: 0.61890431 | S55: 4.8605905 | T55: 0.53105124 | U55: 5.1504464 | V55: 0.58012773 | W55: 0.86153949 | AA55: 0.92837771 | AC55: 0.94297158 | AE55: 1.2764135 | AF55: 3.9752603 | AJ55: 5.2300207 | AM55: 3.1964498 | AN55: 2.0628278 | AO55: 1.201959 | AQ55: 3.0020486 | AR55: 0.54783192 | AS55: 4.4998007 | AT55: 2.3500443 | AU55: 13.477847 | AY55: 0.75386912 | AZ55: 0.75278049 | BB55: 1.5544498
A56: 54 | B56: A_Dates | C56: 01.d | D56: 01.22 | E56: Dates | F56: tonnes | N56: 1.5723495 | T56: 1.0226657 | AL56: 1.1802482 | AV56: 0.49139537 | AX56: 0.98335807 | AY56: 0.93386376 | AZ56: 0.39702456 | BA56: 0.69671211 | BB56: 1.9903162 | BC56: 0.62339455
A57: 55 | B57: A_Eggpl | C57: 01.d | D57: 01.13 | E57: Eggplants (aubergines) | F57: tonnes | G57: 0.26046509 | I57: 0.38188686 | J57: 0.29941328 | N57: 0.67888012 | O57: 0.75729998 | T57: 0.25303001 | V57: 0.37361308 | X57: 0.20120332 | AA57: 0.33589399 | AB57: 0.5697976 | AD57: 0.27291382 | AE57: 0.56836231 | AF57: 1.4122995 | AG57: 0.94634571 | AH57: 1.8426594 | AK57: 0.37300152 | AL57: 0.43975285 | AM57: 0.71504076 | AP57: 0.55430758 | AQ57: 0.30356493 | AV57: 0.41084165 | AW57: 0.011975953 | AX57: 0.44015774 | AY57: 0.30661347 | AZ57: 0.3398476 | BA57: 0.19121176 | BB57: 0.93329911 | BC57: 0.31069178
A58: 56 | B58: A_Figss | C58: 01.d | D58: 01.22 | E58: Figs | F58: tonnes | H58: 3.0779316 | K58: 0.86418395 | N58: 3.3050052 | O58: 0.80072464 | T58: 0.90724133 | V58: 0.72086618 | X58: 0.61976857 | Z58: 1.5163673 | AD58: 1.7385633 | AE58: 1.1216964 | AF58: 1.4751501 | AK58: 1.2140102 | AL58: 1.270369 | AP58: 4.435265 | AT58: 1.0810902 | AV58: 0.79591887 | AX58: 0.63364913 | AY58: 0.724999 | AZ58: 0.6529924 | BA58: 1.2593906 | BB58: 1.1734382 | BC58: 0.65229684 | BD58: 2.1169763
A59: 57 | B59: A_frtrop_nes | C59: 01.d | D59: 01.22 | E59: Fruit, tropical fresh nes | F59: tonnes | H59: 1.2088507 | K59: 0.40946974 | N59: 2.8835376 | O59: 1.3122082 | T59: 0.43570115 | AB59: 0.59744522 | AD59: 0.28001195 | AL59: 0.79626283 | AW59: 0.014371792 | AY59: 0.80852497 | BA59: 0.63190567 | BB59: 0.64061548 | BC59: 0.51979234
A60: 58 | B60: A_Gooss | C60: 01.d | D60: 01.25 | E60: Gooseberries | F60: tonnes | G60: 1.091926 | I60: 0.9227211 | M60: 0.67957652 | P60: 2.6194128 | Q60: 0.88079059 | S60: 4.3018679 | T60: 2.6541646 | U60: 1.8005384 | W60: 0.45998203 | AA60: 0.91908399 | AJ60: 4.013704 | AO60: 0.93506949 | AR60: 0.77229832 | AY60: 0.73231597 | AZ60: 0.42118925
A61: 59 | B61: A_Grapf | C61: 01.d | D61: 01.21 | E61: Grapefruit (inc. pomelos) | F61: tonnes | H61: 0.88330915 | K61: 0.33571019 | N61: 0.53388579 | O61: 0.68986033 | T61: 0.23403283 | V61: 0.35756913 | X61: 0.16800445 | AD61: 0.21211704 | AE61: 0.57090562 | AK61: 0.66294061 | AL61: 0.39690231 | AP61: 0.67838135 | AV61: 0.26217216 | AW61: 0.013987255 | AX61: 0.430271 | AY61: 0.46248135 | BA61: 0.26085666 | BB61: 0.52697384 | BC61: 0.32821581 | BD61: 0.61628097
A62: 60 | B62: A_Graps | C62: 01.d | D62: 01.21 | E62: Grapes | F62: tonnes | G62: 0.87154513 | H62: 0.75422621 | I62: 0.78810932 | J62: 0.82076412 | K62: 0.52138331 | L62: 0.66192293 | M62: 0.75986387 | N62: 1.0134493 | O62: 1.8169143 | P62: 1.1895267 | Q62: 0.53645468 | T62: 0.58593115 | V62: 0.67746732 | W62: 2.7023653 | X62: 0.35265994 | Z62: 0.97925482 | AA62: 0.64460167 | AD62: 0.37073457 | AE62: 0.71650033 | AF62: 1.6379319 | AG62: 0.8675153 | AI62: 1.6995256 | AK62: 1.603555 | AL62: 0.68719982 | AM62: 1.7065881 | AP62: 1.1607763 | AQ62: 0.70133555 | AR62: 0.49169196 | AT62: 0.93841438 | AU62: 0.86033816 | AV62: 0.57745878 | AW62: 0.021525051 | AX62: 0.49660324 | AY62: 0.5526181 | AZ62: 0.57738212 | BA62: 0.39918718 | BB62: 1.0063626 | BC62: 0.43990684 | BD62: 1.1683508
A63: 61 | B63: A_Hazel | C63: 01.d | D63: 01.25 | E63: Hazelnuts, with shell | F63: tonnes | J63: 8.9415325 | N63: 3.1882999 | O63: 4.6804188 | R63: 3.4055634 | T63: 3.7043561 | V63: 2.0732697 | X63: 1.5421277 | Z63: 9.2014372 | AA63: 5.4571131 | AE63: 2.7522429 | AO63: 3.0777036 | AP63: 4.291192 | AQ63: 2.7828651 | AT63: 2.5748263 | AV63: 5.0948336 | AX63: 1.6580179 | AY63: 3.3025905 | AZ63: 2.8684976 | BA63: 2.0071162 | BB63: 5.6634319 | BC63: 2.4397721
A64: 62 | B64: A_Jute | C64: 01.d | D64: 01.16 | E64: Jute | F64: tonnes | K64: 6.4058458 | N64: 3.4352746 | AD64: 1.1197091 | AY64: 0.63131184 | BA64: 0.57597255 | BB64: 1.8627756 | BC64: 1.0628849
A65: 63 | B65: A_Kapot | C65: 01.d | D65: 01.29 | E65: Kapok fruit | F65: tonnes | AB65: 5.6842987 | AY65: 1.076118
A66: 64 | B66: A_Kiwi | C66: 01.d | D66: 01.25 | E66: Kiwi fruit | F66: tonnes | H66: 0.75211694 | J66: 0.664413 | L66: 0.72712191 | M66: 0.48589742 | N66: 1.2480019 | O66: 0.84471474 | T66: 0.43292145 | V66: 0.46379149 | X66: 0.18506368 | AE66: 0.55597765 | AF66: 1.7316928 | AG66: 1.073524 | AP66: 0.83447627 | AT66: 0.44948221 | AV66: 0.43069646 | AX66: 0.52543065 | AY66: 0.323511 | AZ66: 0.40187852 | BA66: 0.79305358 | BB66: 0.79431173 | BC66: 0.3250773
A67: 65 | B67: A_Kola | C67: 01.d | D67: 01.29 | E67: Kola nuts | F67: tonnes | BA67: 4.1180758
A68: 66 | B68: A_Leeks | C68: 01.d | D68: 01.13 | E68: Leeks, other alliaceous vegetables | F68: tonnes | G68: 0.40056642 | I68: 0.48166324 | L68: 0.63167566 | M68: 0.83738406 | N68: 1.0536575 | O68: 1.4339656 | Q68: 0.3516325 | R68: 0.5815981 | T68: 0.37422688 | U68: 0.56550345 | V68: 0.48795031 | W68: 0.57962066 | X68: 0.30694374 | Z68: 0.6625326 | AA68: 0.52858247 | AB68: 0.76723768 | AC68: 0.66077562 | AE68: 0.70591624 | AG68: 1.1323289 | AH68: 0.79335486 | AI68: 1.229737 | AJ68: 0.68889645 | AK68: 0.53870208 | AL68: 0.78810261 | AM68: 0.84337325 | AN68: 0.93513095 | AO68: 0.67645315 | AQ68: 0.36542451 | AS68: 0.59307138 | AT68: 0.6755469 | AU68: 0.99174121 | AV68: 0.53935589 | AW68: 0.096418659 | AY68: 0.45416717 | AZ68: 0.54513642 | BA68: 1.3563792 | BB68: 0.47132767 | BC68: 0.53291292
A69: 67 | B69: A_Lemos | C69: 01.d | D69: 01.13 | E69: Lemons and limes | F69: tonnes | H69: 0.65776316 | K69: 0.29947384 | N69: 0.88166029 | O69: 0.82481914 | T69: 0.30559271 | V69: 0.56725263 | X69: 0.24760869 | Z69: 0.740906 | AD69: 0.34866102 | AE69: 0.5418756 | AF69: 1.2773863 | AK69: 0.4414237 | AL69: 0.60853163 | AP69: 0.61707189 | AV69: 0.31826216 | AW69: 0.0128696 | AX69: 0.36490587 | AY69: 0.73064406 | AZ69: 0.78926538 | BA69: 0.35286264 | BB69: 0.45671832 | BC69: 0.47023358 | BD69: 1.1079873
A70: 68 | B70: A_Lents | C70: 01.d | D70: 01.11 | E70: Lentils | F70: tonnes | H70: 3.9217486 | J70: 1.6548338 | L70: 2.8386523 | N70: 1.4756301 | O70: 5.2332767 | T70: 2.764876 | V70: 4.8207018 | X70: 1.8069999 | Z70: 2.0290998 | AA70: 3.8868822 | AD70: 2.7095845 | AE70: 4.2396505 | AL70: 3.944446 | AR70: 2.0898038 | AU70: 4.6656004 | AV70: 1.5981738 | AX70: 2.8629343 | AY70: 0.78799601 | AZ70: 1.6577894 | BA70: 0.68040566 | BB70: 3.0006069 | BC70: 1.9342862
A71: 69 | B71: A_Letty | C71: 01.d | D71: 01.13 | E71: Lettuce and chicory | F71: tonnes | G71: 0.31167065 | H71: 0.90433518 | I71: 0.35222686 | J71: 0.38830645 | L71: 0.46698717 | M71: 0.51301472 | N71: 0.74928527 | O71: 0.90907392 | P71: 0.84022059 | Q71: 0.35916062 | R71: 0.37561308 | T71: 0.27909675 | U71: 1.1890282 | V71: 0.40746525 | W71: 0.4592871 | X71: 0.24288722 | Z71: 0.50099683 | AA71: 0.29890512 | AC71: 0.39295781 | AD71: 0.47272942 | AE71: 0.56800101 | AF71: 1.2982708 | AG71: 0.86283212 | AI71: 1.1950655 | AJ71: 0.30549602 | AK71: 0.39548993 | AL71: 0.56414323 | AM71: 0.99241453 | AN71: 0.95665992 | AO71: 0.5324285 | AP71: 0.55639266 | AQ71: 0.33096734 | AS71: 0.61056287 | AT71: 0.53817071 | AU71: 0.33724468 | AV71: 0.40205897 | AX71: 0.39508635 | AY71: 0.36642985 | AZ71: 0.57315725 | BA71: 0.12034991 | BB71: 0.85545909 | BC71: 0.34699946 | BD71: 0.78312126
A72: 70 | B72: A_Lupis | C72: 01.d | D72: 01.11 | E72: Lupins | F72: tonnes | G72: 1.578524 | H72: 2.5594676 | M72: 1.7798024 | Q72: 1.9566925 | T72: 2.6178662 | V72: 2.8875405 | X72: 1.2412691 | AA72: 2.0027718 | AE72: 2.7141527 | AH72: 3.0390947 | AJ72: 2.6391287 | AO72: 2.2357365 | AP72: 4.7087217 | AR72: 1.6334872 | AU72: 1.7276427 | AZ72: 2.3867852 | BA72: 0.69602445 | BB72: 1.9518057 | BC72: 1.3699974 | BD72: 1.9878095
A73: 71 | B73: A_Mangs | C73: 01.d | D73: 01.22 | E73: Mangoes, mangosteens, guavas | F73: tonnes | H73: 1.4558474 | K73: 0.3925915 | N73: 2.1201425 | AB73: 0.5288561 | AD73: 0.45080939 | AF73: 3.5577293 | AL73: 0.69241432 | AW73: 0.024454615 | AX73: 0.45827651 | AY73: 0.53470563 | BA73: 0.34085922 | BB73: 0.95944772 | BC73: 0.42861824 | BD73: 1.1332732
A74: 72 | B74: A_Mate | C74: 01.d | D74: 01.29 | E74: Mate | F74: tonnes | K74: 0.50923488 | BB74: 0.48148772
A75: 73 | B75: A_Melon | C75: 01.d | D75: 01.13 | E75: Melons, other (inc.cantaloupes) | F75: tonnes | H75: 0.52097602 | K75: 0.26738308 | L75: 0.35699635 | N75: 0.70326908 | O75: 0.67376468 | T75: 0.25215252 | V75: 0.41884715 | X75: 0.19320032 | AA75: 0.2727506 | AB75: 0.38567183 | AD75: 0.25286028 | AE75: 0.47807419 | AF75: 1.401145 | AG75: 0.7110801 | AK75: 0.38010441 | AL75: 0.41767433 | AM75: 0.81861348 | AP75: 0.58856816 | AQ75: 0.29244943 | AU75: 0.41140343 | AV75: 0.32979091 | AW75: 0.016049208 | AX75: 0.34397352 | AY75: 0.24346487 | AZ75: 0.5070934 | BA75: 0.10084165 | BB75: 0.71293973 | BC75: 0.29379733 | BD75: 1.2741955
A76: 74 | B76: A_Nutss | C76: 01.d | D76: 01.25 | E76: Nuts nes | F76: tonnes | H76: 2.2670421 | J76: 3.2536209 | K76: 5.148663 | N76: 1.8676979 | T76: 1.4052026 | AB76: 8.5599861 | AE76: 1.479873 | AG76: 2.4042249 | AL76: 1.820968 | AR76: 1.1077724 | AT76: 1.5933937 | AV76: 1.4120987 | AX76: 3.9394339 | AY76: 2.4030217 | AZ76: 0.72875709 | BA76: 1.6656944 | BB76: 1.4987649 | BC76: 1.4970748 | BD76: 1.6126541
A77: 75 | B77: A_oFru_cit | C77: 01.d | D77: 01.23 | E77: Fruit, citrus nes | F77: tonnes | H77: 0.72872498 | N77: 0.50677041 | O77: 0.91275525 | T77: 1.3992089 | X77: 0.43735276 | AD77: 0.30842925 | AE77: 0.47653565 | AF77: 1.2641437 | AG77: 2.1043936 | AK77: 0.54299299 | AL77: 1.3823197 | AV77: 0.4888984 | AW77: 0.011946043 | AX77: 0.48264966 | AY77: 0.79091909 | AZ77: 0.32564484 | BA77: 0.61370092 | BB77: 0.90491489 | BC77: 0.39771807 | BD77: 1.0228255
A78: 76 | B78: A_oFru_fresh | C78: 01.d | D78: 01.29 | E78: Fruit, fresh nes | F78: tonnes | J78: 2.67729 | M78: 0.40613194 | N78: 2.9492681 | O78: 1.311165 | P78: 1.3119296 | T78: 0.49851931 | V78: 0.59100476 | X78: 0.6740063 | AA78: 1.3946085 | AB78: 0.55518375 | AC78: 0.61163773 | AD78: 0.50517445 | AE78: 1.3200558 | AG78: 2.3819126 | AJ78: 7.622687 | AK78: 0.72909418 | AL78: 1.0398769 | AO78: 1.0032777 | AP78: 0.76361748 | AQ78: 0.26976171 | AR78: 2.4607333 | AU78: 1.3975592 | AV78: 0.42553383 | AW78: 0.016035571 | AX78: 0.40776018 | AY78: 0.70953253 | AZ78: 0.49408601 | BA78: 0.4843589 | BB78: 0.98429736 | BC78: 0.80650064 | BD78: 1.3504488
A79: 77 | B79: A_oFru_pom | C79: 01.d | D79: 01.24 | E79: Fruit, pome nes | F79: tonnes | AY79: 1.4825742 | AZ79: 1.3434119
A80: 78 | B80: A_oFru_ston | C80: 01.d | D80: 01.24 | E80: Fruit, stone nes | F80: tonnes | N80: 2.0888127 | Q80: 0.55251437 | U80: 2.6102498 | V80: 0.87609281 | X80: 1.0516826 | AA80: 0.91078528 | AD80: 1.1812669 | AE80: 0.78548787 | AF80: 5.9655372 | AK80: 1.1112922 | AO80: 1.8569279 | AP80: 1.6260101 | AV80: 1.0784227 | AY80: 1.1036858 | AZ80: 0.79393368 | BA80: 0.56295537 | BC80: 0.95773096
A81: 79 | B81: A_Okraa | C81: 01.d | D81: 01.13 | E81: Okra | F81: tonnes | O81: 0.89703865 | AD81: 0.33448679 | AL81: 0.91168249 | AV81: 1.1823575 | AX81: 0.8432516 | AY81: 0.31926912 | AZ81: 0.61294875 | BA81: 0.63930394 | BB81: 0.93300068 | BC81: 0.66354845
A82: 80 | B82: A_Olivs | C82: 01.d | D82: 01.26 | E82: Olives | F82: tonnes | H82: 1.7827408 | K82: 4.0627846 | O82: 3.2038833 | T82: 1.0038969 | V82: 3.4736971 | X82: 0.90424973 | Z82: 2.1818795 | AE82: 2.3439887 | AK82: 2.2251825 | AL82: 0.92246669 | AP82: 2.4706291 | AT82: 3.0988721 | AV82: 1.3382125 | AW82: 0.1785167 | AX82: 0.70564626 | AY82: 1.9108981 | AZ82: 1.7479032 | BA82: 2.0622558 | BB82: 1.6103421 | BC82: 1.1784917
A83: 81 | B83: A_Onion | C83: 01.d | D83: 01.13 | E83: Onions, shallots, green | F83: tonnes | J83: 0.35747106 | M83: 0.62879266 | N83: 0.38486649 | O83: 1.6868439 | Q83: 0.16658495 | T83: 0.1715001 | V83: 0.30030857 | W83: 0.52585845 | X83: 0.25624577 | AA83: 0.26928769 | AF83: 0.7603379 | AG83: 0.55782172 | AL83: 0.46723803 | AM83: 0.56266173 | AN83: 0.68003323 | AP83: 0.2914323 | AV83: 0.20976456 | AW83: 0.012038905 | AY83: 0.25281428 | AZ83: 0.32978963 | BA83: 0.099569067 | BB83: 1.0519843 | BC83: 0.34515056
A84: 82 | B84: A_Onioy | C84: 01.d | D84: 01.13 | E84: Onions, dry | F84: tonnes | G84: 0.19601815 | H84: 0.51308608 | I84: 0.29374482 | J84: 0.29493076 | K84: 0.37308053 | L84: 0.39515563 | M84: 0.31918312 | N84: 0.56329246 | O84: 0.71863186 | P84: 0.29901798 | Q84: 0.12697325 | R84: 0.19434769 | S84: 1.9258023 | T84: 0.21094625 | U84: 0.3571787 | V84: 0.29290551 | W84: 0.20649868 | X84: 0.12888853 | Z84: 0.33118382 | AA84: 0.24674151 | AB84: 0.59143069 | AC84: 0.34174611 | AD84: 0.20056913 | AE84: 0.43499942 | AF84: 1.0128981 | AG84: 0.43707685 | AH84: 0.32620942 | AI84: 0.69017329 | AJ84: 0.46717219 | AK84: 0.46665296 | AL84: 0.42368991 | AM84: 0.51982217 | AO84: 0.3732895 | AP84: 0.45629735 | AQ84: 0.35435386 | AR84: 0.31886187 | AS84: 0.14119432 | AT84: 0.43870052 | AU84: 0.16640939 | AV84: 0.22594396 | AW84: 0.012739789 | AX84: 0.31775531 | AY84: 0.28472197 | AZ84: 0.29519016 | BA84: 0.18803774 | BB84: 0.73040942 | BC84: 0.28716673 | BD84: 0.55468065
A85: 83 | B85: A_Orans | C85: 01.d | D85: 01.23 | E85: Oranges | F85: tonnes | H85: 0.71310527 | K85: 0.28378729 | N85: 0.80135968 | O85: 0.79238287 | T85: 0.27412318 | V85: 0.60661145 | X85: 0.16041153 | Z85: 0.46823799 | AB85: 0.22467728 | AD85: 0.28913039 | AE85: 0.55021308 | AF85: 1.5450503 | AK85: 0.43339384 | AL85: 0.61526156 | AP85: 0.56763456 | AR85: 0.85853492 | AV85: 0.28143511 | AW85: 0.013517006 | AX85: 0.50346394 | AY85: 0.4123808 | AZ85: 0.46429095 | BA85: 0.26799587 | BB85: 0.54163579 | BC85: 0.36611435 | BD85: 0.48202262
A86: 84 | B86: A_oVege_fresh | C86: 01.d | D86: 01.13 | E86: Vegetables, fresh nes | F86: tonnes | G86: 0.30688439 | H86: 0.64675117 | I86: 0.27883415 | J86: 0.85070648 | K86: 0.9701273 | L86: 0.36474323 | M86: 0.5279665 | N86: 0.82448503 | O86: 0.60572236 | P86: 0.67540054 | Q86: 0.3503987 | R86: 0.47841915 | S86: 0.54009436 | T86: 0.26858697 | U86: 0.34030465 | V86: 0.3714527 | W86: 0.34355842 | X86: 0.23708173 | Z86: 0.63933128 | AA86: 0.37900844 | AB86: 0.59816459 | AC86: 0.60098286 | AD86: 0.34453879 | AE86: 0.54046251 | AF86: 1.0440094 | AG86: 0.43018494 | AH86: 0.36544624 | AI86: 1.3069843 | AJ86: 0.47896444 | AK86: 0.33881171 | AL86: 0.8929945 | AM86: 0.81188721 | AN86: 0.63235107 | AO86: 0.35869308 | AP86: 0.5137717 | AQ86: 0.28445536 | AR86: 0.38532839 | AS86: 0.51897463 | AT86: 0.50531002 | AU86: 0.36438606 | AV86: 0.39329385 | AW86: 0.088103026 | AX86: 0.31208137 | AY86: 0.37360071 | AZ86: 0.62835058 | BA86: 0.33439141 | BB86: 0.57770905 | BC86: 0.48572344 | BD86: 1.2121897
A87: 85 | B87: A_palm | C87: 01.d | D87: 01.11 | E87: Oil palm fruit | F87: tonnes | K87: 1.1028147 | N87: 1.0000129 | AB87: 0.58661385 | AL87: 0.89497298 | AY87: 0.6562882 | BA87: 0.98367705 | BB87: 0.77617231
A88: 86 | B88: A_Papas | C88: 01.d | D88: 01.22 | E88: Papayas | F88: tonnes | H88: 0.66447944 | K88: 0.27592622 | N88: 1.0171937 | AB88: 0.13060161 | AD88: 0.2110938 | AL88: 0.34537112 | AW88: 0.014554294 | AX88: 0.37297243 | AY88: 0.40880822 | BA88: 0.2918586 | BB88: 0.67391884 | BC88: 0.39614328 | BD88: 1.3201579
A89: 87 | B89: A_Peacs | C89: 01.d | D89: 01.24 | E89: Peaches and nectarines | F89: tonnes | G89: 0.60384193 | H89: 0.89025713 | J89: 0.56135903 | K89: 0.5530516 | L89: 0.56723163 | M89: 0.51649069 | N89: 0.86496201 | O89: 0.6525283 | P89: 5.9373838 | Q89: 0.59507475 | T89: 0.21588629 | V89: 0.33071516 | X89: 0.22873833 | Z89: 0.91669832 | AA89: 0.46636309 | AD89: 0.40395387 | AE89: 0.31461263 | AF89: 1.1578106 | AG89: 1.3483847 | AK89: 0.25310778 | AL89: 0.98790091 | AO89: 0.90123377 | AP89: 0.67325443 | AQ89: 0.26082166 | AR89: 0.46837215 | AT89: 0.3440234 | AU89: 1.114051 | AV89: 0.31297324 | AW89: 0.01260181 | AX89: 0.42670725 | AY89: 0.86053709 | AZ89: 0.58613582 | BA89: 0.32079462 | BB89: 0.79192587 | BC89: 0.32755411 | BD89: 0.98773777
A90: 88 | B90: A_Pears | C90: 01.d | D90: 01.24 | E90: Pears | F90: tonnes | G90: 0.047664652 | H90: 0.52540312 | I90: 0.22651881 | J90: 0.90356799 | K90: 0.46540416 | L90: 0.51240179 | M90: 0.35769152 | N90: 0.61708529 | O90: 0.54317777 | P90: 0.64961164 | Q90: 0.30935759 | R90: 0.29179736 | T90: 0.22783293 | V90: 0.27564027 | W90: 0.30734431 | X90: 0.22407398 | Z90: 0.9883676 | AA90: 0.43331515 | AD90: 0.35177092 | AE90: 0.32870547 | AF90: 0.90706019 | AG90: 0.74520165 | AH90: 1.5358132 | AI90: 0.79144669 | AJ90: 2.0156582 | AK90: 0.16956322 | AL90: 0.9559893 | AM90: 0.39474566 | AN90: 1.6162596 | AO90: 0.45842112 | AP90: 0.57218036 | AQ90: 0.23707147 | AR90: 0.4034774 | AS90: 0.58516116 | AT90: 0.23497741 | AU90: 0.88136712 | AV90: 0.27698857 | AW90: 0.018273681 | AX90: 0.30311194 | AY90: 0.49565415 | AZ90: 0.53438654 | BA90: 0.3873928 | BB90: 0.68691876 | BC90: 0.36558887 | BD90: 0.85310252
A91: 89 | B91: A_Peasn | C91: 01.d | D91: 01.11 | E91: Peas, green | F91: tonnes | G91: 0.61639351 | H91: 0.63212166 | I91: 0.93506829 | J91: 0.66621253 | L91: 0.57472303 | M91: 0.80049205 | N91: 1.0032581 | O91: 0.34206061 | P91: 0.88164837 | Q91: 0.77956894 | R91: 1.3358164 | S91: 1.8265545 | T91: 0.3760048 | U91: 2.1796809 | V91: 1.0038355 | W91: 0.69474536 | X91: 0.42088077 | Z91: 0.57043292 | AA91: 0.5244827 | AC91: 0.80794423 | AD91: 0.36666609 | AE91: 0.72674733 | AF91: 1.7900543 | AH91: 1.2294162 | AI91: 2.7228762 | AJ91: 1.4324518 | AK91: 0.46652604 | AL91: 0.65200821 | AM91: 2.1623488 | AN91: 1.0778691 | AO91: 0.65362123 | AP91: 0.69301536 | AQ91: 0.55583863 | AR91: 0.52536087 | AS91: 0.84016683 | AT91: 1.0035396 | AU91: 0.77054592 | AV91: 0.29052015 | AW91: 0.012718201 | AX91: 0.58525904 | AY91: 0.24896521 | AZ91: 0.69507052 | BA91: 0.17662092 | BB91: 1.3257291 | BC91: 0.37392152 | BD91: 1.553418
A92: 90 | B92: A_Peasy | C92: 01.d | D92: 01.11 | E92: Peas, dry | F92: tonnes | G92: 1.2097367 | H92: 2.6688389 | I92: 1.6904164 | J92: 1.1136351 | K92: 1.3187221 | L92: 1.0073259 | M92: 2.6216917 | N92: 3.0980724 | P92: 1.5934842 | Q92: 1.0659333 | R92: 0.8601324 | S92: 1.8919944 | T92: 1.7160313 | U92: 1.8146748 | V92: 2.6636044 | W92: 0.81111934 | X92: 1.1177878 | Z92: 1.083548 | AA92: 1.3181368 | AC92: 1.0699437 | AD92: 2.4423023 | AE92: 1.6056365 | AF92: 3.0337759 | AG92: 3.7577586 | AH92: 1.2855386 | AI92: 2.2664738 | AJ92: 1.5866267 | AL92: 2.3897067 | AM92: 1.435503 | AN92: 2.2263848 | AO92: 1.7023974 | AQ92: 1.4753282 | AR92: 1.2910871 | AS92: 1.1112567 | AT92: 1.5292509 | AU92: 1.209954 | AV92: 0.94281437 | AX92: 1.177257 | AY92: 0.93505563 | AZ92: 1.1771795 | BA92: 0.58512814 | BB92: 2.365236 | BC92: 1.2735292 | BD92: 2.8470208
A93: 91 | B93: A_Perss | C93: 01.d | D93: 01.13 | E93: Persimmons | F93: tonnes | H93: 1.4991421 | K93: 0.46318166 | N93: 2.8174269 | T93: 0.3117869 | AE93: 0.55001702 | AF93: 1.6689357 | AG93: 1.2573085 | AL93: 0.74120474 | AT93: 0.54282168 | AW93: 0.015977291 | AY93: 0.41101968 | BB93: 1.5839773 | BC93: 0.501971
A94: 92 | B94: A_Piges | C94: 01.d | D94: 01.11 | E94: Pigeon peas | F94: tonnes | AD94: 2.9755834 | AY94: 0.73916797 | BA94: 0.46435376 | BB94: 3.2263793
A95: 93 | B95: A_Pines | C95: 01.d | D95: 01.22 | E95: Pineapples | F95: tonnes | H95: 0.54030826 | K95: 0.22845066 | N95: 0.82512374 | AB95: 0.11833352 | AD95: 0.29716225 | AF95: 1.2556049 | AG95: 0.62605802 | AL95: 0.38224679 | AP95: 0.78441092 | AW95: 0.013756465 | AX95: 0.40327588 | AY95: 0.19306974 | BA95: 0.13299569 | BB95: 0.3062779 | BC95: 0.88277135 | BD95: 1.2265511
A96: 94 | B96: A_Pists | C96: 01.d | D96: 01.25 | E96: Pistachios | F96: tonnes | H96: 4.2080633 | N96: 2.8018221 | O96: 12.312139 | T96: 7.2772091 | X96: 1.8526757 | AE96: 5.1080721 | AL96: 8.3665145 | AV96: 1.6526584 | AX96: 1.6139876 | AY96: 4.0583319 | BA96: 8.8036063 | BC96: 2.5161943
A97: 95 | B97: A_Plans | C97: 01.d | D97: 01.22 | E97: Plantains and others | F97: tonnes | AY97: 0.26356473 | BA97: 0.3377351 | BB97: 0.82030516
A98: 96 | B98: A_Plums | C98: 01.d | D98: 01.24 | E98: Plums and sloes | F98: tonnes | G98: 0.27637794 | H98: 1.0815089 | I98: 9.3878563 | J98: 0.66737394 | L98: 0.8978098 | M98: 0.50650299 | N98: 3.1195797 | O98: 1.9694756 | P98: 1.5118548 | Q98: 0.51041901 | R98: 0.98153563 | S98: 5.7864809 | T98: 0.39114913 | V98: 0.49157019 | W98: 0.44652466 | X98: 0.33527058 | Z98: 2.0267747 | AA98: 0.64511076 | AD98: 0.35521333 | AE98: 0.56774687 | AF98: 2.0178191 | AG98: 1.4523845 | AH98: 4.1756944 | AI98: 12.124719 | AJ98: 3.9484299 | AL98: 1.2452555 | AM98: 1.0557551 | AN98: 1.6911558 | AO98: 0.72136182 | AP98: 0.65448994 | AQ98: 0.43029664 | AR98: 0.72956802 | AS98: 1.2006906 | AT98: 0.7690129 | AU98: 3.9819685 | AV98: 0.45400448 | AW98: 0.023778548 | AX98: 0.70036735 | AY98: 0.92169955 | AZ98: 0.94080425 | BA98: 0.43002946 | BB98: 0.87908541 | BC98: 0.47942151 | BD98: 1.3412429
A99: 97 | B99: A_Potas | C99: 01.d | D99: 01.13 | E99: Potatoes | F99: tonnes | G99: 0.29218572 | H99: 0.64040317 | I99: 0.39540796 | J99: 0.30409538 | K99: 0.38866529 | L99: 0.42897062 | M99: 0.46553172 | N99: 0.60738589 | O99: 0.8899325 | P99: 0.44307546 | Q99: 0.2201126 | R99: 0.29058888 | S99: 0.55682378 | T99: 0.31398484 | U99: 0.47209601 | V99: 0.34514075 | W99: 0.33307113 | X99: 0.2569998 | Z99: 0.51557164 | AA99: 0.35298118 | AB99: 0.35346616 | AC99: 0.33163525 | AD99: 0.23357513 | AE99: 0.60999544 | AF99: 1.2351646 | AG99: 0.65648148 | AH99: 0.48611918 | AI99: 0.79451214 | AJ99: 0.6699528 | AK99: 0.69182856 | AL99: 0.47587021 | AM99: 0.64825122 | AN99: 0.65387184 | AO99: 0.4634071 | AP99: 0.71559187 | AQ99: 0.41884224 | AR99: 0.48371312 | AS99: 0.28159468 | AT99: 0.54176063 | AU99: 0.31752865 | AV99: 0.25636731 | AW99: 0.020679192 | AX99: 0.42580648 | AY99: 0.2303714 | AZ99: 0.41019648 | BA99: 0.19259825 | BB99: 0.56199166 | BC99: 0.37142032 | BD99: 0.54271491
A100: 98 | B100: A_Pulss | C100: 01.d | D100: 01.11 | E100: Pulses nes | F100: tonnes | G100: 1.3608437 | J100: 1.1018292 | N100: 2.2024917 | O100: 1.7823922 | P100: 2.6791281 | Q100: 0.85664525 | R100: 1.5741255 | S100: 1.2453396 | T100: 2.258061 | V100: 1.6950921 | W100: 1.2943962 | X100: 1.2646003 | AA100: 1.7880871 | AB100: 6.6850461 | AD100: 4.8062359 | AE100: 1.1645996 | AG100: 3.1288686 | AH100: 1.7649434 | AI100: 1.5701459 | AJ100: 3.2788263 | AL100: 3.1747512 | AO100: 2.7350176 | AQ100: 1.7490518 | AR100: 1.6156885 | AT100: 1.7710115 | AU100: 1.9099511 | AV100: 2.0568513 | AY100: 0.71891802 | AZ100: 2.2214134 | BA100: 1.1901595 | BB100: 1.2878306 | BC100: 1.1922706
...

Sheet GHG markets - hybrid
A1: GHG intensities: tonne CO2-eq. per unit | F1: MEUR/t | G1: ='GHG markets - hybrid'!G525/'GHG markets - monetary'!G452 * 1000 -> 2.2188454 | H1: ='GHG markets - hybrid'!H525/'GHG markets - monetary'!H452 * 1000 -> 12.543023 | I1: ='GHG markets - hybrid'!I525/'GHG markets - monetary'!I452 * 1000 -> 2.6645769 | J1: ='GHG markets - hybrid'!J525/'GHG markets - monetary'!J452 * 1000 -> 2.4186067 | K1: ='GHG markets - hybrid'!K525/'GHG markets - monetary'!K452 * 1000 -> 8.7587887 | L1: ='GHG markets - hybrid'!L525/'GHG markets - monetary'!L452 * 1000 -> 51.30281 | M1: ='GHG markets - hybrid'!M525/'GHG markets - monetary'!M452 * 1000 -> 2.1497588 | N1: ='GHG markets - hybrid'!N525/'GHG markets - monetary'!N452 * 1000 -> 5.2323261 | ... AJ1: ='GHG markets - hybrid'!AJ525/'GHG markets - monetary'!AJ452 * 1000 -> 2.5899762
A2: No | B2: EXIOBASE product code | C2: Nace rev1 code | D2: Nace rev2 code | E2: Description | F2: Unit | G2: AT | H2: AU | I2: BE | J2: BG | K2: BR | L2: CA | M2: CH | N2: CN | O2: CY | P2: CZ | Q2: DE | R2: DK | S2: EE | T2: ES | U2: FI | V2: FR | W2: GB | X2: GR | Y2: Global | Z2: HR | AA2: HU | AB2: ID | AC2: IE | AD2: IN | AE2: IT | AF2: JP | AG2: KR | AH2: LT | AI2: LU | AJ2: LV | AK2: MT | AL2: MX | AM2: NL | AN2: NO | AO2: PL | AP2: PT | AQ2: RO | AR2: RU | AS2: SE | AT2: SI | AU2: SK | AV2: TR | AW2: TW | AX2: US | AY2: WA | AZ2: WE | BA2: WF | BB2: WL | BC2: WM | BD2: ZA
A3: 1 | B3: M_Ricey | C3: 01.a | D3: 01.12 | E3: Rice, paddy, market of | F3: tonnes | G3: 2.7034813 | H3: 1.6837518 | I3: 2.7433509 | J3: 2.5012937 | K3: 1.831469 | L3: 2.246928 | M3: 2.5267356 | N3: 2.7750241 | O3: 1.5876481 | P3: 2.457337 | Q3: 2.8393737 | R3: 2.7468935 | S3: 2.4916298 | T3: 1.9568852 | U3: 1.9569039 | V3: 2.8888842 | W3: 2.2345233 | X3: 1.4821261 | Y3: 2.7123364 | Z3: 2.6571328 | AA3: 3.3831683 | AB3: 2.8331627 | AC3: 2.2550059 | AD3: 2.9258097 | AE3: 2.4191062 | AF3: 2.8048107 | AG3: 2.4831095 | AH3: 2.3390306 | AI3: 2.7644713 | AJ3: 1.9452962 | AK3: 2.2906356 | AL3: 2.0810677 | AM3: 2.5517708 | AN3: 2.4563285 | AO3: 2.6625415 | AP3: 2.2908518 | AQ3: 3.0960778 | AR3: 2.9872421 | AS3: 2.4538424 | AT3: 2.7099873 | AU3: 2.5481915 | AV3: 2.1105107 | AW3: 0.25797537 | AX3: 2.1455885 | AY3: 2.5472776 | AZ3: 3.1335171 | BA3: 2.8470643 | BB3: 2.6715977 | BC3: 2.3550325 | BD3: 4.8806297
A4: 2 | B4: M_Germt | C4: 01.b | D4: 01.11 | E4: Germ, wheat, market of | F4: tonnes | G4: 0.30966108 | H4: 0.59636788 | I4: 0.6289413 | J4: 5.5532462 | L4: 0.63285132 | M4: 0.10330556 | N4: 0.47788859 | O4: 1.859407 | P4: 0.42436654 | Q4: 0.09995143 | R4: 0.47878909 | S4: 0.36840919 | T4: 1.8072579 | U4: 0.30898634 | V4: 0.6333932 | W4: 1.8387945 | X4: 0.072804992 | Y4: 0.61738239 | Z4: 0.31848263 | AA4: 0.43242269 | AB4: 0.065197648 | AC4: 1.6829984 | AD4: 0.21673567 | AE4: 0.7794657 | AF4: 0.091454024 | AG4: 0.80375356 | AH4: 0.25522888 | AI4: 0.71351851 | AJ4: 0.36956472 | AK4: 1.2905606 | AL4: 0.46017257 | AM4: 1.4131758 | AN4: 0.42020436 | AO4: 1.153073 | AP4: 0.75322876 | AQ4: 0.21205587 | AR4: 1.8216443 | AS4: 0.50950623 | AT4: 0.53026317 | AU4: 0.39017964 | AV4: 0.39420195 | AW4: 0.080091711 | AX4: 0.36200909 | AY4: 0.23604252 | AZ4: 1.7216699 | BA4: 0.17932303 | BB4: 12.096097 | BC4: 0.54996805 | BD4: 0.80275922
A5: 3 | B5: M_Wheat | C5: 01.b | D5: 01.11 | E5: Wheat, market of | F5: tonnes | G5: 1.0090985 | H5: 1.5706298 | I5: 1.0977597 | J5: 1.081597 | K5: 1.8297677 | L5: 1.3304042 | M5: 1.2751885 | N5: 1.6597586 | O5: 1.4971719 | P5: 1.0839728 | Q5: 0.93792557 | R5: 0.90619688 | S5: 1.8790591 | T5: 1.1126208 | U5: 1.4681997 | V5: 1.2085173 | W5: 1.0733201 | X5: 1.135965 | Y5: 1.3869469 | Z5: 1.0565227 | AA5: 0.90867801 | AB5: 1.4587189 | AC5: 0.88121002 | AD5: 1.1815905 | AE5: 1.3364016 | AF5: 1.5325273 | AG5: 1.4477703 | AH5: 1.2056893 | AI5: 1.1262165 | AJ5: 1.5063884 | AK5: 1.145114 | AL5: 1.3369124 | AM5: 1.0902027 | AN5: 1.1936614 | AO5: 1.2225263 | AP5: 1.2155136 | AQ5: 1.0314689 | AR5: 1.5641129 | AS5: 1.1047241 | AT5: 1.1172161 | AU5: 0.97081145 | AV5: 1.3468692 | AW5: 1.5047137 | AX5: 1.4888908 | AY5: 1.6170861 | AZ5: 1.3844072 | BA5: 1.2139353 | BB5: 1.4215361 | BC5: 1.093147 | BD5: 1.2991782
A6: 4 | B6: M_Barly | C6: 01.c | D6: 01.11 | E6: Barley, market of | F6: tonnes | G6: 0.93162088 | H6: 1.412717 | I6: 1.0677338 | J6: 0.88266343 | K6: 1.0561585 | L6: 1.2191225 | M6: 1.1465735 | N6: 1.4997596 | O6: 1.5352057 | P6: 1.1933189 | Q6: 0.90060988 | R6: 0.93531521 | S6: 2.0276287 | T6: 1.1120685 | U6: 1.677671 | V6: 1.116545 | W6: 0.93674243 | X6: 0.95154859 | Y6: 1.2083829 | Z6: 1.2233425 | AA6: 0.97372033 | AB6: 1.0334758 | AC6: 0.83489913 | AD6: 1.1174693 | AE6: 1.5161462 | AF6: 1.7753116 | AG6: 3.4684164 | AH6: 1.510159 | AI6: 1.4888779 | AJ6: 2.1303779 | AK6: 1.1256397 | AL6: 2.1119661 | AM6: 1.0216333 | AN6: 1.3854379 | AO6: 1.6048521 | AP6: 1.1921595 | AQ6: 0.96312901 | AR6: 1.5062257 | AS6: 1.1385772 | AT6: 1.3451558 | AU6: 1.0577497 | AV6: 1.2591523 | AW6: 1.3714958 | AX6: 1.1859739 | AY6: 1.012029 | AZ6: 1.3827087 | BA6: 0.99537542 | BB6: 0.96000216 | BC6: 1.1736334 | BD6: 1.0456374
A7: 5 | B7: M_Buckt | C7: 01.c | D7: 01.11 | E7: Buckwheat, market of | F7: tonnes | G7: 3.3925127 | H7: 4.8021031 | I7: 3.5222284 | J7: 3.4182139 | K7: 4.0673982 | L7: 5.0650099 | M7: 3.3898139 | N7: 7.3366376 | O7: 3.7817082 | P7: 2.7075468 | Q7: 3.5042977 | R7: 3.4645536 | S7: 4.615424 | T7: 3.6182433 | U7: 4.4473505 | V7: 2.092172 | W7: 4.9279979 | X7: 3.5952353 | Y7: 3.8011452 | Z7: 4.0004743 | AA7: 3.0514675 | AB7: 3.8175588 | AC7: 4.7899535 | AD7: 3.2242016 | AE7: 3.5804949 | AF7: 8.5520256 | AG7: 10.601666 | AH7: 3.5659631 | AI7: 3.4881239 | AJ7: 4.701712 | AK7: 3.3209376 | AM7: 4.3085486 | AN7: 5.5937298 | AO7: 3.4022655 | AP7: 3.616555 | AQ7: 3.425752 | AR7: 2.6718612 | AS7: 4.142521 | AT7: 4.8982198 | AU7: 3.4431495 | AV7: 3.5216827 | AW7: 6.3950172 | AX7: 3.9607746 | AY7: 3.2344677 | AZ7: 3.7020822 | BA7: 0.64009168 | BB7: 5.2975609 | BC7: 3.8524882 | BD7: 7.1198199
A8: 6 | B8: M_Ceres | C8: 01.c | D8: 01.11 | E8: Cereals nes, market of | F8: tonnes | G8: 0.78966493 | H8: 1.4094301 | I8: 0.89431123 | J8: 1.1702994 | K8: 1.1667804 | L8: 1.1155835 | M8: 1.0223166 | N8: 1.0391255 | O8: 1.0418404 | P8: 1.8211092 | Q8: 1.3760342 | R8: 1.039567 | S8: 1.6805684 | T8: 0.95871785 | U8: 1.8806728 | V8: 0.921512 | W8: 1.165501 | X8: 0.67864268 | Y8: 0.4083897 | Z8: 1.0126151 | AA8: 0.9081509 | AB8: 0.91556109 | AC8: 1.4502587 | AD8: 0.48097134 | AE8: 1.0036318 | AF8: 0.58967073 | AG8: 1.6866803 | AH8: 2.0289858 | AI8: 0.88656696 | AJ8: 1.7436428 | AK8: 0.4538758 | AL8: 1.7026245 | AM8: 0.97744257 | AN8: 1.0347606 | AO8: 1.5075831 | AP8: 1.0138966 | AQ8: 1.2910828 | AR8: 3.0909513 | AS8: 1.0323857 | AT8: 0.79315807 | AU8: 2.5852342 | AV8: 0.37698665 | AW8: 0.49315594 | AX8: 1.3267745 | AY8: 0.34006912 | AZ8: 1.1551191 | BA8: 0.34530736 | BB8: 1.8446436 | BC8: 0.7450977 | BD8: 2.7771296
A9: 7 | B9: M_Fonio | C9: 01.c | D9: 01.29 | E9: Fonio, market of | F9: tonnes | G9: 0.73777327 | I9: 0.73777327 | L9: 0.73777327 | M9: 0.73777327 | O9: 0.73777327 | P9: 0.73777327 | Q9: 0.73777327 | R9: 0.73777327 | T9: 0.73777327 | V9: 0.73777327 | W9: 0.73777327 | X9: 0.73777327 | Y9: 0.73777327 | AB9: 0.73777327 | AC9: 0.73777327 | AE9: 0.73777327 | AH9: 0.73777327 | AI9: 0.73777327 | AM9: 0.73777327 | AO9: 0.73777327 | AP9: 0.73777327 | AQ9: 0.73777327 | AS9: 0.73777327 | AX9: 0.73777327 | AZ9: 0.73777327 | BA9: 0.73777327 | BC9: 0.73777327
A10: 8 | B10: M_Germe | C10: 01.c | D10: 01.19 | E10: Germ, maize, market of | F10: tonnes | G10: 0.13465036 | H10: 0.27767839 | I10: 0.26951667 | J10: 0.092309205 | K10: 0.081855462 | L10: 0.24045252 | M10: 0.22498475 | N10: 0.26482772 | O10: 0.093742081 | P10: 0.13792103 | Q10: 0.026858557 | R10: 0.17083627 | S10: 0.14079879 | T10: 0.21455931 | U10: 0.17088832 | V10: 0.16905252 | W10: 0.095081175 | X10: 0.035974917 | Y10: 0.17242369 | Z10: 0.16503306 | AA10: 0.15264821 | AB10: 0.09788484 | AC10: 0.13889351 | AD10: 0.17381485 | AE10: 0.28045172 | AF10: 0.93019905 | AG10: 0.35997403 | AH10: 0.13992504 | AI10: 0.23191287 | AJ10: 0.29492031 | AK10: 0.095861839 | AL10: 0.20733447 | AM10: 0.47861697 | AN10: 0.17088832 | AO10: 0.27836821 | AP10: 0.2675483 | AQ10: 0.091680723 | AR10: 0.22587892 | AS10: 0.0230167 | AT10: 0.23035176 | AU10: 0.089315501 | AV10: 0.18054089 | AW10: 0.003796862 | AX10: 0.12986424 | AY10: 0.16080747 | AZ10: 0.11593331 | BA10: 0.049085802 | BB10: 0.19677516 | BC10: 0.37182629 | BD10: 0.38418783
A11: 9 | B11: M_Graid | C11: 01.c | D11: 01.11 | E11: Grain, mixed, market of | F11: tonnes | G11: 1.4282035 | I11: 2.2782375 | J11: 1.4057604 | L11: 1.5959109 | M11: 1.3980298 | N11: 1.7693228 | O11: 2.1141597 | P11: 1.9767199 | Q11: 1.565319 | R11: 1.3194943 | S11: 2.3817762 | T11: 2.0293504 | U11: 2.2803178 | V11: 1.8392274 | W11: 0.98449982 | X11: 1.127864 | Y11: 2.0168376 | Z11: 2.0511401 | AA11: 1.8973645 | AC11: 2.2441459 | AD11: 2.2833932 | AE11: 1.7510112 | AH11: 2.1900829 | AI11: 1.6676463 | AJ11: 4.5668597 | AK11: 1.2570056 | AM11: 2.2499968 | AN11: 1.545814 | AO11: 2.0808125 | AP11: 1.545814 | AQ11: 1.5666099 | AS11: 1.6982002 | AT11: 1.6600088 | AU11: 1.4398319 | AV11: 1.879883 | AX11: 1.8408457 | AY11: 0.60649867 | AZ11: 1.7537465 | BA11: 2.2833932 | BB11: 1.545814 | BC11: 2.2723968
A12: 10 | B12: M_Hops | C12: 01.c | D12: 01.28 | E12: Hops, market of | F12: tonnes | G12: 2.3778772 | H12: 3.1415977 | I12: 2.7538317 | J12: 2.7111933 | K12: 2.5849159 | L12: 2.8746344 | M12: 2.2888509 | N12: 4.0340287 | O12: 3.8403813 | P12: 4.4534038 | Q12: 2.4828312 | R12: 2.2866271 | S12: 2.3043355 | T12: 2.4171332 | U12: 2.7032489 | V12: 2.846412 | W12: 2.7412485 | X12: 2.3145808 | Y12: 2.5858921 | Z12: 2.569335 | AA12: 2.7114676 | AB12: 2.532335 | AC12: 2.5153235 | AD12: 2.6205317 | AE12: 3.0486119 | AF12: 3.1803241 | AG12: 2.7174348 | AH12: 2.3360437 | AI12: 2.3448922 | AJ12: 2.7731861 | AK12: 1.5614844 | AL12: 2.8916692 | AM12: 2.3584933 | AN12: 2.244591 | AO12: 2.8010976 | AP12: 2.2262177 | AQ12: 2.605093 | AR12: 2.8461033 | AS12: 2.2119535 | AT12: 2.8082453 | AU12: 2.6159174 | AV12: 2.3765646 | AW12: 2.524705 | AX12: 2.9157823 | AY12: 4.6038373 | AZ12: 5.7298512 | BA12: 1.0589902 | BB12: 2.7236373 | BC12: 1.2962169 | BD12: 3.8936973
A13: 11 | B13: M_Maize | C13: 01.c | D13: 01.11 | E13: Maize, market of | F13: tonnes | G13: 0.47836777 | H13: 0.39926279 | I13: 0.6795399 | J13: 1.0368718 | K13: 1.2740478 | L13: 0.56375598 | M13: 0.71179696 | N13: 1.0600853 | O13: 0.78011853 | P13: 0.68504897 | Q13: 0.64861446 | R13: 0.66983623 | S13: 0.7028431 | T13: 0.57062849 | U13: 0.61425691 | V13: 0.73374648 | W13: 0.71752574 | X13: 0.41330712 | Y13: 0.79053392 | Z13: 0.60695307 | AA13: 0.49295106 | AB13: 1.1597808 | AC13: 0.68719638 | AD13: 1.1434724 | AE13: 0.61501786 | AF13: 0.68827463 | AG13: 0.73418858 | AH13: 0.70717853 | AI13: 0.67026538 | AJ13: 0.70005812 | AK13: 0.71073953 | AL13: 1.0528988 | AM13: 0.77482498 | AN13: 0.70841139 | AO13: 0.72229077 | AP13: 0.71156358 | AQ13: 0.74571989 | AR13: 0.70069883 | AS13: 0.69623797 | AT13: 0.61486245 | AU13: 0.54782285 | AV13: 0.56025071 | AW13: 0.77413924 | AX13: 0.54815402 | AY13: 0.73822987 | AZ13: 0.75245368 | BA13: 0.66183119 | BB13: 0.69629188 | BC13: 0.77794981 | BD13: 0.88624064
A14: 12 | B14: M_Maizn | C14: 01.c | D14: 01.11 | E14: Maize, green, market of | F14: tonnes | G14: 0.51346798 | H14: 0.56144661 | I14: 0.52795372 | J14: 0.72775693 | K14: 0.51493593 | L14: 0.69802658 | M14: 0.87866828 | N14: 1.8574577 | O14: 0.32875148 | P14: 0.53084204 | Q14: 0.56849257 | R14: 0.51332381 | S14: 0.58126795 | T14: 0.51356842 | U14: 0.51500138 | V14: 0.54116874 | W14: 0.54147896 | X14: 0.20779804 | Y14: 0.60994546 | Z14: 0.43187896 | AA14: 0.47908757 | AB14: 1.1984902 | AC14: 0.53554678 | AD14: 0.53809587 | AE14: 0.85843915 | AF14: 1.9191448 | AG14: 0.52085114 | AH14: 0.59324527 | AI14: 0.53794055 | AJ14: 0.61601625 | AK14: 0.51464265 | AL14: 0.64009699 | AM14: 0.52206303 | AN14: 0.85748213 | AO14: 0.68441513 | AP14: 0.51493601 | AQ14: 0.95337837 | AR14: 0.59324525 | AS14: 0.50708316 | AT14: 0.61170271 | AU14: 0.54535846 | AV14: 0.522063 | AW14: 0.50771659 | AX14: 0.50727818 | AY14: 1.0026829 | AZ14: 0.49664681 | BA14: 0.45367638 | BB14: 0.54950589 | BC14: 0.71685451 | BD14: 0.8884091
A15: 13 | B15: M_Millt | C15: 01.c | D15: 01.11 | E15: Millet, market of | F15: tonnes | G15: 1.1414987 | H15: 1.9793902 | I15: 1.9744365 | J15: 2.0363509 | K15: 1.6140313 | L15: 1.1232608 | M15: 1.6611755 | N15: 2.1748669 | O15: 2.0741818 | P15: 3.1444493 | Q15: 1.8294218 | R15: 1.8734002 | S15: 2.5617806 | T15: 1.8831123 | U15: 1.4732408 | V15: 1.6880466 | W15: 1.9859134 | X15: 1.766918 | Y15: 1.450526 | Z15: 2.9154691 | AA15: 1.9963025 | AB15: 1.1715373 | AC15: 1.9926848 | AD15: 2.0034801 | AE15: 2.0266886 | AF15: 1.9621371 | AG15: 3.4347576 | AH15: 2.2591745 | AI15: 1.6659131 | AJ15: 2.3430963 | AK15: 2.0664973 | AL15: 1.0859683 | AM15: 2.0095011 | AN15: 1.9574941 | AO15: 2.2700292 | AP15: 2.0244936 | AQ15: 1.8206821 | AR15: 1.6482235 | AS15: 2.045107 | AT15: 2.8100966 | AU15: 2.1340652 | AV15: 1.6189921 | AW15: 1.3443419 | AX15: 1.0702944 | AY15: 1.569451 | AZ15: 2.1254214 | BA15: 0.92186394 | BB15: 1.4775995 | BC15: 2.0917776 | BD15: 3.1087632
A16: 14 | B16: M_Mushs | C16: 01.c | D16: 01.13 | E16: Mushrooms and truffles, market of | F16: tonnes | G16: 0.30509237 | H16: 0.6891235 | I16: 0.459033 | J16: 0.39944846 | K16: 0.87612155 | L16: 0.57320062 | M16: 0.58806955 | N16: 0.67387764 | O16: 0.82863237 | P16: 0.43990574 | Q16: 0.36386762 | R16: 0.47673506 | S16: 0.35730017 | T16: 0.34188851 | U16: 1.1936521 | V16: 0.32743476 | W16: 0.28901356 | X16: 0.42242136 | Y16: 0.64201246 | Z16: 0.50896016 | AA16: 0.22606646 | AB16: 0.17033251 | AC16: 0.27401099 | AD16: 0.36385101 | AE16: 1.0173754 | AF16: 1.0003877 | AG16: 0.52601268 | AH16: 0.88928277 | AI16: 0.4297288 | AJ16: 0.34895214 | AK16: 1.834623 | AL16: 0.22333028 | AM16: 0.6554204 | AN16: 0.48783739 | AO16: 0.41365471 | AP16: 0.64518508 | AQ16: 0.23376861 | AR16: 1.0778263 | AS16: 0.35570929 | AT16: 0.44460537 | AU16: 0.39672629 | AV16: 0.33511107 | AW16: 0.099342153 | AX16: 0.23256465 | AY16: 0.59224128 | AZ16: 0.37618161 | BA16: 0.66156054 | BB16: 0.23692191 | BC16: 1.5383097 | BD16: 0.64650686
A17: 15 | B17: M_Oatss | C17: 01.c | D17: 01.11 | E17: Oats, market of | F17: tonnes | G17: 0.98817734 | H17: 1.5943332 | I17: 1.1375675 | J17: 1.6919072 | K17: 1.7464084 | L17: 1.1177485 | M17: 1.3130222 | N17: 1.6649912 | O17: 5.1306355 | P17: 1.5600694 | Q17: 1.1904849 | R17: 0.88630326 | S17: 2.0651088 | T17: 1.4219016 | U17: 1.4380895 | V17: 1.0511663 | W17: 0.82158375 | X17: 1.109215 | Y17: 1.4148121 | Z17: 1.4462322 | AA17: 1.2925257 | AB17: 1.5713105 | AC17: 0.59446798 | AD17: 1.8317815 | AE17: 2.0551064 | AF17: 1.2057595 | AG17: 1.1870283 | AH17: 1.9102388 | AI17: 1.0765415 | AJ17: 2.446419 | AK17: 1.1398328 | AL17: 1.6922799 | AM17: 1.3888017 | AN17: 1.0688919 | AO17: 1.8371787 | AP17: 2.5503629 | AQ17: 1.3230734 | AR17: 1.584189 | AS17: 1.0964297 | AT17: 1.4697155 | AU17: 1.6351602 | AV17: 1.1400215 | AW17: 1.4486499 | AX17: 1.2497412 | AY17: 1.0388581 | AZ17: 1.8606413 | BA17: 0.73996298 | BB17: 1.1576281 | BC17: 1.2772793 | BD17: 1.6098571
A18: 16 | B18: M_Poppd | C18: 01.c | D18: 01.11 | E18: Poppy seed, market of | F18: tonnes | G18: 4.913068 | H18: 3.9276782 | I18: 5.6322307 | J18: 4.0729265 | K18: 4.7873109 | L18: 3.9240043 | M18: 5.6424059 | N18: 7.0597624 | O18: 5.003049 | P18: 4.9909281 | Q18: 5.3955 | R18: 4.5923271 | S18: 4.4418605 | T18: 2.5552028 | U18: 4.1441825 | V18: 4.3883557 | W18: 3.6775512 | X18: 4.8497794 | Y18: 4.261175 | Z18: 3.9637731 | AA18: 3.825085 | AB18: 4.7474493 | AC18: 4.0871429 | AD18: 3.9398911 | AE18: 4.7873109 | AF18: 3.9287535 | AG18: 4.8759873 | AH18: 5.0759776 | AI18: 5.6419832 | AJ18: 6.7133992 | AK18: 4.5242841 | AL18: 3.5613674 | AM18: 4.3353327 | AN18: 4.9534211 | AO18: 4.5461964 | AP18: 3.5908735 | AQ18: 5.1632379 | AR18: 5.1523598 | AS18: 4.2293669 | AT18: 4.2567929 | AU18: 4.131106 | AV18: 3.8430714 | AX18: 3.5613674 | AY18: 4.7474485 | AZ18: 4.5774838 | BA18: 4.2174325 | BB18: 3.8067412 | BC18: 1.8000595 | BD18: 4.4323023
A19: 17 | B19: M_Quina | C19: 01.c | D19: 01.11 | E19: Quinoa, market of | F19: tonnes | G19: 3.5709594 | H19: 3.5709593 | I19: 3.5709595 | J19: 3.5709591 | K19: 3.5709595 | L19: 3.5709588 | M19: 3.5709591 | N19: 3.5709595 | O19: 3.5709594 | P19: 3.5709592 | Q19: 3.5709593 | R19: 3.5709592 | S19: 3.5709593 | T19: 3.5709594 | U19: 3.5709592 | V19: 3.570958 | W19: 3.5709592 | X19: 3.570959 | Y19: 3.5709595 | Z19: 3.5709594 | AA19: 3.5709594 | AB19: 3.5709595 | AC19: 3.5709594 | AD19: 3.5709594 | AE19: 3.570959 | AF19: 3.5709594 | AG19: 3.5709595 | AH19: 3.5709592 | AI19: 3.5709593 | AJ19: 3.5709594 | AK19: 3.5709591 | AL19: 3.570959 | AM19: 3.5709593 | AN19: 3.5709593 | AO19: 3.5709595 | AP19: 3.570959 | AQ19: 3.5709593 | AR19: 3.5709595 | AS19: 3.5709593 | AT19: 3.570959 | AU19: 3.5709592 | AV19: 3.5709589 | AW19: 3.5709583 | AX19: 3.5709591 | AY19: 3.570959 | AZ19: 3.5709593 | BA19: 3.5709592 | BB19: 3.5709595 | BC19: 3.5709591 | BD19: 3.5709595
A20: 18 | B20: M_Ryee | C20: 01.c | D20: 01.11 | E20: Rye, market of | F20: tonnes | G20: 0.78647865 | H20: 3.7108711 | I20: 1.0548071 | J20: 1.5482607 | K20: 2.8270423 | L20: 0.90352227 | M20: 1.1833775 | N20: 1.1744676 | O20: 1.0258756 | P20: 1.1241136 | Q20: 0.92999072 | R20: 0.7038905 | S20: 1.6142195 | T20: 1.3380877 | U20: 1.4352947 | V20: 1.341685 | W20: 2.2069971 | X20: 1.0217775 | Y20: 1.2406428 | Z20: 1.2252932 | AA20: 1.155874 | AB20: 1.4114616 | AC20: 1.4437902 | AD20: 1.5674785 | AE20: 1.2587636 | AF20: 0.92782334 | AG20: 1.7075854 | AH20: 1.7164839 | AI20: 1.0738223 | AJ20: 1.425296 | AK20: 1.5935075 | AL20: 2.3686776 | AM20: 0.99063077 | AN20: 0.91367043 | AO20: 1.5118059 | AP20: 2.8392313 | AQ20: 1.1611794 | AR20: 1.2232989 | AS20: 0.78999466 | AT20: 1.228851 | AU20: 1.1512758 | AV20: 0.95708461 | AW20: 2.5038879 | AX20: 1.4792078 | AY20: 1.4127008 | AZ20: 2.0376386 | BA20: 0.88879113 | BB20: 2.0018498 | BC20: 0.96137736 | BD20: 2.0502406
A21: 19 | B21: M_Sorgm | C21: 01.c | D21: 01.11 | E21: Sorghum, market of | F21: tonnes | G21: 0.6402326 | H21: 0.97455934 | I21: 0.9008373 | J21: 1.3073598 | K21: 2.4544987 | L21: 1.0593949 | M21: 0.90984942 | N21: 1.0631778 | O21: 0.86040494 | P21: 1.9775674 | Q21: 0.92842978 | R21: 0.92732816 | S21: 0.90979951 | T21: 0.87726171 | U21: 0.90064924 | V21: 0.83541054 | W21: 0.90025202 | X21: 1.0061875 | Y21: 1.0985483 | Z21: 2.4085152 | AA21: 0.93795833 | AB21: 1.0207485 | AC21: 0.89677651 | AD21: 3.2555407 | AE21: 0.9573439 | AF21: 1.0916862 | AG21: 2.719454 | AH21: 1.0085887 | AI21: 0.83432121 | AJ21: 0.92842976 | AK21: 0.99016224 | AL21: 1.5219256 | AM21: 0.86040489 | AN21: 0.87057676 | AO21: 1.0174797 | AP21: 0.80780363 | AQ21: 0.91460965 | AR21: 1.6438662 | AS21: 0.87366937 | AT21: 0.92148795 | AU21: 1.466319 | AV21: 1.4344083 | AW21: 1.1480234 | AX21: 1.0102438 | AY21: 1.3956837 | AZ21: 0.99921492 | BA21: 0.68760012 | BB21: 1.1017495 | BC21: 1.051489 | BD21: 1.4373765
A22: 20 | B22: M_Trite | C22: 01.c | D22: 01.11 | E22: Triticale, market of | F22: tonnes | G22: 0.98813978 | H22: 1.7983672 | I22: 1.1162869 | J22: 1.0787378 | K22: 1.9437693 | L22: 1.2799216 | M22: 1.3065092 | N22: 2.502787 | O22: 1.0205241 | P22: 1.3162913 | Q22: 0.94629115 | R22: 1.0080649 | S22: 1.5510404 | T22: 1.4214067 | U22: 1.3028637 | V22: 1.0501935 | W22: 1.1474744 | X22: 0.9631696 | Y22: 1.3406064 | Z22: 1.1921159 | AA22: 1.043582 | AC22: 0.94581569 | AE22: 1.2467767 | AF22: 1.7983672 | AH22: 1.3214938 | AI22: 1.3934267 | AJ22: 1.7615902 | AK22: 1.4346749 | AL22: 1.6392117 | AM22: 0.93381742 | AN22: 1.0520392 | AO22: 1.4787536 | AP22: 2.9235205 | AQ22: 0.88343761 | AR22: 1.0679283 | AS22: 1.0828296 | AT22: 1.2156469 | AU22: 1.1249953 | AV22: 0.95938513 | AX22: 1.2801858 | AY22: 0.99926422 | AZ22: 1.9226479 | BA22: 0.34614823 | BB22: 0.69624056 | BC22: 1.3433097 | BD22: 0.34601534
A23: 21 | B23: M_Almol | C23: 01.d | D23: 01.25 | E23: Almonds, with shell, market of | F23: tonnes | G23: 3.9137826 | H23: 1.4015008 | I23: 1.565375 | J23: 4.4563203 | K23: 6.1297319 | L23: 1.2987992 | M23: 3.1473902 | N23: 2.3536278 | O23: 21.994154 | P23: 4.0849942 | Q23: 2.5600099 | R23: 3.2604681 | S23: 1.2914765 | T23: 7.1281853 | U23: 1.3210637 | V23: 4.9024923 | W23: 1.4710402 | X23: 1.0182119 | Y23: 2.0656556 | Z23: 6.3839906 | AA23: 5.7751785 | AB23: 1.2968469 | AC23: 1.8350737 | AD23: 1.3521761 | AE23: 3.1046039 | AF23: 1.2781114 | AG23: 1.2811916 | AH23: 2.7732803 | AI23: 3.255966 | AJ23: 2.5734228 | AK23: 2.668376 | AL23: 1.4325829 | AM23: 2.3533496 | AN23: 1.8423804 | AO23: 5.5279987 | AP23: 10.863052 | AQ23: 3.546738 | AR23: 2.1505264 | AS23: 3.1759185 | AT23: 3.5080326 | AU23: 2.673688 | AV23: 1.4340022 | AW23: 1.4576162 | AX23: 1.2766609 | AY23: 1.9197916 | AZ23: 1.313741 | BA23: 3.251459 | BB23: 2.0150446 | BC23: 1.6843534 | BD23: 1.7328149
A24: 22 | B24: M_Anisr | C24: 01.d | D24: 01.28 | E24: Anise, badian, fennel, coriander, market of | F24: tonnes | G24: 3.7871404 | H24: 4.6507947 | I24: 3.767965 | J24: 4.931778 | K24: 3.4517969 | L24: 4.7385496 | M24: 4.0211073 | N24: 6.7565675 | O24: 3.0932919 | P24: 3.7433517 | Q24: 3.9528739 | R24: 4.7373743 | S24: 3.8463307 | T24: 3.5017834 | U24: 4.077589 | V24: 3.858103 | W24: 3.5249829 | X24: 2.803352 | Y24: 3.378526 | Z24: 3.4354883 | AA24: 2.6926225 | AB24: 4.4714499 | AC24: 3.6035516 | AD24: 3.3230769 | AE24: 3.6938323 | AF24: 2.4702939 | AG24: 3.9598435 | AH24: 3.7020934 | AI24: 3.8887379 | AJ24: 3.7304874 | AK24: 3.7255264 | AL24: 0.80154073 | AM24: 3.9274877 | AN24: 3.8609806 | AO24: 4.1099744 | AP24: 3.7039196 | AQ24: 2.1681402 | AR24: 4.6474412 | AS24: 3.8150608 | AT24: 3.9669214 | AU24: 3.5991893 | AV24: 5.9121158 | AW24: 5.7831716 | AX24: 3.7504038 | AY24: 3.783648 | AZ24: 4.4046142 | BA24: 1.7090504 | BB24: 3.5742312 | BC24: 2.4872303 | BD24: 3.3937682
A25: 23 | B25: M_Appls | C25: 01.d | D25: 01.22 | E25: Apples, market of | F25: tonnes | G25: 0.26076093 | H25: 0.73233846 | I25: 0.37775826 | J25: 0.44384388 | K25: 0.31976275 | L25: 0.40499048 | M25: 0.34815868 | N25: 0.64055883 | O25: 0.57796205 | P25: 0.44130171 | Q25: 0.30171525 | R25: 0.37519531 | S25: 0.82315956 | T25: 0.3441387 | U25: 0.46745862 | V25: 0.33045928 | W25: 0.41734818 | X25: 0.20714687 | Y25: 0.54905748 | Z25: 0.63607656 | AA25: 0.35092055 | AB25: 0.55266936 | AC25: 0.40550764 | AD25: 0.3776642 | AE25: 0.43888877 | AF25: 1.2667482 | AG25: 0.75017059 | AH25: 0.61776478 | AI25: 0.60824375 | AJ25: 0.60311531 | AK25: 0.46050263 | AL25: 0.60007989 | AM25: 0.60272015 | AN25: 0.61276041 | AO25: 0.41645419 | AP25: 0.55349264 | AQ25: 0.42517949 | AR25: 0.50136526 | AS25: 0.42911864 | AT25: 0.41968685 | AU25: 0.42198256 | AV25: 0.40631253 | AW25: 0.65571656 | AX25: 0.35199037 | AY25: 0.57288681 | AZ25: 0.45665058 | BA25: 0.4725434 | BB25: 0.71021652 | BC25: 0.42600979 | BD25: 1.0345022
A26: 24 | B26: M_Apris | C26: 01.d | D26: 01.24 | E26: Apricots, market of | F26: tonnes | G26: 0.74810013 | H26: 2.3463007 | I26: 0.44025218 | J26: 0.68058493 | K26: 0.94290948 | L26: 0.63369049 | M26: 0.52275465 | N26: 3.2632935 | O26: 1.3636321 | P26: 1.2470827 | Q26: 0.53954564 | R26: 0.65639508 | S26: 0.49734984 | T26: 0.57108818 | U26: 0.62213915 | V26: 0.31522048 | W26: 0.62952025 | X26: 0.27730848 | Y26: 0.68670765 | Z26: 0.96283343 | AA26: 0.78342746 | AB26: 1.998271 | AC26: 0.60048985 | AD26: 1.1603532 | AE26: 0.66363277 | AF26: 2.2569039 | AG26: 0.60894446 | AH26: 0.56022033 | AI26: 0.38796376 | AJ26: 0.51406991 | AK26: 0.65850901 | AL26: 0.78419968 | AM26: 0.62390352 | AN26: 0.59994754 | AO26: 0.97774274 | AP26: 0.81703129 | AQ26: 0.34451481 | AR26: 0.65532807 | AS26: 0.58301653 | AT26: 0.63419926 | AU26: 1.7072815 | AV26: 0.79097052 | AW26: 0.015795712 | AX26: 0.61416336 | AY26: 0.72642871 | AZ26: 0.60184034 | BA26: 0.42888266 | BB26: 0.96903267 | BC26: 0.61535741 | BD26: 1.3570952
A27: 25 | B27: M_Arecs | C27: 01.d | D27: 01.25 | E27: Areca nuts, market of | F27: tonnes | G27: 2.1394317 | H27: 2.4143064 | I27: 1.8402256 | L27: 1.8134542 | M27: 1.7562436 | N27: 4.6401391 | O27: 0 | Q27: 2.1394317 | R27: 2.2183782 | T27: 2.7791443 | U27: 2.8480103 | V27: 8.7649931 | W27: 2.8698688 | X27: 2.8480103 | Y27: 2.4236421 | AA27: 2.8382738 | AB27: 10.011604 | AC27: 2.8477796 | AD27: 1.9451236 | AE27: 2.7181042 | AF27: 4.5273883 | AG27: 10.027341 | AJ27: 2.2183782 | AM27: 2.2183782 | AP27: 2.5473789 | AQ27: 2.2183782 | AS27: 2.8480103 | AV27: 2.2183782 | AW27: 0.017141534 | AX27: 3.2682153 | AY27: 5.0871412 | AZ27: 3.0894314 | BA27: 2.2424452 | BB27: 8.5834342 | BC27: 2.2982125 | BD27: 3.6720215
A28: 26 | B28: M_Artis | C28: 01.d | D28: 01.13 | E28: Artichokes, market of | F28: tonnes | G28: 0.74178628 | I28: 0.92822319 | J28: 0.71620476 | L28: 0.47460988 | M28: 0.88488044 | N28: 2.557272 | O28: 0.43967435 | P28: 0.66303295 | Q28: 0.73408666 | R28: 0.78410484 | S28: 0.52413876 | T28: 0.30113525 | U28: 0.86714515 | V28: 0.89881526 | W28: 0.82754995 | X28: 0.37789165 | Y28: 0.61724432 | Z28: 0.7121457 | AA28: 0.77102237 | AB28: 0.5032328 | AC28: 0.86041063 | AE28: 0.71495121 | AF28: 0.61153967 | AG28: 0.92822321 | AH28: 0.52093824 | AI28: 0.92796163 | AJ28: 0.78054179 | AK28: 0.35543405 | AL28: 0.65549415 | AM28: 0.84249262 | AN28: 0.84329238 | AO28: 0.87905944 | AP28: 0.51653669 | AQ28: 0.32037911 | AR28: 0.30296923 | AS28: 0.87750165 | AT28: 0.68121561 | AU28: 0.64502671 | AV28: 0.60377992 | AW28: 0.63321025 | AX28: 0.47465024 | AY28: 0.37372347 | AZ28: 0.5644214 | BA28: 0.14237781 | BB28: 0.78172195 | BC28: 0.26692678 | BD28: 0.14236938
A29: 27 | B29: M_Aspas | C29: 01.d | D29: 01.13 | E29: Asparagus, market of | F29: tonnes | G29: 1.4089679 | H29: 1.1918202 | I29: 1.0891574 | J29: 0.99505241 | K29: 0.85402695 | L29: 1.3517467 | M29: 1.4659514 | N29: 1.907229 | O29: 1.2730665 | P29: 1.8648314 | Q29: 1.271634 | R29: 1.3088134 | S29: 1.5557705 | T29: 0.77675835 | U29: 1.2320356 | V29: 1.2447451 | W29: 1.5104879 | X29: 0.67478852 | Y29: 1.7967633 | Z29: 0.93995017 | AA29: 1.0073251 | AB29: 0.99467326 | AC29: 1.5990176 | AD29: 0.74453215 | AE29: 0.95020644 | AF29: 1.9255864 | AG29: 1.0636689 | AH29: 0.83046298 | AI29: 1.1028938 | AJ29: 1.1417346 | AK29: 1.3017004 | AL29: 0.80973719 | AM29: 1.3618179 | AN29: 1.4022609 | AO29: 0.85468296 | AP29: 0.75278129 | AQ29: 1.2854855 | AR29: 0.80217842 | AS29: 1.2683709 | AT29: 1.3984874 | AU29: 1.1568639 | AV29: 1.5113224 | AW29: 0.40322777 | AX29: 0.92796287 | AY29: 0.66701837 | AZ29: 1.2578985 | BA29: 0.38698619 | BB29: 0.84944342 | BC29: 0.61253669 | BD29: 0.80916842
A30: 28 | B30: M_Avocs | C30: 01.d | D30: 01.22 | E30: Avocados, market of | F30: tonnes | G30: 0.9662699 | H30: 1.2833774 | I30: 0.91303013 | J30: 0.79356145 | K30: 0.45818322 | L30: 1.1375719 | M30: 0.96981984 | N30: 1.8612024 | O30: 0.99707763 | P30: 0.9487008 | Q30: 0.96157521 | R30: 0.9668186 | S30: 0.91189553 | T30: 0.78463521 | U30: 0.88406301 | V30: 0.79396537 | W30: 0.97523225 | X30: 0.73848795 | Y30: 0.92333203 | Z30: 0.94448426 | AA30: 0.94206903 | AB30: 0.57535305 | AC30: 1.0003849 | AD30: 1.1140311 | AE30: 0.88266921 | AF30: 1.0269757 | AG30: 1.126908 | AH30: 0.92624347 | AI30: 0.85041266 | AJ30: 0.83379256 | AK30: 0.94132192 | AL30: 1.0205271 | AM30: 1.0287287 | AN30: 1.0150558 | AO30: 0.8929162 | AP30: 0.74410478 | AQ30: 0.86578053 | AR30: 0.81026909 | AS30: 0.96922913 | AT30: 0.78766241 | AU30: 0.95631617 | AV30: 1.1357111 | AW30: 1.1778291 | AX30: 1.0600353 | AY30: 0.8784934 | AZ30: 1.0788409 | BA30: 0.41881523 | BB30: 0.97193377 | BC30: 0.67421928 | BD30: 1.5938457
A31: 29 | B31: M_Bambs | C31: 01.d | D31: 01.25 | E31: Bambara beans, market of | F31: tonnes | G31: 0.000412552 | I31: 0.000650395 | J31: 0.000535924 | L31: 0.00546233 | M31: 0.000651188 | N31: 1.0026368 | O31: 0.000306133 | P31: 6.27e-06 | Q31: 0.000675287 | R31: 0.000651188 | S31: 0.49010285 | T31: 0.84835078 | U31: 0.000651188 | V31: 0.001836074 | W31: 0.49027901 | X31: 0.000651188 | Y31: 1.0026368 | Z31: 0.000651188 | AA31: 0.000536882 | AB31: 0.000560084 | AE31: 3.26e-05 | AG31: 0.000368686 | AI31: 0.000368686 | AJ31: 0.000651188 | AK31: 0.000651188 | AM31: 0.000305396 | AN31: 0.000305396 | AO31: 0.000651188 | AP31: 0.000651188 | AQ31: 0.000415866 | AS31: 0.000646078 | AT31: 0.000309944 | AU31: 0.000343663 | AV31: 0.000368686 | AX31: 0.000612684 | AY31: 0.000869812 | BA31: 1.0002216 | BB31: 2.3e-05 | BC31: 0.003651127 | BD31: 0.000651188
A32: 30 | B32: M_Banas | C32: 01.d | D32: 01.22 | E32: Bananas, market of | F32: tonnes | G32: 0.41711765 | H32: 0.66417165 | I32: 0.41184975 | J32: 0.36318231 | K32: 0.49420343 | L32: 0.61452295 | M32: 0.42126912 | N32: 0.71755402 | O32: 0.62211174 | P32: 0.41171131 | Q32: 0.41937068 | R32: 0.4197433 | S32: 0.41842061 | T32: 0.31927718 | U32: 0.42159684 | V32: 0.38699461 | W32: 0.41634923 | X32: 0.42390511 | Y32: 0.37110193 | Z32: 0.43119067 | AA32: 0.41872928 | AB32: 0.17522797 | AC32: 0.42129928 | AD32: 0.2195334 | AE32: 0.41677605 | AF32: 0.36639099 | AG32: 0.36161468 | AH32: 0.41862753 | AI32: 0.41528633 | AJ32: 0.41701225 | AK32: 0.44731129 | AL32: 0.4714253 | AM32: 0.42184454 | AN32: 0.42219797 | AO32: 0.41874566 | AP32: 0.3610695 | AQ32: 0.40187046 | AR32: 0.42241471 | AS32: 0.421304 | AT32: 0.42826066 | AU32: 0.41396612 | AV32: 0.37038428 | AW32: 0.014923925 | AX32: 0.4253481 | AY32: 0.34356284 | AZ32: 0.41813996 | BA32: 0.35744659 | BB32: 0.42232654 | BC32: 0.40039197 | BD32: 0.99814932
A33: 31 | B33: M_Beann | C33: 01.d | D33: 01.25 | E33: Beans, green, market of | F33: tonnes | G33: 0.31913534 | H33: 0.97149686 | I33: 0.62308693 | J33: 0.40043668 | K33: 1.3125563 | L33: 0.76846097 | M33: 0.69620727 | N33: 0.27987309 | O33: 0.2396747 | P33: 1.2168402 | Q33: 0.46348265 | R33: 0.84765392 | S33: 0.88092536 | T33: 0.36643015 | U33: 1.199421 | V33: 0.57761429 | W33: 0.52870806 | X33: 0.35201216 | Y33: 0.32355688 | Z33: 1.0494906 | AA33: 0.3117783 | AB33: 0.59879309 | AC33: 0.7039605 | AD33: 0.88777556 | AE33: 0.56110473 | AF33: 0.35088232 | AG33: 1.2980355 | AH33: 0.9419824 | AI33: 0.81647269 | AJ33: 0.86569925 | AK33: 0.58897181 | AL33: 0.40956533 | AM33: 0.56529236 | AN33: 0.88329862 | AO33: 0.415178 | AP33: 0.36726155 | AQ33: 0.44687692 | AR33: 0.44133391 | AS33: 0.86301071 | AT33: 0.71393954 | AU33: 1.1402584 | AV33: 0.2422628 | AW33: 0.016408268 | AX33: 0.82653287 | AY33: 0.29847138 | AZ33: 1.6489049 | BA33: 0.14197542 | BB33: 0.97366995 | BC33: 0.30143399 | BD33: 1.0574546
A34: 32 | B34: M_Beany | C34: 01.d | D34: 01.25 | E34: Beans, dry, market of | F34: tonnes | G34: 1.4668593 | H34: 3.6361691 | I34: 2.0005173 | J34: 1.1642546 | K34: 3.2544586 | L34: 2.0772849 | M34: 2.1729129 | N34: 1.9548149 | O34: 2.2066219 | P34: 1.133865 | Q34: 1.7018852 | R34: 1.8680846 | S34: 1.4939001 | T34: 2.6477611 | U34: 1.7737203 | V34: 2.245721 | W34: 2.1120861 | X34: 1.535126 | Y34: 2.3055523 | Z34: 2.4922845 | AA34: 2.1591228 | AB34: 3.6056725 | AC34: 1.9691722 | AD34: 4.8581104 | AE34: 2.3745702 | AF34: 2.5136885 | AG34: 2.2057017 | AH34: 1.1334046 | AI34: 3.5973021 | AJ34: 1.4599952 | AK34: 1.5665931 | AL34: 4.0866102 | AM34: 1.7674948 | AN34: 1.6260662 | AO34: 1.7949494 | AP34: 2.2684061 | AQ34: 1.9381758 | AR34: 0.99416733 | AS34: 1.7834758 | AT34: 2.0230201 | AU34: 1.4561174 | AV34: 1.2795713 | AW34: 2.0962912 | AX34: 2.292711 | AY34: 0.79780971 | AZ34: 1.6421759 | BA34: 0.67098356 | BB34: 3.0809098 | BC34: 1.1422573 | BD34: 2.2889827
A35: 33 | B35: M_Berrs | C35: 01.d | D35: 01.25 | E35: Berries nes, market of | F35: tonnes | G35: 1.1500604 | H35: 1.6127295 | I35: 1.0839871 | J35: 2.8941578 | K35: 1.1319747 | L35: 1.6418214 | M35: 0.86186438 | N35: 1.3240512 | O35: 1.1904272 | P35: 2.3792011 | Q35: 1.384827 | R35: 1.0573426 | S35: 6.8120662 | T35: 0.62738012 | U35: 4.6231407 | V35: 0.78370663 | W35: 0.99051303 | X35: 0.87324068 | Y35: 0.83388338 | Z35: 4.8920586 | AA35: 0.84166378 | AB35: 0.99369308 | AC35: 1.2547952 | AD35: 0.56411712 | AE35: 0.91088682 | AF35: 0.54872527 | AH35: 3.8530672 | AI35: 1.0175338 | AJ35: 4.1378109 | AK35: 1.1888486 | AL35: 0.54827465 | AM35: 1.1159808 | AN35: 3.2097244 | AO35: 1.2547797 | AP35: 0.52191248 | AQ35: 0.5003955 | AR35: 0.97829475 | AS35: 4.3037493 | AT35: 1.2450159 | AU35: 0.86422866 | AV35: 0.77007515 | AX35: 0.81837929 | AY35: 0.74075002 | AZ35: 1.5992314 | BA35: 0.56413596 | BB35: 2.1430844 | BC35: 0.96681883 | BD35: 1.5873471
A36: 34 | B36: M_Blues | C36: 01.d | D36: 01.25 | E36: Blueberries, market of | F36: tonnes | G36: 1.7625331 | H36: 1.3635259 | I36: 1.5014456 | J36: 0.95031193 | K36: 0.76502722 | L36: 0.81843027 | M36: 1.6322458 | N36: 1.6047366 | O36: 2.7575707 | P36: 1.7900534 | Q36: 1.3937103 | R36: 2.4268439 | S36: 2.5535193 | T36: 0.59258434 | U36: 1.8726928 | V36: 1.6467655 | W36: 1.1278318 | X36: 2.4801838 | Y36: 0.88107286 | Z36: 1.4691205 | AA36: 1.8258903 | AB36: 0.96026234 | AC36: 1.3275044 | AD36: 2.5132752 | AE36: 1.2014777 | AF36: 0.81754812 | AG36: 0.78149839 | AH36: 2.876124 | AI36: 2.3600025 | AJ36: 2.1527473 | AK36: 1.6760072 | AL36: 0.70774247 | AM36: 1.5978913 | AN36: 2.2344928 | AO36: 2.082147 | AP36: 0.76060545 | AQ36: 1.4290275 | AR36: 0.59730227 | AS36: 2.0760536 | AT36: 1.527492 | AU36: 1.928926 | AV36: 1.9524153 | AW36: 0.84433035 | AX36: 0.79395019 | AY36: 1.7094505 | AZ36: 1.1775191 | BA36: 0.89514624 | BB36: 0.93760369 | BC36: 1.606503 | BD36: 0.77354092
A37: 35 | B37: M_Brazl | C37: 01.d | D37: 01.25 | E37: Brazil nuts, with shell, market of | F37: tonnes | G37: 1.1860819 | H37: 0.24929691 | I37: 0.009452516 | J37: 0.56424868 | K37: 0.24929691 | L37: 0.27134317 | M37: 1.3328178 | N37: 0.24993639 | O37: 0.077567598 | P37: 1.6835507 | Q37: 1.4819602 | R37: 1.6225535 | S37: 1.078822 | T37: 0.052758735 | V37: 0.91063131 | W37: 1.0712618 | X37: 1.124979 | Y37: 1.080643 | AC37: 0.76900296 | AD37: 0.26954716 | AE37: 1.1239319 | AF37: 0.27058499 | AG37: 0.69763757 | AH37: 1.0796223 | AI37: 0.037360127 | AJ37: 1.080643 | AK37: 1.0713552 | AL37: 0.27134317 | AM37: 1.7343402 | AN37: 1.6396977 | AO37: 1.1243421 | AP37: 1.1238937 | AQ37: 1.0713552 | AS37: 1.0974306 | AT37: 1.1005645 | AU37: 1.733911 | AX37: 0.27134375 | AY37: 0.26833439 | AZ37: 0.24939173 | BA37: 0.26949904 | BB37: 1.5551602 | BC37: 0.31878437 | BD37: 1.7652138
A38: 36 | B38: M_Broay | C38: 01.d | D38: 01.25 | E38: Broad beans, horse beans, dry, market of | F38: tonnes | G38: 1.3369469 | H38: 2.5546068 | I38: 1.8318033 | J38: 1.656473 | K38: 17.442099 | L38: 1.6351457 | M38: 1.3734376 | N38: 2.2332213 | O38: 1.2164589 | P38: 2.3364056 | Q38: 0.860073 | R38: 1.0390066 | S38: 1.0631106 | T38: 2.2773629 | U38: 0.9791679 | V38: 2.5822833 | W38: 0.75383776 | X38: 1.4031532 | Y38: 1.5409481 | Z38: 1.9051023 | AA38: 1.3048517 | AB38: 2.5345122 | AC38: 0.99560202 | AD38: 2.343805 | AE38: 2.1533226 | AF38: 2.3258677 | AH38: 1.0673914 | AI38: 2.1282813 | AJ38: 1.0673702 | AK38: 0.92766457 | AL38: 1.9933533 | AM38: 1.8136338 | AN38: 2.4889503 | AO38: 1.8663648 | AP38: 1.2396374 | AQ38: 2.5907029 | AR38: 1.7943264 | AS38: 0.84371917 | AT38: 2.173002 | AU38: 2.4679878 | AV38: 0.96907228 | AW38: 2.1927068 | AX38: 1.6854035 | AY38: 1.2458043 | AZ38: 1.3641497 | BA38: 0.46296898 | BB38: 1.7857871 | BC38: 1.4078262 | BD38: 0.72568646
A39: 37 | B39: M_Cabbs | C39: 01.d | D39: 01.13 | E39: Cabbages and other brassicas, market of | F39: tonnes | G39: 0.14228426 | H39: 0.39397873 | I39: 0.28778158 | J39: 0.23233387 | L39: 0.26623143 | M39: 0.3748258 | N39: 0.3298072 | O39: 0.18702232 | P39: 0.20390726 | Q39: 0.1514503 | R39: 0.17932002 | S39: 0.16731173 | T39: 0.14406689 | U39: 0.22002983 | V39: 0.26697571 | W39: 0.24906115 | X39: 0.15781756 | Y39: 0.26734951 | Z39: 0.23385985 | AA39: 0.20984966 | AB39: 0.30409605 | AC39: 0.24557408 | AD39: 0.1450889 | AE39: 0.35426445 | AF39: 0.54236088 | AG39: 0.28688458 | AH39: 0.16703947 | AI39: 0.29311487 | AJ39: 0.18647047 | AK39: 0.23486692 | AL39: 0.28736731 | AM39: 0.27802025 | AN39: 0.64162516 | AO39: 0.14547426 | AP39: 0.31444161 | AQ39: 0.17371199 | AR39: 0.18157675 | AS39: 0.17887301 | AT39: 0.23138737 | AU39: 0.15884763 | AV39: 0.21472528 | AW39: 0.046998519 | AX39: 0.26064474 | AY39: 0.18270085 | AZ39: 0.19123203 | BA39: 0.13196694 | BB39: 0.7511855 | BC39: 0.18306882 | BD39: 0.17264061
A40: 38 | B40: M_Carrs | C40: 01.d | D40: 01.13 | E40: Carrots and turnips, market of | F40: tonnes | G40: 0.1335582 | H40: 0.38232225 | I40: 0.19077577 | J40: 0.14889457 | K40: 0.29915235 | L40: 0.26713622 | M40: 0.36618364 | N40: 0.21728128 | O40: 0.21184829 | P40: 0.23238566 | Q40: 0.15725065 | R40: 0.18502839 | S40: 0.18414147 | T40: 0.097079197 | U40: 0.25734194 | V40: 0.18054929 | W40: 0.15901057 | X40: 0.1568791 | Y40: 0.21197596 | Z40: 0.25826385 | AA40: 0.13933425 | AB40: 0.36690477 | AC40: 0.16794481 | AD40: 0.21739638 | AE40: 0.2321803 | AF40: 0.55238607 | AG40: 0.29915826 | AH40: 0.21061363 | AI40: 0.25011293 | AJ40: 0.22490061 | AK40: 0.19402555 | AL40: 0.3164796 | AM40: 0.24743552 | AN40: 0.60350843 | AO40: 0.1604634 | AP40: 0.22948692 | AQ40: 0.25512373 | AR40: 0.19477894 | AS40: 0.16519489 | AT40: 0.2801747 | AU40: 0.20529598 | AV40: 0.08780533 | AW40: 0.082810783 | AX40: 0.29724444 | AY40: 0.10806326 | AZ40: 0.20421255 | BA40: 0.10685521 | BB40: 0.39322825 | BC40: 0.18076653 | BD40: 0.32275701
A41: 39 | B41: M_Cashe | C41: 01.d | D41: 01.22 | E41: Cashewapple, market of | F41: tonnes | K41: 2.0349691 | Y41: 1.9079279 | BA41: 0.7351175 | BB41: 0.98469586
A42: 40 | B42: M_Cashl | C42: 01.d | D42: 01.25 | E42: Cashew nuts, with shell, market of | F42: tonnes | G42: 2.8571949 | H42: 1.7081782 | I42: 3.6017834 | K42: 25.163019 | L42: 3.613498 | M42: 2.8915412 | N42: 3.8163633 | O42: 3.6202081 | P42: 2.8571949 | Q42: 2.9856732 | R42: 3.6343142 | S42: 3.2286399 | T42: 2.8581721 | U42: 2.865603 | V42: 3.6185321 | W42: 2.8571949 | Y42: 4.3797002 | AA42: 2.8571949 | AB42: 16.378545 | AC42: 2.8595141 | AD42: 3.5743049 | AE42: 3.2286395 | AF42: 1.8151931 | AG42: 1.7081782 | AH42: 3.6306059 | AI42: 3.5979571 | AJ42: 3.6306059 | AK42: 3.0669367 | AL42: 1.6517833 | AM42: 3.5601861 | AN42: 3.0262688 | AO42: 3.5601861 | AP42: 2.9403295 | AQ42: 3.2635395 | AR42: 1.7081782 | AS42: 3.6122373 | AT42: 3.2225777 | AU42: 2.8571949 | AV42: 3.3600551 | AW42: 10.628931 | AX42: 3.1655947 | AY42: 3.3112809 | AZ42: 3.9227091 | BA42: 3.6344452 | BB42: 6.0170893 | BC42: 3.6287827 | BD42: 3.2352526
A43: 41 | B43: M_Cassa | C43: 01.d | D43: 01.13 | E43: Cassava, market of | F43: tonnes | K43: 0.31766409 | N43: 0.51250279 | Y43: 0.20735 | AB43: 0.25036419 | AD43: 0.20290573 | AL43: 0.49618094 | AW43: 0.011243012 | AY43: 0.14926259 | BA43: 0.18589872 | BB43: 0.46635223
A44: 42 | B44: M_Casss | C44: 01.d | D44: 01.13 | E44: Cassava leaves | F44: tonnes | Y44: 0.18589872 | BA44: 0.18589872
A45: 43 | B45: M_Cauli | C45: 01.d | D45: 01.13 | E45: Cauliflowers and broccoli, market of | F45: tonnes | G45: 0.2795494 | H45: 0.58913446 | I45: 0.37434604 | J45: 0.37709004 | K45: 0.48532617 | L45: 0.40094114 | M45: 0.50085166 | N45: 0.55798547 | O45: 0.32782801 | P45: 0.34012664 | Q45: 0.28268944 | R45: 0.36770037 | S45: 0.36396544 | T45: 0.20666399 | U45: 0.47691228 | V45: 0.34164345 | W45: 0.44135345 | X45: 0.22931224 | Y45: 0.38098012 | Z45: 0.3954336 | AA45: 0.25491337 | AB45: 0.5247054 | AC45: 0.41629345 | AD45: 0.1648126 | AE45: 0.31712473 | AF45: 0.99095736 | AG45: 0.71157108 | AH45: 0.38358035 | AI45: 0.3628838 | AJ45: 0.46496172 | AK45: 0.20034102 | AL45: 0.46506203 | AM45: 0.47438311 | AN45: 0.70079195 | AO45: 0.26045109 | AP45: 0.40686579 | AQ45: 0.27025228 | AR45: 0.3786101 | AS45: 0.40453237 | AT45: 0.3582832 | AU45: 0.35639035 | AV45: 0.27218469 | AW45: 0.060372877 | AX45: 0.42202668 | AY45: 0.24658084 | AZ45: 0.42302055 | BA45: 0.098535242 | BB45: 0.91503195 | BC45: 0.20562285 | BD45: 1.0220277
A46: 44 | B46: M_Cherr | C46: 01.d | D46: 01.24 | E46: Cherries, sour, market of | F46: tonnes | G46: 0.77480666 | H46: 0.70800816 | I46: 0.89576665 | J46: 1.2440827 | K46: 0.71219504 | L46: 0.78952697 | M46: 1.2441576 | N46: 0.83660861 | O46: 0.58475426 | P46: 1.0212029 | Q46: 0.77565748 | R46: 1.0541129 | S46: 0.71960231 | T46: 0.96940676 | U46: 0.80990108 | V46: 0.89053311 | W46: 0.87543304 | X46: 0.43153887 | Y46: 0.71123793 | Z46: 1.3389163 | AA46: 0.69423153 | AB46: 0.72820977 | AC46: 0.82643473 | AD46: 0.72954474 | AE46: 1.2708154 | AF46: 0.70798148 | AG46: 0.70798146 | AH46: 0.72787177 | AI46: 0.94819503 | AJ46: 0.7527672 | AK46: 0.87752363 | AL46: 0.70798148 | AM46: 0.81955798 | AN46: 0.6929398 | AO46: 0.79978129 | AP46: 1.4790741 | AQ46: 0.84713792 | AR46: 0.6408615 | AS46: 0.82553233 | AT46: 1.0199106 | AU46: 1.0600579 | AV46: 0.60853416 | AW46: 0.71694672 | AX46: 0.70832215 | AY46: 0.70755389 | AZ46: 0.7407544 | BA46: 0.75988347 | BB46: 1.5589219 | BC46: 0.65353395
A47: 45 | B47: M_Chers | C47: 01.d | D47: 01.24 | E47: Cherries, market of | F47: tonnes | G47: 1.0281074 | H47: 1.2462308 | I47: 1.6484475 | J47: 0.9936489 | K47: 1.4446926 | L47: 0.76323508 | M47: 1.0066107 | N47: 1.5489327 | O47: 1.7011073 | P47: 1.7389638 | Q47: 1.1577599 | R47: 1.3169699 | S47: 2.9780815 | T47: 0.94722103 | U47: 2.5083756 | V47: 1.2420761 | W47: 1.4982123 | X47: 0.60640809 | Y47: 0.96427956 | Z47: 2.6225345 | AA47: 0.88429585 | AB47: 1.0814183 | AC47: 2.2872418 | AD47: 0.80579125 | AE47: 1.6984306 | AF47: 3.0412998 | AG47: 0.84534655 | AH47: 1.9506437 | AI47: 1.2683637 | AJ47: 1.8643748 | AK47: 2.8049549 | AL47: 1.0184675 | AM47: 1.1493512 | AN47: 1.3564557 | AO47: 1.0257883 | AP47: 1.8270654 | AQ47: 0.36664926 | AR47: 0.78798814 | AS47: 1.2871666 | AT47: 0.63235277 | AU47: 1.0105531 | AV47: 0.73057565 | AW47: 0.9416485 | AX47: 0.80612456 | AY47: 0.77668425 | AZ47: 1.0709897 | BA47: 1.1579335 | BB47: 1.4543896 | BC47: 0.7652952 | BD47: 2.6911754
A48: 46 | B48: M_Chest | C48: 01.d | D48: 01.25 | E48: Chestnut, market of | F48: tonnes | G48: 2.4947951 | H48: 2.7281982 | I48: 3.5384543 | J48: 1.2976152 | K48: 4.5352465 | L48: 2.5775708 | M48: 2.5755969 | N48: 1.6738881 | O48: 1.3766207 | P48: 2.0369334 | Q48: 2.9500529 | R48: 3.5465235 | S48: 2.5830349 | T48: 5.4404794 | U48: 2.3592269 | V48: 4.1781139 | W48: 2.4421484 | X48: 0.85999123 | Y48: 1.8699042 | Z48: 2.4477437 | AA48: 3.0810393 | AB48: 1.7515185 | AC48: 2.8801582 | AD48: 4.3337852 | AE48: 2.9733464 | AF48: 4.7605404 | AG48: 3.1219131 | AH48: 2.8158695 | AI48: 4.2297713 | AJ48: 2.7258396 | AK48: 2.6659399 | AL48: 2.2475804 | AM48: 1.865907 | AN48: 2.0759668 | AO48: 4.3337851 | AP48: 4.7602354 | AQ48: 1.8798283 | AR48: 1.6870547 | AS48: 2.6301186 | AT48: 2.3517104 | AU48: 2.1664624 | AV48: 2.1361225 | AW48: 1.7623972 | AX48: 2.251473 | AY48: 1.8546626 | AZ48: 2.3529466 | BA48: 2.3391516 | BB48: 2.6296979 | BC48: 1.7757403 | BD48: 1.3964335
A49: 47 | B49: M_Chick | C49: 01.d | D49: 01.11 | E49: Chick peas, market of | F49: tonnes | G49: 2.1700878 | H49: 2.883413 | I49: 2.1904946 | J49: 1.9684557 | K49: 1.719051 | L49: 2.1478189 | M49: 2.1424001 | N49: 0.74007558 | O49: 1.8609363 | P49: 2.150316 | Q49: 2.1251082 | R49: 2.169301 | S49: 2.2700204 | T49: 2.179715 | U49: 2.1472997 | V49: 2.157229 | W49: 2.4563596 | X49: 1.564608 | Y49: 2.2534811 | Z49: 2.0301061 | AA49: 2.1460419 | AB49: 1.104411 | AC49: 2.4408897 | AD49: 2.4673151 | AE49: 2.1458744 | AF49: 2.157734 | AG49: 2.2146819 | AH49: 2.1394964 | AI49: 3.3389162 | AJ49: 2.1614739 | AK49: 2.2186191 | AL49: 1.5926741 | AM49: 2.120384 | AN49: 2.0496481 | AO49: 2.0012941 | AP49: 2.2076536 | AQ49: 1.7261089 | AR49: 2.1596862 | AS49: 2.0811411 | AT49: 2.0160023 | AU49: 2.8251019 | AV49: 1.8673378 | AW49: 2.3362167 | AX49: 2.2849808 | AY49: 1.7017146 | AZ49: 1.2495464 | BA49: 0.64785966 | BB49: 1.8946236 | BC49: 2.0535954 | BD49: 2.4413156
A50: 48 | B50: M_Chics | C50: 01.d | D50: 01.13 | E50: Chicory roots, market of | F50: tonnes | G50: 0.45475363 | H50: 0.40770309 | I50: 0.34368468 | L50: 0.34399211 | M50: 0.67915142 | N50: 0.40770309 | P50: 0.39862125 | Q50: 0.67915142 | R50: 0.67915142 | T50: 0.29703452 | V50: 0.28952221 | W50: 0.86479046 | Y50: 0.40813155 | Z50: 0.41631671 | AA50: 0.6190151 | AE50: 0.64193166 | AH50: 0.39372621 | AI50: 0.86507512 | AJ50: 0.40539667 | AL50: 0.34486936 | AM50: 0.86323137 | AN50: 0.28411452 | AO50: 0.39552045 | AP50: 0.28826415 | AQ50: 0.46488288 | AR50: 0.39439928 | AS50: 0.67915142 | AT50: 0.6190151 | AU50: 0.42677923 | AW50: 0.40770309 | AX50: 0.34486935 | AY50: 0.25930575 | AZ50: 0.31355283 | BA50: 0.079806873 | BB50: 0.60461389 | BC50: 0.34644758 | BD50: 1.1207936
A51: 49 | B51: M_Clovs | C51: 01.d | D51: 01.28 | E51: Cloves, market of | F51: tonnes | G51: 10.612819 | H51: 14.491762 | I51: 9.5747772 | J51: 8.4364212 | K51: 18.685065 | L51: 14.480183 | M51: 9.9667956 | N51: 7.9454768 | O51: 8.7373754 | P51: 10.418825 | Q51: 10.698934 | R51: 10.053349 | S51: 9.3067948 | T51: 11.719161 | U51: 10.207697 | V51: 11.530942 | W51: 9.4507133 | X51: 8.5871441 | Y51: 19.045529 | Z51: 10.426632 | AA51: 11.251575 | AB51: 22.752319 | AC51: 9.6149836 | AD51: 9.7264929 | AE51: 9.8035557 | AF51: 6.4500492 | AG51: 16.185875 | AH51: 9.6041317 | AI51: 10.712142 | AJ51: 9.161112 | AK51: 9.8861978 | AL51: 13.741684 | AM51: 9.7444675 | AN51: 10.17357 | AO51: 10.665199 | AP51: 11.132231 | AQ51: 14.795191 | AR51: 8.0907426 | AS51: 8.6080297 | AT51: 11.27412 | AU51: 13.241307 | AV51: 16.95901 | AW51: 14.239258 | AX51: 13.28112 | AY51: 9.896441 | AZ51: 10.435295 | BA51: 6.9764529 | BB51: 12.851465 | BC51: 15.094316 | BD51: 8.8462386
A52: 50 | B52: M_Cocon | C52: 01.d | D52: 01.26 | E52: Coconuts, market of | F52: tonnes | G52: 0.69178048 | H52: 0.67760626 | I52: 0.6900285 | J52: 0.68204335 | K52: 0.44953702 | L52: 0.80318828 | M52: 0.67898094 | N52: 0.79144374 | O52: 0.67952075 | P52: 0.6805121 | Q52: 0.69625898 | R52: 0.74966163 | S52: 0.67246668 | T52: 0.67391254 | U52: 0.69342244 | V52: 0.80159004 | W52: 0.55941988 | X52: 0.68555571 | Y52: 0.69101943 | Z52: 0.67249081 | AA52: 0.68615621 | AB52: 0.79770095 | AC52: 0.58561616 | AD52: 0.47251966 | AE52: 0.72620529 | AF52: 0.68182949 | AG52: 0.6823217 | AH52: 0.68268395 | AI52: 0.70872148 | AJ52: 0.68469055 | AK52: 0.65632037 | AL52: 1.1996063 | AM52: 0.68287094 | AN52: 0.68368909 | AO52: 0.67519593 | AP52: 0.65556637 | AQ52: 0.68363876 | AR52: 0.67730005 | AS52: 0.68852127 | AT52: 0.70304745 | AU52: 0.68633123 | AV52: 0.60754374 | AW52: 0.05067343 | AX52: 0.89055394 | AY52: 0.68217959 | AZ52: 0.68241384 | BA52: 0.89561875 | BB52: 1.0129002 | BC52: 0.51056358 | BD52: 0.55807161
A53: 51 | B53: M_Coirr | C53: 01.d | D53: 01.26 | E53: Production of crude petroleum and services related to crude oil extraction, excluding surveying, market of | F53: tonnes | G53: 0 | H53: 0 | I53: 0 | J53: 0 | K53: 0 | L53: 0 | M53: 0 | N53: 0 | O53: 0 | P53: 0 | Q53: 0 | R53: 0 | S53: 0 | T53: 0 | U53: 0 | V53: 0 | W53: 0 | X53: 0 | Z53: 0 | AA53: 0 | AB53: 0 | AC53: 0 | AD53: 0 | AE53: 0 | AF53: 0 | AG53: 0 | AH53: 0 | AI53: 0 | AJ53: 0 | AK53: 0 | AL53: 0 | AM53: 0 | AN53: 0 | AO53: 0 | AP53: 0 | AQ53: 0 | AR53: 0 | AS53: 0 | AT53: 0 | AU53: 0 | AV53: 0 | AW53: 0 | AX53: 0 | AY53: 0 | AZ53: 0 | BA53: 0 | BB53: 0 | BC53: 0 | BD53: 0
A54: 52 | B54: M_Cowpea | C54: 01.d | D54: 01.11 | E54: Cow peas, dry, market of | F54: tonnes | G54: 2.1470924 | H54: 2.4892532 | I54: 2.6447281 | J54: 1.3277768 | K54: 2.5462608 | L54: 2.5326982 | M54: 2.5061794 | N54: 5.0749983 | O54: 2.3874222 | P54: 2.5576582 | Q54: 2.4900058 | R54: 2.5231122 | S54: 2.6450972 | T54: 2.5462969 | U54: 2.5874254 | V54: 2.3661792 | W54: 2.5182116 | X54: 2.5266602 | Y54: 1.3277782 | Z54: 1.3847302 | AA54: 1.5999011 | AB54: 1.3995669 | AC54: 2.522184 | AD54: 1.2991721 | AE54: 2.5892421 | AF54: 5.1064815 | AG54: 2.5278936 | AH54: 1.3275268 | AI54: 2.4900058 | AJ54: 1.3275268 | AK54: 2.5462608 | AL54: 2.5268011 | AM54: 2.6450971 | AN54: 2.0837793 | AP54: 2.5462623 | AQ54: 1.9682314 | AR54: 2.5462608 | AS54: 2.2665335 | AU54: 2.528943 | AV54: 1.7943498 | AX54: 2.5357775 | AY54: 0.85818666 | AZ54: 1.1284062 | BA54: 1.3198777 | BB54: 2.5509249 | BC54: 0.86834053 | BD54: 5.8756944
A55: 53 | B55: M_Crans | C55: 01.d | D55: 01.25 | E55: Cranberries, market of | F55: tonnes | G55: 0.3844332 | H55: 0 | I55: 0.38352017 | J55: 3.3946384 | K55: 0.041480788 | L55: 0.38076604 | M55: 0.39145391 | N55: 0.015659156 | O55: 1.2532923 | P55: 0.24651606 | Q55: 0.39231017 | R55: 0.38357586 | S55: 0.59482152 | T55: 0.38340557 | U55: 0.28268071 | V55: 0.3839867 | W55: 0.38253573 | X55: 1.7435567 | Y55: 0.33014784 | Z55: 0.38354944 | AA55: 0.28662601 | AB55: 0 | AC55: 0.38276512 | AD55: 0.38247265 | AE55: 0.38322611 | AF55: 0.2106319 | AG55: 0.073766114 | AH55: 0.71985504 | AI55: 0.31278815 | AJ55: 1.9747257 | AK55: 0.048441264 | AL55: 0.38239598 | AM55: 0.38357663 | AN55: 0.38356896 | AO55: 0.18133346 | AP55: 0.047181038 | AQ55: 0.45512075 | AR55: 0.526413 | AS55: 0.38352385 | AT55: 0.28352774 | AU55: 0.38366142 | AV55: 0.24431957 | AW55: 0.18030773 | AX55: 0.33430811 | AY55: 1.0410419 | AZ55: 0.54276681 | BA55: 0.73665494 | BB55: 0.38239598 | BC55: 0.38699261
A56: 54 | B56: M_Cucus | C56: 01.d | D56: 01.13 | E56: Cucumbers and gherkins, market of | F56: tonnes | G56: 0.14515892 | H56: 0.52148259 | I56: 0.20105466 | J56: 0.16614306 | L56: 0.35579493 | M56: 0.26639379 | N56: 0.42677701 | O56: 0.25325349 | P56: 0.2085281 | Q56: 0.19709024 | R56: 0.23914599 | S56: 0.19328847 | T56: 0.10125917 | U56: 0.28486824 | V56: 0.21779832 | W56: 0.21162933 | X56: 0.12309933 | Y56: 0.39676361 | Z56: 0.25832996 | AA56: 0.13736939 | AB56: 0.60796293 | AC56: 0.23759611 | AD56: 0.42640489 | AE56: 0.23645985 | AF56: 0.76371171 | AG56: 0.56123925 | AH56: 0.26264014 | AI56: 0.16194598 | AJ56: 0.17565707 | AK56: 0.17084094 | AL56: 0.31868005 | AM56: 0.29294111 | AN56: 0.52632043 | AO56: 0.17488873 | AP56: 0.25860048 | AQ56: 0.22568965 | AR56: 0.22682228 | AS56: 0.2214876 | AT56: 0.24564514 | AU56: 0.18954548 | AV56: 0.22794592 | AW56: 0.011952448 | AX56: 0.37958512 | AY56: 0.21019882 | AZ56: 0.24174686 | BA56: 0.49162617 | BB56: 0.89255062 | BC56: 0.21244528 | BD56: 0.96942968
A57: 55 | B57: M_Currs | C57: 01.d | D57: 01.25 | E57: Currants, market of | F57: tonnes | G57: 1.0079639 | H57: 0.95837708 | I57: 0.99571284 | J57: 1.5228862 | L57: 1.7050735 | M57: 1.4352579 | N57: 1.7475381 | O57: 4.6711528 | P57: 2.1748682 | Q57: 1.0285003 | R57: 0.64027036 | S57: 4.8370005 | T57: 0.60946208 | U57: 5.1249436 | V57: 1.0557008 | W57: 0.85871158 | X57: 1.8827174 | Y57: 0.80661219 | Z57: 0.84586329 | AA57: 0.93168776 | AC57: 1.0514362 | AD57: 2.0150768 | AE57: 1.2920065 | AF57: 2.1918344 | AH57: 1.9669144 | AI57: 0.8763882 | AJ57: 5.1505392 | AK57: 3.1660442 | AM57: 2.5930273 | AN57: 2.1509117 | AO57: 1.2020765 | AP57: 0.8337038 | AQ57: 2.7067024 | AR57: 0.54819312 | AS57: 4.1044615 | AT57: 1.6028733 | AU57: 6.9968354 | AV57: 3.1488989 | AX57: 1.7049364 | AY57: 0.77697172 | AZ57: 0.75650205 | BA57: 0.96033697 | BB57: 1.5699672 | BC57: 1.8584214
A58: 56 | B58: M_Dates | C58: 01.d | D58: 01.22 | E58: Dates, market of | F58: tonnes | G58: 0.68391647 | H58: 0.72111942 | I58: 0.70225827 | J58: 0.64361737 | K58: 0.698398 | L58: 0.7290655 | M58: 0.67030375 | N58: 1.5400389 | O58: 0.65651866 | P58: 0.65439394 | Q58: 0.69933146 | R58: 0.70900922 | S58: 0.7216496 | T58: 0.72142022 | U58: 0.67358727 | V58: 0.68773193 | W58: 0.68673564 | X58: 0.67823904 | Y58: 0.67810391 | Z58: 0.6760682 | AA58: 0.66777195 | AB58: 0.64551357 | AC58: 0.68613151 | AD58: 0.76982082 | AE58: 0.67753247 | AF58: 0.78076408 | AG58: 0.64625698 | AH58: 0.71944391 | AI58: 0.69249547 | AJ58: 0.76107652 | AK58: 0.64927802 | AL58: 1.1690126 | AM58: 0.66535583 | AN58: 0.72877654 | AO58: 0.64206811 | AP58: 0.85430947 | AQ58: 0.62866483 | AR58: 0.70382847 | AS58: 0.65955602 | AT58: 0.6604184 | AU58: 0.68860616 | AV58: 0.5670092 | AW58: 0.62846262 | AX58: 0.92727556 | AY58: 0.84757633 | AZ58: 0.48444977 | BA58: 0.69427441 | BB58: 0.93246604 | BC58: 0.62350478 | BD58: 0.6778305
A59: 57 | B59: M_Eggpl | C59: 01.d | D59: 01.13 | E59: Eggplants (aubergines), market of | F59: tonnes | G59: 0.39001731 | H59: 0.30661347 | I59: 0.40449294 | J59: 0.31129281 | L59: 0.44407933 | M59: 0.40106439 | N59: 0.67887978 | O59: 0.74267612 | P59: 0.38528178 | Q59: 0.41810964 | R59: 0.55093306 | S59: 0.38325233 | T59: 0.25337525 | U59: 0.59973381 | V59: 0.31747847 | W59: 0.48130389 | X59: 0.20433901 | Y59: 0.54322994 | Z59: 0.43995262 | AA59: 0.324175 | AB59: 0.5697976 | AC59: 0.54643703 | AD59: 0.27291382 | AE59: 0.54905327 | AF59: 1.411227 | AG59: 0.94627138 | AH59: 0.8992069 | AI59: 0.38096591 | AJ59: 0.39057032 | AK59: 0.40504417 | AL59: 0.43975293 | AM59: 0.62347362 | AN59: 0.57812575 | AO59: 0.49079837 | AP59: 0.43135306 | AQ59: 0.30564104 | AR59: 0.40230215 | AS59: 0.55853347 | AT59: 0.46004421 | AU59: 0.39022012 | AV59: 0.41084136 | AW59: 0.011977416 | AX59: 0.47862371 | AY59: 0.30813227 | AZ59: 0.46976151 | BA59: 0.19122997 | BB59: 0.93275428 | BC59: 0.31085167 | BD59: 0.19121176
A60: 58 | B60: M_Figss | C60: 01.d | D60: 01.22 | E60: Figs, market of | F60: tonnes | G60: 1.0426214 | H60: 2.86106 | I60: 1.002974 | J60: 0.66435477 | K60: 0.86420751 | L60: 0.99068586 | M60: 0.94644534 | N60: 3.3040457 | O60: 0.80050937 | P60: 1.0360528 | Q60: 1.0277882 | R60: 0.98578041 | S60: 0.99887512 | T60: 0.90722773 | U60: 0.99687988 | V60: 0.90500728 | W60: 0.92926287 | X60: 0.62025872 | Y60: 0.91603828 | Z60: 1.4402767 | AA60: 1.0140448 | AB60: 0.67133789 | AC60: 0.93654103 | AD60: 1.7355402 | AE60: 1.1128264 | AF60: 1.4751113 | AH60: 1.0261127 | AI60: 0.93480437 | AJ60: 1.0171394 | AK60: 1.1863852 | AL60: 1.270369 | AM60: 0.99126043 | AN60: 0.99558774 | AO60: 1.0291829 | AP60: 4.3524377 | AQ60: 0.76789287 | AR60: 0.80688661 | AS60: 0.95648033 | AT60: 1.1155607 | AU60: 1.0202336 | AV60: 0.79599803 | AW60: 0.96863347 | AX60: 0.65040569 | AY60: 0.72871544 | AZ60: 0.65772645 | BA60: 1.2467128 | BB60: 1.1728328 | BC60: 0.65251859 | BD60: 2.1167819
A61: 59 | B61: M_frtrop_nes | C61: 01.d | D61: 01.22 | E61: Fruit, tropical fresh nes, market of | F61: tonnes | G61: 0.79845137 | H61: 1.1748554 | I61: 0.82571431 | K61: 0.40947011 | L61: 0.84224506 | M61: 0.89283522 | N61: 2.666501 | O61: 1.3109762 | P61: 0.71540976 | Q61: 0.69544134 | R61: 0.71281635 | S61: 0.71393369 | T61: 0.43715145 | U61: 0.73122013 | V61: 0.65178608 | W61: 0.84840022 | X61: 0.71281422 | Y61: 0.9648689 | AA61: 0.71281422 | AB61: 0.5976349 | AC61: 0.7671963 | AD61: 0.28002575 | AE61: 0.71288536 | AF61: 0.95581492 | AG61: 0.9417965 | AH61: 0.7142274 | AI61: 0.82556301 | AJ61: 0.71388042 | AK61: 0.71281462 | AL61: 0.79663211 | AM61: 0.71281418 | AN61: 0.80828865 | AO61: 0.71291187 | AP61: 0.71281422 | AQ61: 0.71281422 | AR61: 2.130504 | AS61: 0.69115165 | AT61: 0.71373149 | AU61: 0.71281422 | AV61: 0.80852497 | AW61: 0.032495667 | AX61: 0.88105183 | AY61: 0.81318521 | AZ61: 0.93005992 | BA61: 0.63253807 | BB61: 0.64067318 | BC61: 0.52185246 | BD61: 0.80852497
A62: 60 | B62: M_Gooss | C62: 01.d | D62: 01.25 | E62: Gooseberries, market of | F62: tonnes | G62: 0.97080911 | I62: 0.9227211 | J62: 0.93506949 | M62: 0.67957652 | P62: 1.4074496 | Q62: 0.88140939 | S62: 4.2632609 | T62: 2.6541646 | U62: 1.8005384 | W62: 0.46099302 | Y62: 0.82633422 | AA62: 0.91908399 | AB62: 0.73231597 | AC62: 0.93506949 | AH62: 0.93506949 | AJ62: 3.9736209 | AM62: 0.93506949 | AO62: 0.93506949 | AR62: 0.77229832 | AU62: 0.93506949 | AY62: 0.73270042 | AZ62: 0.43550726
A63: 61 | B63: M_Grapf | C63: 01.d | D63: 01.21 | E63: Grapefruit (inc. pomelos), market of | F63: tonnes | G63: 0.42908288 | H63: 0.79609207 | I63: 0.44770269 | J63: 0.28975216 | K63: 0.33545655 | L63: 0.45584652 | M63: 0.38802637 | N63: 0.53311433 | O63: 0.68733781 | P63: 0.4071196 | Q63: 0.40851111 | R63: 0.46118183 | S63: 0.45616456 | T63: 0.3074536 | U63: 0.43916714 | V63: 0.41918888 | W63: 0.46662398 | X63: 0.34334753 | Y63: 0.4636181 | Z63: 0.3800371 | AA63: 0.35797712 | AB63: 0.45533285 | AC63: 0.42986008 | AD63: 0.21230672 | AE63: 0.48628595 | AF63: 0.48310928 | AG63: 0.49514336 | AH63: 0.48129084 | AI63: 0.42987841 | AJ63: 0.42860203 | AK63: 0.44285108 | AL63: 0.39696766 | AM63: 0.51566375 | AN63: 0.45111234 | AO63: 0.38623034 | AP63: 0.56991973 | AQ63: 0.38316633 | AR63: 0.43218701 | AS63: 0.45749349 | AT63: 0.4049061 | AU63: 0.37283355 | AV63: 0.26248337 | AW63: 0.036908718 | AX63: 0.43082917 | AY63: 0.4616195 | AZ63: 0.39859795 | BA63: 0.26417973 | BB63: 0.52625658 | BC63: 0.33104104 | BD63: 0.60917576
A64: 62 | B64: M_Graps | C64: 01.d | D64: 01.21 | E64: Grapes, market of | F64: tonnes | G64: 0.8833556 | H64: 0.75232615 | I64: 1.0689025 | J64: 0.80194012 | K64: 0.5330287 | L64: 0.61718576 | M64: 0.75622059 | N64: 1.0055561 | O64: 1.6817366 | P64: 1.1106385 | Q64: 0.657053 | R64: 1.032673 | S64: 0.95092001 | T64: 0.58944621 | U64: 1.0113251 | V64: 0.68103791 | W64: 0.83217989 | X64: 0.35353276 | Y64: 0.70912129 | Z64: 0.96281233 | AA64: 0.64784316 | AB64: 0.79473559 | AC64: 1.2363484 | AD64: 0.37127574 | AE64: 0.71676232 | AF64: 1.4820948 | AG64: 0.86869082 | AH64: 0.83916249 | AI64: 1.5481168 | AJ64: 0.81951611 | AK64: 1.4317102 | AL64: 0.68172267 | AM64: 0.85741469 | AN64: 0.9064849 | AO64: 0.89777341 | AP64: 1.1470405 | AQ64: 0.69868826 | AR64: 0.5231809 | AS64: 0.98969882 | AT64: 0.90335026 | AU64: 0.8588239 | AV64: 0.57760179 | AW64: 0.2116274 | AX64: 0.52891308 | AY64: 0.57788563 | AZ64: 0.59730006 | BA64: 0.40940302 | BB64: 1.0041341 | BC64: 0.44561749 | BD64: 1.1664799
A65: 63 | B65: M_Hazel | C65: 01.d | D65: 01.25 | E65: Hazelnuts, with shell, market of | F65: tonnes | G65: 3.0596805 | H65: 1.6625973 | I65: 2.4793127 | J65: 8.526959 | K65: 4.0336717 | L65: 1.6581088 | M65: 2.227309 | N65: 3.18214 | O65: 4.6317236 | P65: 2.2981235 | Q65: 2.1965059 | R65: 2.2329085 | S65: 2.9779596 | T65: 3.55392 | U65: 2.2791368 | V65: 2.0847647 | W65: 2.6856471 | X65: 1.5733728 | Y65: 4.1515538 | Z65: 9.2009762 | AA65: 5.209088 | AC65: 2.8308167 | AE65: 2.7592954 | AF65: 2.839174 | AG65: 2.7147267 | AH65: 2.9102476 | AI65: 2.2050628 | AJ65: 3.0514479 | AK65: 2.7506477 | AL65: 1.9302982 | AM65: 2.7147267 | AN65: 2.7650644 | AO65: 3.0766813 | AP65: 4.0079996 | AQ65: 2.7919063 | AR65: 3.3025905 | AS65: 2.6331733 | AT65: 2.5758741 | AU65: 2.3117267 | AV65: 5.0940486 | AW65: 1.6580179 | AX65: 1.6580764 | AY65: 3.0785089 | AZ65: 2.3437935 | BA65: 2.8300683 | BB65: 5.6453384 | BC65: 2.4745426 | BD65: 5.0948336
A66: 64 | B66: M_Jute | C66: 01.d | D66: 01.16 | E66: Jute, market of | F66: tonnes | G66: 0.63115402 | H66: 1.0212216 | I66: 0.63111201 | J66: 0.63098349 | K66: 0.81272595 | L66: 0.63338558 | M66: 0.62205517 | N66: 2.052417 | O66: 0.63486014 | P66: 0.63111688 | Q66: 0.63111571 | R66: 0.63184731 | S66: 0.63233245 | T66: 0.61756085 | U66: 0.63158153 | V66: 0.62725327 | W66: 0.63528543 | X66: 0.63670152 | Y66: 0.93532548 | Z66: 0.63105265 | AA66: 0.63247681 | AB66: 0.62338827 | AC66: 0.63460427 | AD66: 1.0854139 | AE66: 0.63105349 | AF66: 0.74237377 | AG66: 0.63132352 | AH66: 0.63334758 | AI66: 0.63118502 | AJ66: 0.6320228 | AK66: 0.63497903 | AL66: 0.63342 | AM66: 0.63436609 | AN66: 0.6325604 | AO66: 0.63116972 | AP66: 0.6621557 | AQ66: 0.63146486 | AR66: 0.63131256 | AS66: 0.63150692 | AT66: 0.63097418 | AU66: 0.6310533 | AV66: 0.62913655 | AW66: 0.63131184 | AX66: 0.63342534 | AY66: 0.63709552 | AZ66: 0.63154383 | BA66: 0.6122578 | BB66: 0.90866929 | BC66: 0.71884306 | BD66: 0.63483126
A67: 65 | B67: M_Kapol | C67: 01.d | D67: 01.29 | E67: Kapokseed in shell | F67: tonnes | Y67: 4.3083715 | AB67: 5.6842987 | AY67: 1.076118
A68: 66 | B68: M_Kapot | C68: 01.d | D68: 01.29 | E68: Kapok fruit, market of | F68: tonnes | Y68: 4.3083715
A69: 67 | B69: M_Kiwi | C69: 01.d | D69: 01.25 | E69: Kiwi fruit, market of | F69: tonnes | G69: 0.53508583 | H69: 0.41166595 | I69: 0.52734447 | J69: 0.21619925 | K69: 0.64052042 | L69: 0.51898312 | M69: 0.53033549 | N69: 1.1972914 | O69: 0.30546603 | P69: 0.39411561 | Q69: 0.50483664 | R69: 0.53075319 | S69: 0.36535599 | T69: 0.46644696 | U69: 0.50461509 | V69: 0.50732497 | W69: 0.55613334 | X69: 0.19043142 | Y69: 0.90908914 | Z69: 0.53203625 | AA69: 0.49586914 | AB69: 0.38812591 | AC69: 0.5539784 | AD69: 0.41424284 | AE69: 0.54752559 | AF69: 0.60890225 | AG69: 0.52463936 | AH69: 0.401504 | AI69: 0.53310305 | AJ69: 0.39509384 | AK69: 0.55587104 | AL69: 0.64902321 | AM69: 0.56767789 | AN69: 0.55655669 | AO69: 0.46727016 | AP69: 0.70434323 | AQ69: 0.31238348 | AR69: 0.42561665 | AS69: 0.53383958 | AT69: 0.50847244 | AU69: 0.47581361 | AV69: 0.41439772 | AW69: 0.38427953 | AX69: 0.55988307 | AY69: 0.32887194 | AZ69: 0.40069291 | BA69: 0.48674061 | BB69: 0.78343959 | BC69: 0.34594739 | BD69: 0.39058627
A70: 68 | B70: M_Kola | C70: 01.d | D70: 01.29 | E70: Kola nuts, market of | F70: tonnes | G70: 4.1180758 | H70: 4.1180758 | I70: 4.1180758 | K70: 4.1180758 | L70: 4.1180758 | M70: 4.1180758 | N70: 4.1180758 | P70: 4.1180758 | Q70: 4.1180758 | R70: 0.20590379 | T70: 4.1180758 | V70: 4.1180758 | W70: 4.1180758 | Y70: 4.1180758 | AC70: 4.1180758 | AE70: 4.1180758 | AF70: 4.1180758 | AI70: 4.1180758 | AL70: 4.1180758 | AM70: 4.1180758 | AN70: 0.20590379 | AO70: 4.1180758 | AP70: 4.1180758 | AS70: 4.1180758 | AT70: 4.1180758 | AU70: 4.1180758 | AX70: 4.1180758 | AY70: 4.1180758 | BA70: 4.1180758 | BB70: 4.1180758 | BC70: 4.1180758 | BD70: 4.1180758
A71: 69 | B71: M_Leeks | C71: 01.d | D71: 01.13 | E71: Leeks, other alliaceous vegetables, market of | F71: tonnes | G71: 0.46314984 | H71: 0.93811502 | I71: 0.49021842 | J71: 0.50192399 | L71: 0.66092967 | M71: 0.79490796 | N71: 1.0536311 | O71: 0.9344589 | P71: 0.61653053 | Q71: 0.43827471 | R71: 0.58525606 | S71: 0.67228289 | T71: 0.40113688 | U71: 0.65350387 | V71: 0.49396779 | W71: 0.5598016 | X71: 0.31061691 | Y71: 0.66171132 | Z71: 0.66578948 | AA71: 0.57610674 | AB71: 0.76719195 | AC71: 0.62825257 | AD71: 0.45562267 | AE71: 0.66163399 | AF71: 1.0418449 | AG71: 1.1301677 | AH71: 0.70117207 | AI71: 0.50412981 | AJ71: 0.71301663 | AK71: 0.64019212 | AL71: 0.78774948 | AM71: 0.8004746 | AN71: 0.87156886 | AO71: 0.66362123 | AP71: 0.46765958 | AQ71: 0.48681274 | AR71: 0.5959983 | AS71: 0.73179232 | AT71: 0.65444457 | AU71: 0.65167391 | AV71: 0.53935595 | AW71: 0.096625919 | AX71: 0.74289241 | AY71: 0.47232031 | AZ71: 0.5695808 | BA71: 1.3408205 | BB71: 0.47147978 | BC71: 0.5338696 | BD71: 1.3563792
A72: 70 | B72: M_Lemos | C72: 01.d | D72: 01.13 | E72: Lemons and limes, market of | F72: tonnes | G72: 0.42307803 | H72: 0.62494674 | I72: 0.42601946 | J72: 0.31506542 | K72: 0.2995356 | L72: 0.45430927 | M72: 0.43721438 | N72: 0.88023801 | O72: 0.76498258 | P72: 0.37071246 | Q72: 0.37993175 | R72: 0.42457309 | S72: 0.37960969 | T72: 0.32219273 | U72: 0.41314259 | V72: 0.39713464 | W72: 0.49547825 | X72: 0.30513509 | Y72: 0.50515179 | Z72: 0.41033944 | AA72: 0.36919688 | AB72: 0.6065349 | AC72: 0.45922235 | AD72: 0.34866223 | AE72: 0.52122033 | AF72: 0.56210967 | AG72: 0.38389463 | AH72: 0.36922679 | AI72: 0.42646376 | AJ72: 0.36368284 | AK72: 0.47757084 | AL72: 0.60823579 | AM72: 0.51787476 | AN72: 0.46967593 | AO72: 0.37925025 | AP72: 0.55630929 | AQ72: 0.34060637 | AR72: 0.47378602 | AS72: 0.40923351 | AT72: 0.40783278 | AU72: 0.36981608 | AV72: 0.31839815 | AW72: 0.17303339 | AX72: 0.46843923 | AY72: 0.72241333 | AZ72: 0.47820946 | BA72: 0.35783909 | BB72: 0.45649008 | BC72: 0.49310039 | BD72: 1.1058857
A73: 71 | B73: M_Lents | C73: 01.d | D73: 01.11 | E73: Lentils, market of | F73: tonnes | G73: 2.3648893 | H73: 3.917032 | I73: 2.4882258 | J73: 1.9110407 | K73: 2.8478565 | L73: 2.8389441 | M73: 2.5942584 | N73: 1.5200622 | O73: 2.6113286 | P73: 2.9608368 | Q73: 2.3577775 | R73: 2.1962769 | S73: 2.2691444 | T73: 2.8394973 | U73: 2.3540227 | V73: 3.5628631 | W73: 2.3954994 | X73: 2.3338875 | Y73: 2.5847403 | Z73: 2.7318469 | AA73: 2.6774952 | AB73: 2.0537958 | AC73: 2.4492319 | AD73: 2.7832176 | AE73: 2.6817529 | AF73: 2.5467357 | AG73: 2.7893663 | AH73: 2.476661 | AI73: 3.2238868 | AJ73: 2.1462102 | AK73: 2.1194099 | AL73: 2.9024704 | AM73: 2.3667832 | AN73: 1.9726559 | AO73: 1.9520735 | AP73: 2.8664516 | AQ73: 2.4261098 | AR73: 2.0684916 | AS73: 2.3275962 | AT73: 2.1077184 | AU73: 3.1482054 | AV73: 2.1930134 | AW73: 2.7333249 | AX73: 2.8586091 | AY73: 2.0364459 | AZ73: 2.0371909 | BA73: 1.4341301 | BB73: 2.8720827 | BC73: 2.3326672 | BD73: 2.403413
A74: 72 | B74: M_Letty | C74: 01.d | D74: 01.13 | E74: Lettuce and chicory, market of | F74: tonnes | G74: 0.3615751 | H74: 0.90427761 | I74: 0.4332279 | J74: 0.42973164 | K74: 0.85545909 | L74: 0.41328941 | M74: 0.47757338 | N74: 0.74928404 | O74: 0.82850734 | P74: 0.44090434 | Q74: 0.37861094 | R74: 0.36971548 | S74: 0.44415503 | T74: 0.2828649 | U74: 0.72541399 | V74: 0.36675138 | W74: 0.39013014 | X74: 0.25212632 | Y74: 0.62737653 | Z74: 0.51841202 | AA74: 0.35525883 | AB74: 0.7555436 | AC74: 0.43237159 | AD74: 0.47259515 | AE74: 0.55292127 | AF74: 1.2750415 | AG74: 0.82273122 | AH74: 0.42933213 | AI74: 0.43899415 | AJ74: 0.44826056 | AK74: 0.461793 | AL74: 0.55900949 | AM74: 0.6799006 | AN74: 0.80700661 | AO74: 0.43943788 | AP74: 0.53165112 | AQ74: 0.42722366 | AR74: 0.50285543 | AS74: 0.47042971 | AT74: 0.53360025 | AU74: 0.56642126 | AV74: 0.40213865 | AW74: 0.41757532 | AX74: 0.40144528 | AY74: 0.39792675 | AZ74: 0.66322546 | BA74: 0.1256578 | BB74: 0.85116843 | BC74: 0.34820935 | BD74: 0.78307578
A75: 73 | B75: M_Lupis | C75: 01.d | D75: 01.11 | E75: Lupins, market of | F75: tonnes | G75: 1.578524 | H75: 2.5594676 | L75: 1.9518057 | M75: 1.7798024 | Q75: 1.9566907 | T75: 2.4330769 | V75: 2.8875405 | X75: 1.2439938 | Y75: 2.3076624 | AA75: 2.0027718 | AE75: 2.5790521 | AH75: 3.0390947 | AJ75: 2.6391287 | AO75: 2.2357365 | AP75: 1.9567407 | AR75: 1.6334872 | AU75: 1.7276427 | AX75: 1.9518057 | AZ75: 2.3867852 | BA75: 0.69602445 | BB75: 1.9518057 | BC75: 1.8794933 | BD75: 1.9877172
A76: 74 | B76: M_Mangs | C76: 01.d | D76: 01.22 | E76: Mangoes, mangosteens, guavas, market of | F76: tonnes | G76: 0.58544555 | H76: 1.4342457 | I76: 0.4651837 | J76: 0.59276854 | K76: 0.39259226 | L76: 0.69304013 | M76: 0.6202843 | N76: 2.0429062 | O76: 0.51414069 | P76: 0.59819146 | Q76: 0.59419799 | R76: 0.59502851 | S76: 0.58343532 | T76: 0.54783773 | U76: 0.57752852 | V76: 0.4996024 | W76: 0.57187013 | X76: 0.57769775 | Y76: 0.586318 | Z76: 0.6034466 | AA76: 0.59882413 | AB76: 0.52873501 | AC76: 0.5654678 | AD76: 0.45081119 | AE76: 0.58154541 | AF76: 1.4251284 | AG76: 0.54289594 | AH76: 0.57717292 | AI76: 0.45050747 | AJ76: 0.59093319 | AK76: 0.5951398 | AL76: 0.6924639 | AM76: 0.60971646 | AN76: 0.59114938 | AO76: 0.55446151 | AP76: 0.47975982 | AQ76: 0.60323138 | AR76: 0.55260075 | AS76: 0.57901133 | AT76: 0.4914392 | AU76: 0.59607727 | AV76: 0.57703182 | AW76: 0.027751012 | AX76: 0.73550459 | AY76: 0.53464027 | AZ76: 0.53600972 | BA76: 0.34102407 | BB76: 0.95870997 | BC76: 0.43293511 | BD76: 1.1279003
A77: 75 | B77: M_Mate | C77: 01.d | D77: 01.29 | E77: Mate, market of | F77: tonnes | G77: 0.49826131 | H77: 0.48766783 | I77: 0.49248268 | J77: 0.49252341 | K77: 0.50922952 | L77: 0.48822885 | M77: 0.49392662 | N77: 0.48507641 | O77: 0.48700771 | P77: 0.49901497 | Q77: 0.50005406 | R77: 0.50012997 | S77: 0.49920316 | T77: 0.49038728 | U77: 0.50560355 | V77: 0.49166256 | W77: 0.49308391 | X77: 0.49104569 | Y77: 0.49871974 | Z77: 0.49838299 | AA77: 0.4992069 | AB77: 0.4927797 | AC77: 0.49614611 | AD77: 0.49325239 | AE77: 0.49220681 | AF77: 0.49431329 | AG77: 0.49077548 | AH77: 0.49519592 | AI77: 0.49831956 | AJ77: 0.49772692 | AK77: 0.49799839 | AL77: 0.49042936 | AM77: 0.49083587 | AN77: 0.48947191 | AO77: 0.49663795 | AP77: 0.50573375 | AQ77: 0.49931447 | AR77: 0.48982979 | AS77: 0.48254448 | AT77: 0.49876015 | AU77: 0.49909377 | AV77: 0.49108657 | AW77: 0.49238391 | AX77: 0.49534169 | AY77: 0.4918704 | AZ77: 0.49090822 | BA77: 0.49298829 | BB77: 0.4836556 | BC77: 0.48149473 | BD77: 0.49999944
A78: 76 | B78: M_Melon | C78: 01.d | D78: 01.13 | E78: Melons, other (inc.cantaloupes), market of | F78: tonnes | G78: 0.54333858 | H78: 0.5209115 | I78: 0.49324387 | J78: 0.23878202 | K78: 0.26738308 | L78: 0.34871645 | M78: 0.42228414 | N78: 0.70326425 | O78: 0.66675303 | P78: 0.50127301 | Q78: 0.41240516 | R78: 0.53864173 | S78: 0.55425753 | T78: 0.25777601 | U78: 0.59544307 | V78: 0.35162723 | W78: 0.40141994 | X78: 0.19699592 | Y78: 0.51359819 | Z78: 0.47551903 | AA78: 0.28516083 | AB78: 0.38552739 | AC78: 0.5204228 | AD78: 0.25285564 | AE78: 0.47612569 | AF78: 1.2422624 | AG78: 0.70672163 | AH78: 0.56554936 | AI78: 0.44757078 | AJ78: 0.50560002 | AK78: 0.42018531 | AL78: 0.41625928 | AM78: 0.40771572 | AN78: 0.64741108 | AO78: 0.56876463 | AP78: 0.41554962 | AQ78: 0.30115017 | AR78: 0.45362894 | AS78: 0.49331977 | AT78: 0.50017423 | AU78: 0.44015844 | AV78: 0.3298559 | AW78: 0.033933963 | AX78: 0.49540892 | AY78: 0.25644126 | AZ78: 0.5337326 | BA78: 0.10252789 | BB78: 0.71226476 | BC78: 0.29460882 | BD78: 1.2051555
A79: 77 | B79: M_Nutss | C79: 01.d | D79: 01.25 | E79: Nuts nes, market of | F79: tonnes | G79: 2.244823 | H79: 2.2620628 | I79: 2.3753344 | J79: 3.1609559 | K79: 5.0775879 | L79: 3.8518019 | M79: 2.4613605 | N79: 1.920542 | O79: 2.4051683 | P79: 2.4772778 | Q79: 2.2258308 | R79: 2.7926757 | S79: 3.2119643 | T79: 1.8286821 | U79: 2.6693445 | V79: 2.8624139 | W79: 3.1199194 | X79: 2.4210605 | Y79: 2.8614402 | Z79: 2.3417076 | AA79: 2.349919 | AB79: 8.5437296 | AC79: 2.955624 | AD79: 2.4885963 | AE79: 1.819162 | AF79: 2.4825332 | AG79: 2.5009959 | AH79: 3.0594221 | AI79: 2.1904595 | AJ79: 2.6056452 | AK79: 2.4220003 | AL79: 1.9978226 | AM79: 2.8078733 | AN79: 2.3244599 | AO79: 2.3879098 | AP79: 1.490076 | AQ79: 2.6082275 | AR79: 1.1215656 | AS79: 2.8164704 | AT79: 1.6519343 | AU79: 2.4084917 | AV79: 1.4720156 | AW79: 2.7592381 | AX79: 3.7266613 | AY79: 2.0178475 | AZ79: 2.3870952 | BA79: 1.668426 | BB79: 1.5260722 | BC79: 1.7516786 | BD79: 1.6240148
A80: 78 | B80: M_oFru_cit | C80: 01.d | D80: 01.23 | E80: Fruit, citrus nes, market of | F80: tonnes | G80: 0.88767421 | H80: 0.72193941 | I80: 0.77577984 | J80: 0.47911169 | K80: 0.79091909 | L80: 1.1598945 | M80: 0.7505827 | N80: 0.50673515 | O80: 0.88951209 | P80: 0.87143337 | Q80: 0.80520845 | R80: 0.97946601 | S80: 0.95095467 | T80: 1.342391 | U80: 0.86371053 | V80: 1.0114462 | W80: 1.084588 | X80: 0.44131364 | Y80: 0.56995853 | Z80: 0.4383036 | AA80: 0.98189971 | AB80: 0.79091909 | AC80: 0.99788178 | AD80: 0.30876896 | AE80: 0.48358392 | AF80: 1.2616205 | AG80: 0.59916954 | AH80: 0.88404996 | AI80: 0.84785781 | AJ80: 0.97449715 | AK80: 0.54802821 | AL80: 1.3821703 | AM80: 0.94503984 | AN80: 0.89844495 | AO80: 0.76149814 | AP80: 1.3674756 | AQ80: 0.83393874 | AR80: 0.4792505 | AS80: 0.87147717 | AT80: 0.65295074 | AU80: 0.92793448 | AV80: 0.48976926 | AW80: 0.013179928 | AX80: 0.47705267 | AY80: 0.75573071 | AZ80: 0.51901724 | BA80: 0.61407128 | BB80: 0.90476185 | BC80: 0.39958599 | BD80: 1.0177442
A81: 79 | B81: M_oFru_fresh | C81: 01.d | D81: 01.29 | E81: Fruit, fresh nes, market of | F81: tonnes | G81: 1.0519622 | H81: 0.634606 | I81: 0.75007878 | J81: 2.2598878 | K81: 0.67299383 | L81: 0.63822732 | M81: 0.7776184 | N81: 2.2274418 | O81: 0.84917771 | P81: 1.2567074 | Q81: 0.75177402 | R81: 0.58833989 | S81: 2.6965447 | T81: 0.50412777 | U81: 0.70609729 | V81: 0.66155755 | W81: 0.72199257 | X81: 0.70048482 | Y81: 0.81565082 | Z81: 0.4815956 | AA81: 1.3480426 | AB81: 0.56270587 | AC81: 0.64783777 | AD81: 0.50530509 | AE81: 1.069549 | AF81: 0.7045501 | AG81: 2.2858454 | AH81: 1.0321721 | AI81: 0.74039367 | AJ81: 1.296113 | AK81: 0.75917849 | AL81: 1.0392472 | AM81: 0.81689877 | AN81: 0.72145467 | AO81: 0.96289825 | AP81: 0.64613394 | AQ81: 0.31237831 | AR81: 0.61876237 | AS81: 0.62601446 | AT81: 0.73206482 | AU81: 1.1023192 | AV81: 0.42584659 | AW81: 0.027282302 | AX81: 0.96503348 | AY81: 0.72094769 | AZ81: 0.66816412 | BA81: 0.48668122 | BB81: 0.98268211 | BC81: 0.79302268 | BD81: 1.3478372
A82: 80 | B82: M_oFru_pom | C82: 01.d | D82: 01.24 | E82: Fruit, pome nes, market of | F82: tonnes | Y82: 1.4800426 | AY82: 1.4825742 | AZ82: 1.3434119
A83: 81 | B83: M_oFru_ston | C83: 01.d | D83: 01.24 | E83: Fruit, stone nes, market of | F83: tonnes | N83: 2.0888127 | Q83: 0.55251437 | U83: 2.6102498 | V83: 0.87609281 | X83: 1.0516826 | Y83: 1.3089497 | AA83: 0.91078528 | AD83: 1.1812669 | AE83: 0.78548787 | AF83: 5.9655372 | AK83: 1.1112922 | AO83: 1.8569279 | AP83: 1.6260101 | AV83: 1.0784227 | AY83: 1.1036633 | AZ83: 0.79393368 | BA83: 0.56300822 | BC83: 0.95773096
A84: 82 | B84: M_Okraa | C84: 01.d | D84: 01.13 | E84: Okra, market of | F84: tonnes | H84: 0.63930394 | I84: 0.63930394 | K84: 0.63930394 | L84: 0.63953777 | M84: 0.63930394 | N84: 0.63930394 | O84: 0.89703865 | Q84: 0.63930394 | R84: 0.63930394 | T84: 0.63930394 | V84: 0.63930394 | W84: 0.63930435 | Y84: 0.43433951 | AC84: 0.63930394 | AD84: 0.33448679 | AF84: 0.63930394 | AK84: 0.63930394 | AL84: 0.91168249 | AM84: 0.63930394 | AN84: 0.63930394 | AR84: 0.63930394 | AS84: 0.63930394 | AV84: 1.1823575 | AX84: 0.8431814 | AY84: 0.31927654 | AZ84: 0.61297653 | BA84: 0.63930394 | BB84: 0.93300068 | BC84: 0.66344831 | BD84: 0.63930394
A85: 83 | B85: M_Olivs | C85: 01.d | D85: 01.26 | E85: Olives, market of | F85: tonnes | G85: 1.4674631 | H85: 1.7827812 | I85: 1.9560191 | J85: 0.93416927 | K85: 3.8073459 | L85: 1.4685334 | M85: 1.4079817 | N85: 1.7838651 | O85: 3.1898823 | P85: 1.7876329 | Q85: 1.2801394 | R85: 2.318819 | S85: 2.1922553 | T85: 1.0087091 | U85: 2.4597753 | V85: 3.2658225 | W85: 2.1910574 | X85: 0.90428501 | Y85: 1.3903328 | Z85: 2.1818967 | AA85: 1.4963512 | AB85: 2.3194115 | AC85: 2.201431 | AD85: 0.99695896 | AE85: 2.3420866 | AF85: 2.3014067 | AG85: 2.4386752 | AH85: 2.3505376 | AI85: 2.0352145 | AJ85: 2.2989968 | AK85: 1.7658563 | AL85: 0.92246963 | AM85: 1.8825702 | AN85: 2.1132584 | AO85: 1.7107626 | AP85: 2.4438417 | AQ85: 1.034769 | AR85: 1.5500096 | AS85: 1.9485982 | AT85: 3.0517495 | AU85: 2.2529068 | AV85: 1.3382125 | AW85: 0.17852887 | AX85: 0.7221508 | AY85: 1.8675295 | AZ85: 1.7478092 | BA85: 2.062248 | BB85: 1.610212 | BC85: 1.1784973
A86: 84 | B86: M_Onion | C86: 01.d | D86: 01.13 | E86: Onions, shallots, green, market of | F86: tonnes | G86: 0.25413052 | H86: 0.53715823 | I86: 0.27478569 | J86: 0.35713774 | K86: 0.39148576 | L86: 0.41122033 | M86: 0.53470288 | N86: 0.38485811 | O86: 1.6008211 | P86: 0.26247263 | Q86: 0.19372821 | R86: 0.23530084 | S86: 0.53018734 | T86: 0.17700728 | U86: 0.37165867 | V86: 0.29455709 | W86: 0.4377843 | X86: 0.25634576 | Y86: 0.36214435 | Z86: 0.2476095 | AA86: 0.26486047 | AB86: 0.25281428 | AC86: 0.32200326 | AE86: 0.28319175 | AF86: 0.7438167 | AG86: 0.5578162 | AH86: 0.45371739 | AI86: 0.28190409 | AJ86: 0.50480537 | AK86: 0.3800435 | AL86: 0.46723803 | AM86: 0.41901585 | AN86: 0.63671232 | AO86: 0.4743291 | AP86: 0.29147894 | AQ86: 0.34370372 | AR86: 0.34378943 | AS86: 0.24864337 | AT86: 0.2598476 | AU86: 0.28209751 | AV86: 0.21258553 | AW86: 0.031370945 | AX86: 0.36284364 | AY86: 0.26246074 | AZ86: 0.33335054 | BA86: 0.10008267 | BB86: 0.97990845 | BC86: 0.34383195 | BD86: 0.56266173
A87: 85 | B87: M_Onioy | C87: 01.d | D87: 01.13 | E87: Onions, dry, market of | F87: tonnes | G87: 0.20536278 | H87: 0.51257258 | I87: 0.35840832 | J87: 0.28563513 | K87: 0.39494162 | L87: 0.35989525 | M87: 0.32312217 | N87: 0.56305126 | O87: 0.65332537 | P87: 0.29390233 | Q87: 0.19250862 | R87: 0.21587857 | S87: 0.6023514 | T87: 0.22326653 | U87: 0.37665582 | V87: 0.30189533 | W87: 0.28031881 | X87: 0.14361613 | Y87: 0.36755414 | Z87: 0.33338476 | AA87: 0.25980222 | AB87: 0.56729228 | AC87: 0.39231436 | AD87: 0.2005739 | AE87: 0.41710129 | AF87: 0.92845204 | AG87: 0.44470334 | AH87: 0.34468149 | AI87: 0.31131035 | AJ87: 0.44312999 | AK87: 0.46435101 | AL87: 0.42033832 | AM87: 0.50056607 | AN87: 0.42626885 | AO87: 0.37422387 | AP87: 0.40924095 | AQ87: 0.3507434 | AR87: 0.32393916 | AS87: 0.20580743 | AT87: 0.36827354 | AU87: 0.24563983 | AV87: 0.22600807 | AW87: 0.2306052 | AX87: 0.33930903 | AY87: 0.28683171 | AZ87: 0.30111087 | BA87: 0.20818284 | BB87: 0.71950105 | BC87: 0.27951237 | BD87: 0.55241744
A88: 86 | B88: M_Orans | C88: 01.d | D88: 01.23 | E88: Oranges, market of | F88: tonnes | G88: 0.34803329 | H88: 0.70446789 | I88: 0.3391315 | J88: 0.18223537 | K88: 0.28386343 | L88: 0.49764982 | M88: 0.43789659 | N88: 0.79127864 | O88: 0.77135604 | P88: 0.26232581 | Q88: 0.3013267 | R88: 0.30551869 | S88: 0.33197332 | T88: 0.28557153 | U88: 0.34250815 | V88: 0.31690832 | W88: 0.37126926 | X88: 0.16152321 | Y88: 0.41642255 | Z88: 0.27871342 | AA88: 0.21226813 | AB88: 0.22704914 | AC88: 0.36179085 | AD88: 0.28979417 | AE88: 0.53356659 | AF88: 0.71402542 | AG88: 0.50245588 | AH88: 0.33571981 | AI88: 0.3961146 | AJ88: 0.32534286 | AK88: 0.38312952 | AL88: 0.61462644 | AM88: 0.38812385 | AN88: 0.34905179 | AO88: 0.28495803 | AP88: 0.52765553 | AQ88: 0.22267444 | AR88: 0.37820954 | AS88: 0.3326754 | AT88: 0.35194687 | AU88: 0.26220357 | AV88: 0.28144618 | AW88: 0.11363753 | AX88: 0.50493548 | AY88: 0.42319488 | AZ88: 0.39236716 | BA88: 0.27064013 | BB88: 0.5408846 | BC88: 0.36833738 | BD88: 0.4715008
A89: 87 | B89: M_oVege_fresh | C89: 01.d | D89: 01.13 | E89: Vegetables, fresh nes, market of | F89: tonnes | G89: 0.37283481 | H89: 0.64549656 | I89: 0.38865654 | J89: 0.80820116 | K89: 0.97011562 | L89: 0.3625865 | M89: 0.53752453 | N89: 0.82448343 | O89: 0.57973489 | P89: 0.60583459 | Q89: 0.41399452 | R89: 0.52841819 | S89: 0.53646111 | T89: 0.27864365 | U89: 0.40225917 | V89: 0.37725034 | W89: 0.37398053 | X89: 0.24654822 | Y89: 0.64823078 | Z89: 0.62475961 | AA89: 0.39380145 | AB89: 0.59803189 | AC89: 0.56264629 | AD89: 0.3445399 | AE89: 0.53939854 | AF89: 1.0343911 | AG89: 0.4347067 | AH89: 0.38443647 | AI89: 0.48985381 | AJ89: 0.4872504 | AK89: 0.36363607 | AL89: 0.88929158 | AM89: 0.72780747 | AN89: 0.65186386 | AO89: 0.36334902 | AP89: 0.50592015 | AQ89: 0.36825141 | AR89: 0.39086986 | AS89: 0.52684375 | AT89: 0.50798162 | AU89: 0.50001139 | AV89: 0.39352703 | AW89: 0.097268537 | AX89: 0.50710324 | AY89: 0.3742367 | AZ89: 0.65425641 | BA89: 0.33508254 | BB89: 0.57770547 | BC89: 0.4820345 | BD89: 1.2080865
A90: 88 | B90: M_palm | C90: 01.d | D90: 01.11 | E90: Oil palm fruit, market of | F90: tonnes | K90: 1.1028147 | N90: 1.0000129 | Y90: 0.64503377 | AB90: 0.58661385 | AL90: 0.89497298 | AY90: 0.6562882 | BA90: 0.98367705 | BB90: 0.77617231
A91: 89 | B91: M_Papas | C91: 01.d | D91: 01.22 | E91: Papayas, market of | F91: tonnes | G91: 0.30400073 | H91: 0.66302384 | I91: 0.40784043 | J91: 0.29699106 | K91: 0.27592622 | L91: 0.41300291 | M91: 0.27952022 | N91: 1.0041694 | O91: 0.31735787 | P91: 0.31585082 | Q91: 0.31488165 | R91: 0.30343926 | S91: 0.33724048 | T91: 0.30365803 | U91: 0.30127817 | V91: 0.28357639 | W91: 0.42497314 | X91: 0.29666928 | Y91: 0.31154075 | Z91: 0.29435694 | AA91: 0.30623102 | AB91: 0.13061435 | AC91: 0.33296946 | AD91: 0.21109383 | AE91: 0.28945768 | AF91: 0.39328762 | AG91: 0.40880822 | AH91: 0.32948422 | AI91: 0.35255201 | AJ91: 0.36048557 | AK91: 0.29440423 | AL91: 0.34537306 | AM91: 0.29467878 | AN91: 0.28640275 | AO91: 0.29137725 | AP91: 0.27782528 | AQ91: 0.29554556 | AR91: 0.40032517 | AS91: 0.32911045 | AT91: 0.33293305 | AU91: 0.31241998 | AV91: 0.29467883 | AW91: 0.014554294 | AX91: 0.39730857 | AY91: 0.40843473 | AZ91: 0.88028482 | BA91: 0.2926729 | BB91: 0.67379304 | BC91: 0.35689896 | BD91: 1.3091392
A92: 90 | B92: M_Peacs | C92: 01.d | D92: 01.24 | E92: Peaches and nectarines, market of | F92: tonnes | G92: 0.33032388 | H92: 0.87414864 | I92: 0.27724047 | J92: 0.40356039 | K92: 0.5465008 | L92: 0.48457994 | M92: 0.28677647 | N92: 0.8648731 | O92: 0.44754671 | P92: 0.31049767 | Q92: 0.24984705 | R92: 0.30916343 | S92: 0.2340404 | T92: 0.21793227 | U92: 0.32838521 | V92: 0.28950289 | W92: 0.30419023 | X92: 0.22893315 | Y92: 0.70245214 | Z92: 0.491994 | AA92: 0.44126231 | AB92: 0.84341132 | AC92: 0.28655682 | AD92: 0.40393665 | AE92: 0.3095447 | AF92: 1.1571815 | AG92: 1.3482911 | AH92: 0.23184583 | AI92: 0.31263162 | AJ92: 0.2559907 | AK92: 0.29108883 | AL92: 0.92252284 | AM92: 0.3464796 | AN92: 0.31209287 | AO92: 0.3288617 | AP92: 0.41179685 | AQ92: 0.26386493 | AR92: 0.61610149 | AS92: 0.27324639 | AT92: 0.33802421 | AU92: 1.5300303 | AV92: 0.31218643 | AW92: 0.24096169 | AX92: 0.44603345 | AY92: 0.85254357 | AZ92: 0.46875065 | BA92: 0.32570232 | BB92: 0.78990167 | BC92: 0.33063859 | BD92: 0.98122286
A93: 91 | B93: M_Pears | C93: 01.d | D93: 01.24 | E93: Pears, market of | F93: tonnes | G93: 0.19033004 | H93: 0.5272483 | I93: 0.24022869 | J93: 0.40363817 | K93: 0.60464448 | L93: 0.46011762 | M93: 0.35354629 | N93: 0.61695304 | O93: 0.31882095 | P93: 0.34551186 | Q93: 0.39203659 | R93: 0.37067805 | S93: 0.48126943 | T93: 0.24474088 | U93: 0.37577794 | V93: 0.32824005 | W93: 0.40108896 | X93: 0.24179877 | Y93: 0.56586646 | Z93: 0.62807816 | AA93: 0.41080818 | AB93: 0.62813702 | AC93: 0.42335217 | AD93: 0.38010081 | AE93: 0.35140006 | AF93: 0.90705925 | AG93: 0.74513785 | AH93: 0.39881212 | AI93: 0.40130652 | AJ93: 0.31384398 | AK93: 0.35025717 | AL93: 0.49934843 | AM93: 0.45459184 | AN93: 0.3523737 | AO93: 0.42002451 | AP93: 0.56457166 | AQ93: 0.26899679 | AR93: 0.57864001 | AS93: 0.35718089 | AT93: 0.27117182 | AU93: 0.38580914 | AV93: 0.27727271 | AW93: 0.092763486 | AX93: 0.34449463 | AY93: 0.54472982 | AZ93: 0.71125891 | BA93: 0.40982054 | BB93: 0.68296761 | BC93: 0.42758585 | BD93: 0.85301581
A94: 92 | B94: M_Peasn | C94: 01.d | D94: 01.11 | E94: Peas, green, market of | F94: tonnes | G94: 0.65152665 | H94: 0.63890503 | I94: 0.97431681 | J94: 0.66599003 | K94: 0.60005442 | L94: 0.58145408 | M94: 0.82044816 | N94: 1.0030572 | O94: 0.34477 | P94: 0.86712979 | Q94: 0.85158271 | R94: 1.3100097 | S94: 1.8205546 | T94: 0.37911926 | U94: 2.1537354 | V94: 0.99714611 | W94: 0.72199288 | X94: 0.42157028 | Y94: 0.79578968 | Z94: 0.57105025 | AA94: 0.52535586 | AB94: 0.66451916 | AC94: 0.81787029 | AD94: 0.36680303 | AE94: 0.72666835 | AF94: 1.7127551 | AG94: 0.58260932 | AH94: 0.89267452 | AI94: 1.3870249 | AJ94: 0.70546741 | AK94: 0.68969221 | AL94: 0.65162277 | AM94: 1.3976266 | AN94: 1.2840474 | AO94: 0.65609087 | AP94: 0.69114518 | AQ94: 0.56920093 | AR94: 0.52571075 | AS94: 0.8671378 | AT94: 0.98950312 | AU94: 0.77024467 | AV94: 0.29193613 | AW94: 0.11853835 | AX94: 0.64782093 | AY94: 0.32089818 | AZ94: 0.69496117 | BA94: 0.17977128 | BB94: 1.3183569 | BC94: 0.37603588 | BD94: 1.5026361
A95: 93 | B95: M_Peasy | C95: 01.d | D95: 01.11 | E95: Peas, dry, market of | F95: tonnes | G95: 1.2647654 | H95: 2.6579517 | I95: 2.4115103 | J95: 1.1155218 | K95: 2.0188792 | L95: 1.0081249 | M95: 2.2664153 | N95: 2.1817895 | O95: 1.4158227 | P95: 1.5850883 | Q95: 1.1662073 | R95: 0.98497748 | S95: 1.8823533 | T95: 1.7127067 | U95: 1.7718116 | V95: 2.4981252 | W95: 0.86045041 | X95: 1.5192613 | Y95: 1.4898908 | Z95: 1.2085472 | AA95: 1.3221398 | AB95: 1.0188462 | AC95: 1.0049133 | AD95: 1.5549262 | AE95: 1.7296338 | AF95: 1.1528322 | AG95: 1.1922634 | AH95: 1.2936338 | AI95: 2.1571934 | AJ95: 1.3690707 | AK95: 0.97975677 | AL95: 1.2603101 | AM95: 1.5247074 | AN95: 1.4635252 | AO95: 1.6847671 | AP95: 1.9704332 | AQ95: 1.4655665 | AR95: 1.2945622 | AS95: 1.1111325 | AT95: 1.4536323 | AU95: 1.2251563 | AV95: 1.2820295 | AW95: 1.2476981 | AX95: 1.1659253 | AY95: 1.202175 | AZ95: 1.1785462 | BA95: 0.77898451 | BB95: 1.8559014 | BC95: 1.1646998 | BD95: 1.2656374
A96: 94 | B96: M_Perss | C96: 01.d | D96: 01.13 | E96: Persimmons, market of | F96: tonnes | G96: 0.38955953 | H96: 1.0270989 | I96: 0.35069378 | J96: 0.34408513 | K96: 0.46177151 | L96: 0.61141727 | M96: 0.35011107 | N96: 2.8173351 | O96: 0.37262702 | P96: 0.31268294 | Q96: 0.33440852 | R96: 0.38067755 | S96: 0.31372628 | T96: 0.3123463 | U96: 0.31730508 | V96: 0.31860265 | W96: 0.45666568 | X96: 0.37564172 | Y96: 2.1593068 | Z96: 0.34958892 | AA96: 0.33624751 | AB96: 0.87996599 | AC96: 0.37260886 | AD96: 0.3117869 | AE96: 0.460893 | AF96: 1.6688853 | AG96: 1.2573085 | AH96: 0.31755135 | AI96: 0.32312751 | AJ96: 0.32432128 | AK96: 0.34829385 | AL96: 0.58962458 | AM96: 0.65988907 | AN96: 0.32607714 | AO96: 0.31365023 | AP96: 0.31196356 | AQ96: 0.33236074 | AR96: 0.49817451 | AS96: 0.42045426 | AT96: 0.49083301 | AU96: 0.31710257 | AV96: 0.3450998 | AW96: 0.016465415 | AX96: 0.56665857 | AY96: 0.85398488 | AZ96: 0.49595546 | BA96: 0.39394266 | BB96: 1.4593302 | BC96: 0.48464216
A97: 95 | B97: M_Piges | C97: 01.d | D97: 01.11 | E97: Pigeon peas, market of | F97: tonnes | G97: 2.7356586 | H97: 2.3551447 | I97: 1.5126529 | J97: 2.8587143 | L97: 2.6437126 | M97: 0.73916797 | N97: 0.46435376 | O97: 2.9952798 | Q97: 3.0186793 | R97: 2.9835377 | S97: 3.0195923 | T97: 2.9900466 | U97: 2.7248928 | V97: 3.022039 | W97: 2.7035298 | X97: 3.0195923 | Y97: 2.1331781 | AB97: 0.99379248 | AC97: 2.7035298 | AD97: 2.9326037 | AE97: 2.8587143 | AF97: 2.9346673 | AG97: 1.5218116 | AJ97: 2.8889119 | AK97: 3.0195923 | AM97: 3.0195923 | AO97: 0.47243996 | AP97: 3.1445503 | AQ97: 2.7035298 | AS97: 1.6000394 | AV97: 2.7502186 | AX97: 2.7967175 | AY97: 0.74119254 | AZ97: 1.8518822 | BA97: 0.46704337 | BB97: 3.2263075 | BC97: 0.99379248 | BD97: 0.46435376
A98: 96 | B98: M_Pines | C98: 01.d | D98: 01.22 | E98: Pineapples, market of | F98: tonnes | G98: 0.30155154 | H98: 0.54023584 | I98: 0.2968678 | J98: 0.3043197 | K98: 0.2284569 | L98: 0.4016492 | M98: 0.30494293 | N98: 0.77051619 | O98: 0.30573217 | P98: 0.30304331 | Q98: 0.3029931 | R98: 0.30419025 | S98: 0.30224901 | T98: 0.31132717 | U98: 0.30237353 | V98: 0.27308712 | W98: 0.30432816 | X98: 0.30600123 | Y98: 0.25833233 | Z98: 0.30526349 | AA98: 0.30447468 | AB98: 0.11834726 | AC98: 0.30522673 | AD98: 0.29716183 | AE98: 0.30508821 | AF98: 0.23467255 | AG98: 0.20091679 | AH98: 0.30221767 | AI98: 0.30190186 | AJ98: 0.30291034 | AK98: 0.30533172 | AL98: 0.38227225 | AM98: 0.30505411 | AN98: 0.30572989 | AO98: 0.36014144 | AP98: 0.32181065 | AQ98: 0.30416967 | AR98: 0.33669721 | AS98: 0.30169835 | AT98: 0.3044128 | AU98: 0.30469837 | AV98: 0.30535974 | AW98: 0.01735038 | AX98: 0.32136213 | AY98: 0.19331009 | AZ98: 0.23792266 | BA98: 0.13344606 | BB98: 0.3062978 | BC98: 0.20943778 | BD98: 1.2260167
A99: 97 | B99: M_Pists | C99: 01.d | D99: 01.25 | E99: Pistachios, market of | F99: tonnes | G99: 2.03462 | H99: 3.0856493 | I99: 1.7687669 | J99: 2.1515604 | K99: 1.772858 | L99: 2.0762359 | M99: 1.9327322 | N99: 2.6560853 | O99: 2.5693258 | P99: 2.348165 | Q99: 2.0426821 | R99: 1.7693839 | S99: 1.9531354 | T99: 3.9412855 | U99: 1.9009323 | V99: 2.0863602 | W99: 1.9219772 | X99: 1.9203768 | Y99: 2.207089 | Z99: 3.9055732 | AA99: 2.0786352 | AB99: 3.5416621 | AC99: 1.9176236 | AD99: 2.7403984 | AE99: 2.7573118 | AF99: 1.803104 | AG99: 1.6505525 | AH99: 2.045217 | AI99: 1.6755095 | AJ99: 2.2349234 | AK99: 2.6496912 | AL99: 2.0223254 | AM99: 1.7505011 | AN99: 1.8335536 | AO99: 2.0647266 | AP99: 2.8175783 | AQ99: 2.255748 | AR99: 3.0017824 | AS99: 2.0768659 | AT99: 3.1296056 | AU99: 2.4936456 | AV99: 1.6841787 | AW99: 2.4531403 | AX99: 1.6160533 | AY99: 2.3623376 | AZ99: 1.8836919 | BA99: 7.3558011 | BB99: 1.7198945 | BC99: 2.506737 | BD99: 2.0910149
A100: 98 | B100: M_Plans | C100: 01.d | D100: 01.22 | E100: Plantains and others, market of | F100: tonnes | G100: 0.81927044 | H100: 0.47219693 | I100: 0.82011371 | J100: 0.81971489 | L100: 0.81936893 | M100: 0.81922015 | N100: 0.43487842 | O100: 0.81969256 | P100: 0.81987849 | Q100: 0.81835737 | R100: 0.81979185 | S100: 0.81679431 | T100: 0.82005899 | U100: 0.81748683 | V100: 0.81624374 | W100: 0.81660854 | X100: 0.81971461 | Y100: 0.43412706 | Z100: 0.8196415 | AA100: 0.81977042 | AC100: 0.81721791 | AD100: 0.81413474 | AE100: 0.81979171 | AF100: 0.46925999 | AG100: 0.53054496 | AH100: 0.81594753 | AI100: 0.81985336 | AJ100: 0.8176875 | AK100: 0.81942821 | AL100: 0.82014487 | AM100: 0.81926752 | AN100: 0.81506324 | AO100: 0.81960783 | AP100: 0.8200614 | AQ100: 0.81977268 | AR100: 0.75841391 | AS100: 0.82003797 | AT100: 0.81969809 | AU100: 0.81961136 | AV100: 0.81687957 | AW100: 0.4534086 | AX100: 0.8201357 | AY100: 0.2637771 | AZ100: 0.8146284 | BA100: 0.33778114 | BB100: 0.82026014 | BC100: 0.30200553 | BD100: 0.43854982
...

Sheet GHG markets - monetary
A1: GHG intensities: tonne CO2-eq per unit
A2: No | B2: EXIOBASE product code | C2: Nace rev1 code | D2: Nace rev2 code | E2: Description | F2: Unit | G2: AT | H2: AU | I2: BE | J2: BG | K2: BR | L2: CA | M2: CH | N2: CN | O2: CY | P2: CZ | Q2: DE | R2: DK | S2: EE | T2: ES | U2: FI | V2: FR | W2: GB | X2: GR | Y2: HR | Z2: HU | AA2: ID | AB2: IE | AC2: IN | AD2: IT | AE2: JP | AF2: KR | AG2: LT | AH2: LU | AI2: LV | AJ2: MT | AK2: MX | AL2: NL | AM2: NO | AN2: PL | AO2: PT | AP2: RO | AQ2: RU | AR2: SE | AS2: SI | AT2: SK | AU2: TR | AV2: US | AW2: WA | AX2: WE | AY2: WF | AZ2: WL | BA2: WM | BB2: ZA
A3: 1 | B3: M_Ricey | C3: 01.a | D3: 01.12 | E3: Rice, paddy, market of | F3: Meuro | G3: 4683.3285 | H3: 5645.14 | I3: 4164.328 | J3: 6843.363 | K3: 7473.5674 | L3: 5588.6947 | M3: 4258.8479 | N3: 5028.3632 | O3: 6804.9659 | P3: 1474.5828 | Q3: 9233.6285 | R3: 6600.3744 | S3: 4307.5773 | T3: 5168.8676 | U3: 3758.9676 | V3: 1818.255 | W3: 5505.4839 | X3: 1508.7793 | Y3: 4385.459 | Z3: 13691.708 | AA3: 4445.7254 | AB3: 4937.6053 | AC3: 6253.5456 | AD3: 3098.7141 | AE3: 1486.707 | AF3: 1771.0127 | AG3: 7521.3779 | AH3: 6709.8533 | AI3: 5940.8972 | AJ3: 4327.1055 | AK3: 9794.4665 | AL3: 5297.9315 | AM3: 4559.5521 | AN3: 8056.8286 | AO3: 7157.8261 | AP3: 6345.945 | AQ3: 12018.908 | AR3: 8458.575 | AS3: 4711.7422 | AT3: 5038.3625 | AU3: 4533.5761 | AV3: 8355.7068 | AW3: 9258.6507 | AX3: 7724.2043 | AY3: 8007.3636 | AZ3: 2369.5644 | BA3: 3940.6197 | BB3: 6367.33
A4: 2 | B4: M_Germt | C4: 01.b | D4: 01.11 | E4: Germ, wheat, market of | F4: Meuro | G4: 150.37098 | H4: 173.00886 | I4: 135.29888 | J4: 1338.4262 | L4: 326.09906 | M4: 56.378347 | N4: 78.438099 | O4: 1143.0364 | P4: 123.36244 | Q4: 38.730835 | R4: 80.848417 | S4: 95.185108 | T4: 1016.0229 | U4: 26.70851 | V4: 329.31025 | W4: 1136.7402 | X4: 19.446423 | Y4: 30.422568 | Z4: 272.62551 | AA4: 12.125262 | AB4: 882.62406 | AC4: 169.08535 | AD4: 196.46835 | AE4: 45.511616 | AF4: 420.6454 | AG4: 58.074968 | AH4: 85.751123 | AI4: 96.777229 | AJ4: 225.35396 | AK4: 608.13589 | AL4: 404.51648 | AM4: 431.44057 | AN4: 526.51954 | AO4: 147.52651 | AP4: 134.55657 | AQ4: 921.75754 | AR4: 93.943921 | AS4: 125.95339 | AT4: 151.7535 | AU4: 61.326367 | AV4: 474.39871 | AW4: 35.324855 | AX4: 297.12506 | AY4: 147.33083 | AZ4: 1913.7268 | BA4: 257.71093 | BB4: 406.38881
A5: 3 | B5: M_Wheat | C5: 01.b | D5: 01.11 | E5: Wheat, market of | F5: Meuro | G5: 7471.2066 | H5: 7798.5194 | I5: 7018.0686 | J5: 7512.6348 | K5: 11551.319 | L5: 7462.485 | M5: 4526.354 | N5: 4505.0114 | O5: 10241.186 | P5: 7705.5553 | Q5: 6155.4004 | R5: 5831.1053 | S5: 12996.188 | T5: 6074.7825 | U5: 9452.2494 | V5: 7800.8381 | W5: 7135.1737 | X5: 6046.9088 | Y5: 8315.2113 | Z5: 6820.0188 | AA5: 8585.6113 | AB5: 5921.4718 | AC5: 4682.2649 | AD5: 7089.4513 | AE5: 8956.9876 | AF5: 8781.514 | AG5: 8238.19 | AH5: 6922.8151 | AI5: 9676.53 | AJ5: 6086.837 | AK5: 8440.6126 | AL5: 6912.5989 | AM5: 4566.9135 | AN5: 7682.4677 | AO5: 6771.6372 | AP5: 6334.2275 | AQ5: 11926.001 | AR5: 7052.7468 | AS5: 8321.5706 | AT5: 7520.2076 | AU5: 5661.2481 | AV5: 5094.1155 | AW5: 7457.0736 | AX5: 10279.43 | AY5: 6093.5651 | AZ5: 6183.3627 | BA5: 4257.9339 | BB5: 6622.5309
A6: 4 | B6: M_Barly | C6: 01.c | D6: 01.11 | E6: Barley, market of | F6: Meuro | G6: 7590.7958 | H6: 7317.3294 | I6: 7945.8443 | J6: 5968.0971 | K6: 4919.1164 | L6: 7521.6525 | M6: 4352.7014 | N6: 2298.7278 | O6: 10407.583 | P6: 7646.8771 | Q6: 6182.2633 | R6: 5952.2745 | S6: 15304.835 | T6: 6848.453 | U6: 12922.282 | V6: 8307.9392 | W6: 6925.8936 | X6: 5837.831 | Y6: 8736.6716 | Z6: 7880.8904 | AA6: 8479.9349 | AB6: 4574.8469 | AC6: 2648.2919 | AD6: 4720.556 | AE6: 4381.5655 | AF6: 2341.4791 | AG6: 11691.885 | AH6: 10070.934 | AI6: 14633.83 | AJ6: 7862.1481 | AK6: 10149.986 | AL6: 6252.099 | AM6: 4361.5589 | AN6: 11462.036 | AO6: 8007.6574 | AP6: 4726.0708 | AQ6: 13247.619 | AR6: 7848.1139 | AS6: 9542.0425 | AT6: 6958.1366 | AU6: 5895.1186 | AV6: 5319.4578 | AW6: 9075.1677 | AX6: 11316.361 | AY6: 4639.0086 | AZ6: 3083.7716 | BA6: 5612.7491 | BB6: 4776.747
A7: 5 | B7: M_Buckt | C7: 01.c | D7: 01.11 | E7: Buckwheat, market of | F7: Meuro | G7: 6175.8331 | H7: 10853.21 | I7: 7374.6875 | J7: 8805.887 | K7: 9078.6236 | L7: 7439.7102 | M7: 7567.7332 | N7: 10639.989 | O7: 8422.4503 | P7: 3636.9612 | Q7: 7994.4721 | R7: 8716.5128 | S7: 6604.5343 | T7: 5304.7091 | U7: 6028.9072 | V7: 3086.1356 | W7: 7987.8763 | X7: 9338.1907 | Y7: 6145.9067 | Z7: 4744.7714 | AA7: 5915.3094 | AB7: 13164.775 | AC7: 9790.1062 | AD7: 7351.9916 | AE7: 5717.1785 | AF7: 12380.448 | AG7: 9225.6171 | AH7: 4179.6183 | AI7: 11003.302 | AJ7: 5148.9925 | AL7: 9429.444 | AM7: 8044.1115 | AN7: 8924.3649 | AO7: 5210.1233 | AP7: 5935.6169 | AQ7: 7070.9995 | AR7: 9738.0318 | AS7: 7107.7745 | AT7: 5115.5975 | AU7: 7449.3423 | AV7: 5710.9921 | AW7: 11606.585 | AX7: 7323.2156 | AY7: 4443.1808 | AZ7: 6235.3377 | BA7: 5859.6951 | BB7: 4646.8283
A8: 6 | B8: M_Ceres | C8: 01.c | D8: 01.11 | E8: Cereals nes, market of | F8: Meuro | G8: 3288.7639 | H8: 5871.1979 | I8: 3879.1458 | J8: 5211.3509 | K8: 5221.2362 | L8: 4914.9521 | M8: 4359.827 | N8: 4494.0263 | O8: 4430.5229 | P8: 8062.0869 | Q8: 5591.7835 | R8: 4311.6701 | S8: 7494.1658 | T8: 4106.4873 | U8: 8395.3098 | V8: 4033.1311 | W8: 5045.0581 | X8: 3007.3238 | Y8: 4436.358 | Z8: 4087.2729 | AA8: 4293.0501 | AB8: 6443.4146 | AC8: 1523.8999 | AD8: 3886.7178 | AE8: 2761.7126 | AF8: 7522.6434 | AG8: 9406.8129 | AH8: 3251.3708 | AI8: 6659.0004 | AJ8: 2217.4225 | AK8: 7711.578 | AL8: 3630.1259 | AM8: 4948.2027 | AN8: 6740.9679 | AO8: 4315.619 | AP8: 5073.0317 | AQ8: 13370.377 | AR8: 4143.3191 | AS8: 3435.6249 | AT8: 11807.662 | AU8: 1423.023 | AV8: 5566.5778 | AW8: 1584.9671 | AX8: 6966.9606 | AY8: 1304.1377 | AZ8: 6392.302 | BA8: 2960.4071 | BB8: 12205.94
A9: 7 | B9: M_Fonio | C9: 01.c | D9: 01.29 | E9: Fonio, market of | F9: Meuro | G9: 5571.1657 | I9: 5841.9458 | L9: 5863.2895 | M9: 5745.547 | O9: 5551.5893 | P9: 5971.6301 | Q9: 5483.6081 | R9: 5593.8978 | T9: 5771.4062 | V9: 5885.5728 | W9: 5809.1447 | X9: 5971.9093 | AA9: 6122.1853 | AB9: 5995.2099 | AD9: 5196.3107 | AG9: 6256.1362 | AH9: 4915.8077 | AL9: 4976.9699 | AN9: 6033.8727 | AO9: 5738.1392 | AP9: 5300.2169 | AR9: 5411.515 | AV9: 5709.1615 | AX9: 5533.5787 | AY9: 5885.5653 | BA9: 5630.4615
A10: 8 | B10: M_Germe | C10: 01.c | D10: 01.19 | E10: Germ, maize, market of | F10: Meuro | G10: 100.53191 | H10: 108.75804 | I10: 48.753051 | J10: 111.07951 | K10: 29.696226 | L10: 68.344365 | M10: 30.107651 | N10: 75.828907 | O10: 37.704218 | P10: 55.717822 | Q10: 17.218202 | R10: 17.531902 | S10: 23.494077 | T10: 49.992425 | U10: 21.80175 | V10: 75.099407 | W10: 22.290102 | X10: 8.3611608 | Y10: 49.026424 | Z10: 79.131383 | AA10: 117.22833 | AB10: 5.3272423 | AC10: 196.95142 | AD10: 106.43333 | AE10: 33.651623 | AF10: 17.690866 | AG10: 1.253059 | AH10: 85.186385 | AI10: 49.371173 | AJ10: 68.890609 | AK10: 370.39943 | AL10: 222.58984 | AM10: 20.419715 | AN10: 41.687808 | AO10: 35.718587 | AP10: 45.5706 | AQ10: 83.760003 | AR10: 15.215201 | AS10: 40.960978 | AT10: 42.094306 | AU10: 38.307477 | AV10: 50.292922 | AW10: 40.275429 | AX10: 72.097734 | AY10: 72.920384 | AZ10: 216.07141 | BA10: 330.89175 | BB10: 190.55457
A11: 9 | B11: M_Graid | C11: 01.c | D11: 01.11 | E11: Grain, mixed, market of | F11: Meuro | G11: 1389.7514 | I11: 4630.3041 | J11: 2873.3903 | L11: 13719.222 | M11: 4988.9979 | N11: 1588.0604 | O11: 4124.0209 | P11: 16607.21 | Q11: 1067.2605 | R11: 10723.586 | S11: 21026.033 | T11: 15741.961 | U11: 20196.639 | V11: 14747.86 | W11: 8279.4672 | X11: 2389.8057 | Y11: 17519.84 | Z11: 2151.4841 | AB11: 4294.0896 | AC11: 3736.5119 | AD11: 1585.4285 | AG11: 20147.28 | AH11: 6889.88 | AI11: 35328.503 | AJ11: 2579.3011 | AL11: 3678.4904 | AM11: 1058.7767 | AN11: 18502.363 | AO11: 1078.3284 | AP11: 1248.0888 | AR11: 13511.992 | AS11: 4568.6675 | AT11: 1534.2729 | AU11: 16435.1 | AV11: 1745.9697 | AW11: 3274.0374 | AX11: 14212.778 | AY11: 4737.309 | AZ11: 1022.2744 | BA11: 4406.425
A12: 10 | B12: M_Hops | C12: 01.c | D12: 01.28 | E12: Hops, market of | F12: Meuro | G12: 364.94929 | H12: 319.70284 | I12: 332.91448 | J12: 416.81363 | K12: 355.74443 | L12: 311.94323 | M12: 325.57129 | N12: 801.47301 | O12: 505.63351 | P12: 594.54264 | Q12: 404.87216 | R12: 304.31768 | S12: 314.78551 | T12: 421.63474 | U12: 363.14355 | V12: 432.78397 | W12: 290.63667 | X12: 384.57398 | Y12: 464.12314 | Z12: 401.75048 | AA12: 457.15946 | AB12: 273.20936 | AC12: 465.90668 | AD12: 499.94933 | AE12: 444.92856 | AF12: 412.5518 | AG12: 406.84519 | AH12: 406.85267 | AI12: 299.00293 | AJ12: 170.93576 | AK12: 313.53938 | AL12: 465.67969 | AM12: 263.9994 | AN12: 554.81724 | AO12: 420.30237 | AP12: 436.85341 | AQ12: 459.52643 | AR12: 287.25843 | AS12: 415.02559 | AT12: 656.94916 | AU12: 423.0277 | AV12: 284.82443 | AW12: 830.52682 | AX12: 1068.8178 | AY12: 880.5421 | AZ12: 380.25963 | BA12: 707.66133 | BB12: 621.13819
A13: 11 | B13: M_Maize | C13: 01.c | D13: 01.11 | E13: Maize, market of | F13: Meuro | G13: 3302.7315 | H13: 1681.162 | I13: 3604.3689 | J13: 6889.2249 | K13: 6904.5415 | L13: 4011.8755 | M13: 3124.8447 | N13: 4133.0588 | O13: 5043.6014 | P13: 4533.3127 | Q13: 3755.2834 | R13: 4757.8762 | S13: 5241.1038 | T13: 3352.1546 | U13: 4444.867 | V13: 4306.1006 | W13: 3665.6654 | X13: 2032.974 | Y13: 4764.796 | Z13: 3550.1883 | AA13: 4150.2131 | AB13: 4763.5719 | AC13: 3429.1383 | AD13: 3122.0182 | AE13: 4918.4714 | AF13: 3739.4815 | AG13: 5673.4464 | AH13: 2885.4029 | AI13: 5042.4411 | AJ13: 4203.3019 | AK13: 6615.4187 | AL13: 4081.442 | AM13: 5009.5956 | AN13: 5541.5136 | AO13: 4405.5808 | AP13: 3942.8885 | AQ13: 5747.5007 | AR13: 4540.397 | AS13: 4380.3436 | AT13: 4171.2815 | AU13: 2825.6393 | AV13: 4168.3923 | AW13: 2815.6906 | AX13: 5105.7989 | AY13: 3027.1953 | AZ13: 1698.6064 | BA13: 3233.575 | BB13: 3764.8729
A14: 12 | B14: M_Maizn | C14: 01.c | D14: 01.11 | E14: Maize, green, market of | F14: Meuro | G14: 311.70513 | H14: 1110.5892 | I14: 720.83121 | J14: 3997.135 | K14: 920.59273 | L14: 2555.4475 | M14: 686.99975 | N14: 752.50876 | O14: 283.43505 | P14: 2756.1654 | Q14: 1048.9003 | R14: 1132.6379 | S14: 2461.6527 | T14: 858.14607 | U14: 427.91046 | V14: 753.85879 | W14: 641.08758 | X14: 182.53758 | Y14: 871.58026 | Z14: 3840.0425 | AA14: 2486.1888 | AB14: 733.87866 | AC14: 787.9484 | AD14: 2410.9688 | AE14: 931.84503 | AF14: 819.55551 | AG14: 1877.1544 | AH14: 649.04458 | AI14: 1639.8407 | AJ14: 2327.2586 | AK14: 5908.9747 | AL14: 1147.3135 | AM14: 1604.5023 | AN14: 2066.7142 | AO14: 822.10056 | AP14: 2741.6006 | AQ14: 1374.1605 | AR14: 3615.7449 | AS14: 321.75107 | AT14: 3036.6985 | AU14: 802.70958 | AV14: 1956.6461 | AW14: 372.95422 | AX14: 948.91887 | AY14: 1517.046 | AZ14: 1514.8428 | BA14: 684.29675 | BB14: 971.61886
A15: 13 | B15: M_Millt | C15: 01.c | D15: 01.11 | E15: Millet, market of | F15: Meuro | G15: 1663.2786 | H15: 2827.7238 | I15: 7435.3433 | J15: 6571.7876 | K15: 2635.8702 | L15: 8636.9797 | M15: 4412.2066 | N15: 2205.1656 | O15: 14039.561 | P15: 8395.3813 | Q15: 5512.7845 | R15: 7760.9769 | S15: 10379.709 | T15: 7692.1596 | U15: 13308.415 | V15: 3553.0484 | W15: 7736.2616 | X15: 7214.1775 | Y15: 1111.6411 | Z15: 10077.732 | AA15: 9041.6505 | AB15: 9704.6998 | AC15: 5330.6372 | AD15: 8873.833 | AE15: 5453.0136 | AF15: 4954.7763 | AG15: 14503.408 | AH15: 2146.8607 | AI15: 4684.9407 | AJ15: 6203.7073 | AK15: 9854.9946 | AL15: 6442.2649 | AM15: 3019.6876 | AN15: 11163.107 | AO15: 10700.434 | AP15: 3069.1384 | AQ15: 17408.129 | AR15: 10267.149 | AS15: 9723.049 | AT15: 6904.5564 | AU15: 12949.831 | AV15: 9119.8205 | AW15: 5526.4933 | AX15: 16398.217 | AY15: 3441.8653 | AZ15: 2106.5317 | BA15: 4298.0715 | BB15: 6706.7693
A16: 14 | B16: M_Mushs | C16: 01.c | D16: 01.13 | E16: Mushrooms and truffles, market of | F16: Meuro | G16: 239.6632 | H16: 240.5906 | I16: 320.71753 | J16: 387.53226 | K16: 81.21983 | L16: 243.76162 | M16: 105.17708 | N16: 688.78123 | O16: 414.80195 | P16: 338.05454 | Q16: 208.88112 | R16: 215.69767 | S16: 305.97761 | T16: 306.6196 | U16: 189.70061 | V16: 297.95227 | W16: 111.31979 | X16: 183.19958 | Y16: 139.9047 | Z16: 213.62181 | AA16: 161.01751 | AB16: 140.96873 | AC16: 375.22957 | AD16: 151.85713 | AE16: 393.33872 | AF16: 264.84033 | AG16: 481.62707 | AH16: 290.58496 | AI16: 269.86969 | AJ16: 626.23305 | AK16: 126.85706 | AL16: 555.45166 | AM16: 371.72347 | AN16: 390.90177 | AO16: 245.02716 | AP16: 149.41627 | AQ16: 625.41842 | AR16: 256.2481 | AS16: 117.66967 | AT16: 174.04021 | AU16: 305.06151 | AV16: 129.4411 | AW16: 409.26099 | AX16: 301.08673 | AY16: 294.61647 | AZ16: 241.24584 | BA16: 379.45607 | BB16: 497.61686
A17: 15 | B17: M_Oatss | C17: 01.c | D17: 01.11 | E17: Oats, market of | F17: Meuro | G17: 8069.7075 | H17: 6834.7776 | I17: 8217.5999 | J17: 9141.75 | K17: 5326.4176 | L17: 8658.4016 | M17: 7963.166 | N17: 1228.9176 | O17: 13406.948 | P17: 9925.2149 | Q17: 7517.7008 | R17: 6292.7556 | S17: 19243.51 | T17: 8417.1968 | U17: 10580.022 | V17: 6320.2635 | W17: 5463.6171 | X17: 6215.9433 | Y17: 10828.646 | Z17: 9600.8587 | AA17: 7566.4833 | AB17: 4406.2921 | AC17: 11583.488 | AD17: 9063.9562 | AE17: 7893.994 | AF17: 9242.4778 | AG17: 15561.383 | AH17: 6230.5552 | AI17: 16382.483 | AJ17: 7668.5837 | AK17: 10737.041 | AL17: 7757.3509 | AM17: 3707.7112 | AN17: 14776.293 | AO17: 14157.49 | AP17: 5612.6448 | AQ17: 16840.307 | AR17: 8104.0301 | AS17: 6142.8853 | AT17: 8096.0087 | AU17: 4445.4584 | AV17: 9162.15 | AW17: 10649.192 | AX17: 15885.315 | AY17: 2930.5526 | AZ17: 3352.1844 | BA17: 8510.0917 | BB17: 8911.2009
A18: 16 | B18: M_Poppd | C18: 01.c | D18: 01.11 | E18: Poppy seed, market of | F18: Meuro | G18: 2846.3198 | H18: 2913.4478 | I18: 3241.0379 | J18: 2758.5204 | K18: 3025.2273 | L18: 2838.5479 | M18: 3050.1144 | N18: 3196.7195 | O18: 2756.5297 | P18: 3871.5845 | Q18: 2954.7279 | R18: 2323.9516 | S18: 3127.651 | T18: 2655.7494 | U18: 2391.9501 | V18: 3498.147 | W18: 3136.3389 | X18: 3004.9265 | Y18: 1665.7538 | Z18: 2721.7572 | AA18: 3239.8678 | AB18: 3034.7652 | AC18: 1510.5096 | AD18: 2604.412 | AE18: 1774.2785 | AF18: 3462.9633 | AG18: 3984.4535 | AH18: 2751.5925 | AI18: 4455.844 | AJ18: 2450.9996 | AK18: 3050.0586 | AL18: 2803.5677 | AM18: 3200.9988 | AN18: 3542.3303 | AO18: 3104.9362 | AP18: 2202.7692 | AQ18: 3848.2297 | AR18: 1965.0936 | AS18: 2029.2056 | AT18: 2699.4659 | AU18: 1742.4478 | AV18: 2917.0149 | AW18: 2766.0154 | AX18: 2671.9365 | AY18: 3444.0122 | AZ18: 1512.9344 | BA18: 748.47988 | BB18: 2495.7112
A19: 17 | B19: M_Quina | C19: 01.c | D19: 01.11 | E19: Quinoa, market of | F19: Meuro | G19: 3153.3098 | H19: 3167.6614 | I19: 3287.346 | J19: 3397.7552 | K19: 3394.1692 | L19: 3313.6919 | M19: 3232.1529 | N19: 3285.2693 | O19: 3124.6883 | P19: 3363.0063 | Q19: 3080.0194 | R19: 3139.8615 | S19: 3378.7665 | T19: 3251.8794 | U19: 3384.1782 | V19: 3318.5729 | W19: 3261.5187 | X19: 3351.2245 | Y19: 3323.6467 | Z19: 3407.0416 | AA19: 3482.5826 | AB19: 3361.3061 | AC19: 2665.7239 | AD19: 2950.38 | AE19: 3235.1666 | AF19: 3381.7134 | AG19: 3507.4245 | AH19: 2783.4026 | AI19: 2905.6342 | AJ19: 3234.214 | AK19: 3454.5782 | AL19: 2877.8607 | AM19: 3174.4219 | AN19: 3384.0844 | AO19: 3223.931 | AP19: 2988.9733 | AQ19: 3294.0877 | AR19: 3038.9495 | AS19: 3277.2266 | AT19: 3463.366 | AU19: 3338.0693 | AV19: 3220.9196 | AW19: 3043.3147 | AX19: 3125.0192 | AY19: 3316.4278 | AZ19: 2726.7038 | BA19: 3214.6682 | BB19: 3334.4807
A20: 18 | B20: M_Ryee | C20: 01.c | D20: 01.11 | E20: Rye, market of | F20: Meuro | G20: 5576.2508 | H20: 7233.2711 | I20: 7714.3466 | J20: 10249.895 | K20: 21018.414 | L20: 6274.6309 | M20: 3938.4985 | N20: 9480.2674 | O20: 6865.0176 | P20: 7873.2949 | Q20: 7176.2543 | R20: 5040.4724 | S20: 14983.877 | T20: 9147.9087 | U20: 8454.2202 | V20: 7310.8502 | W20: 2483.5876 | X20: 7363.127 | Y20: 9670.0787 | Z20: 9705.085 | AA20: 16409.371 | AB20: 7217.6429 | AC20: 2506.0582 | AD20: 1605.9544 | AE20: 7317.4858 | AF20: 8930.3182 | AG20: 15755.388 | AH20: 7297.3024 | AI20: 10749.224 | AJ20: 1177.0713 | AK20: 12680.135 | AL20: 6240.4715 | AM20: 3006.599 | AN20: 12186.52 | AO20: 15845.736 | AP20: 4961.0406 | AQ20: 13537.411 | AR20: 5477.6623 | AS20: 8137.8326 | AT20: 10474.861 | AU20: 4540.8023 | AV20: 8429.4013 | AW20: 14574.55 | AX20: 19509.098 | AY20: 2365.6928 | AZ20: 4547.6249 | BA20: 1385.4246 | BB20: 3243.3362
A21: 19 | B21: M_Sorgm | C21: 01.c | D21: 01.11 | E21: Sorghum, market of | F21: Meuro | G21: 3225.4219 | H21: 4681.1979 | I21: 3842.1954 | J21: 8564.9904 | K21: 12384.33 | L21: 9373.2851 | M21: 1916.656 | N21: 5259.9789 | O21: 3462.3374 | P21: 8640.4861 | Q21: 3300.8469 | R21: 7286.0389 | S21: 4664.9089 | T21: 5032.9131 | U21: 3953.4367 | V21: 3580.1649 | W21: 3819.1637 | X21: 1178.3306 | Y21: 406.86618 | Z21: 6867.6436 | AA21: 7836.8538 | AB21: 3924.2966 | AC21: 7447.3856 | AD21: 1032.0213 | AE21: 7456.7983 | AF21: 3467.5606 | AG21: 8308.7177 | AH21: 2989.7018 | AI21: 3297.6687 | AJ21: 3987.9516 | AK21: 10253.831 | AL21: 3169.9382 | AM21: 3570.6112 | AN21: 8548.8007 | AO21: 4118.0892 | AP21: 4505.0865 | AQ21: 12634.914 | AR21: 3552.8931 | AS21: 6715.3689 | AT21: 7846.7891 | AU21: 11109.867 | AV21: 9174.9607 | AW21: 7845.8258 | AX21: 9074.7458 | AY21: 2744.3845 | AZ21: 5944.0085 | BA21: 2999.344 | BB21: 8880.8438
A22: 20 | B22: M_Trite | C22: 01.c | D22: 01.11 | E22: Triticale, market of | F22: Meuro | G22: 8379.8709 | H22: 9473.0087 | I22: 15651.33 | J22: 7217.6462 | K22: 14886.672 | L22: 3478.2824 | M22: 4273.2126 | N22: 18371.149 | O22: 2293.8437 | P22: 9962.541 | Q22: 6410.8793 | R22: 6969.149 | S22: 7698.6412 | T22: 8393.1812 | U22: 9852.2895 | V22: 7748.1347 | W22: 1784.4379 | X22: 3067.3924 | Y22: 9105.1738 | Z22: 9053.1521 | AB22: 6940.949 | AD22: 1553.3119 | AE22: 9847.1764 | AG22: 11723.014 | AH22: 9403.3234 | AI22: 13293.51 | AJ22: 5814.1257 | AK22: 9551.4203 | AL22: 5798.9137 | AM22: 7929.7615 | AN22: 10759.012 | AO22: 15927.494 | AP22: 5045.8757 | AQ22: 4638.334 | AR22: 7853.0758 | AS22: 8783.8063 | AT22: 6386.6987 | AU22: 4285.7465 | AV22: 3381.7595 | AW22: 4631.2401 | AX22: 19551.066 | AY22: 2153.4673 | AZ22: 555.26361 | BA22: 1416.2627 | BB22: 2156.5218
A23: 21 | B23: M_Almol | C23: 01.d | D23: 01.25 | E23: Almonds, with shell, market of | F23: Meuro | G23: 2124.4032 | H23: 270.8416 | I23: 342.27434 | J23: 1152.9274 | K23: 2128.2564 | L23: 365.76896 | M23: 1652.234 | N23: 604.27247 | O23: 16012.859 | P23: 2338.6393 | Q23: 648.44925 | R23: 1158.4769 | S23: 271.24402 | T23: 3892.2013 | U23: 306.28028 | V23: 1789.7576 | W23: 303.42788 | X23: 321.61514 | Y23: 3125.8977 | Z23: 1455.7002 | AA23: 342.42886 | AB23: 650.86654 | AC23: 308.9225 | AD23: 1698.4274 | AE23: 268.3384 | AF23: 264.64265 | AG23: 675.94058 | AH23: 814.46078 | AI23: 625.99767 | AJ23: 1544.1405 | AK23: 334.63887 | AL23: 613.33445 | AM23: 342.50685 | AN23: 2429.7663 | AO23: 10944.841 | AP23: 1263.3687 | AQ23: 557.40886 | AR23: 816.37404 | AS23: 1855.6635 | AT23: 1535.7584 | AU23: 473.1006 | AV23: 319.95046 | AW23: 636.79687 | AX23: 290.43445 | AY23: 1707.4673 | AZ23: 525.90629 | BA23: 456.42073 | BB23: 1315.4454
A24: 22 | B24: M_Anisr | C24: 01.d | D24: 01.28 | E24: Anise, badian, fennel, coriander, market of | F24: Meuro | G24: 1309.2263 | H24: 2077.324 | I24: 1464.786 | J24: 8586.5557 | K24: 1560.442 | L24: 3207.9501 | M24: 2070.8905 | N24: 2783.0945 | O24: 977.05636 | P24: 1264.1563 | Q24: 1475.4829 | R24: 742.35533 | S24: 1485.0275 | T24: 1579.9057 | U24: 1358.8974 | V24: 1498.5717 | W24: 1769.7711 | X24: 815.57223 | Y24: 1170.2593 | Z24: 836.71578 | AA24: 4080.4495 | AB24: 1178.2709 | AC24: 1823.4437 | AD24: 1535.6341 | AE24: 1185.295 | AF24: 1713.1792 | AG24: 1397.8436 | AH24: 1299.7958 | AI24: 1895.8722 | AJ24: 1588.2923 | AK24: 759.76628 | AL24: 1620.1371 | AM24: 837.37005 | AN24: 2857.545 | AO24: 1615.5268 | AP24: 2322.1448 | AQ24: 9597.7595 | AR24: 1432.298 | AS24: 2203.5512 | AT24: 1268.3258 | AU24: 2710.6764 | AV24: 1685.4204 | AW24: 1715.8714 | AX24: 2589.8058 | AY24: 815.96063 | AZ24: 1194.1412 | BA24: 704.08359 | BB24: 1621.9892
A25: 23 | B25: M_Appls | C25: 01.d | D25: 01.22 | E25: Apples, market of | F25: Meuro | G25: 700.29684 | H25: 644.09034 | I25: 881.26647 | J25: 1693.1896 | K25: 574.97226 | L25: 886.73326 | M25: 377.70711 | N25: 1475.327 | O25: 1139.7882 | P25: 1588.8539 | Q25: 633.70107 | R25: 547.35009 | S25: 2612.8909 | T25: 733.95317 | U25: 792.87665 | V25: 564.44201 | W25: 579.71001 | X25: 350.02899 | Y25: 1976.1136 | Z25: 3306.0694 | AA25: 1063.4653 | AB25: 393.65901 | AC25: 961.95585 | AD25: 783.0601 | AE25: 495.69953 | AF25: 370.50048 | AG25: 1847.9566 | AH25: 925.84674 | AI25: 2367.3972 | AJ25: 832.86285 | AK25: 1535.7546 | AL25: 1217.8715 | AM25: 799.28066 | AN25: 2818.8842 | AO25: 876.06963 | AP25: 811.06831 | AQ25: 1729.9501 | AR25: 695.43592 | AS25: 913.64522 | AT25: 1447.2534 | AU25: 1229.5217 | AV25: 585.99701 | AW25: 1180.3578 | AX25: 1972.3299 | AY25: 503.72167 | AZ25: 933.94896 | BA25: 837.45521 | BB25: 2255.4512
A26: 24 | B26: M_Apris | C26: 01.d | D26: 01.24 | E26: Apricots, market of | F26: Meuro | G26: 388.85516 | H26: 1325.0493 | I26: 322.08036 | J26: 1870.9197 | K26: 914.37599 | L26: 766.93835 | M26: 263.64873 | N26: 3258.1686 | O26: 1262.1472 | P26: 1050.175 | Q26: 419.06214 | R26: 344.84795 | S26: 483.57032 | T26: 653.11389 | U26: 467.98997 | V26: 228.21415 | W26: 630.68812 | X26: 473.24818 | Y26: 876.80649 | Z26: 1360.9567 | AA26: 1172.381 | AB26: 473.20239 | AC26: 512.44115 | AD26: 448.51407 | AE26: 833.43234 | AF26: 816.40877 | AG26: 764.0931 | AH26: 254.9851 | AI26: 548.88185 | AJ26: 469.57962 | AK26: 1245.7091 | AL26: 609.4773 | AM26: 427.22515 | AN26: 876.16644 | AO26: 625.41056 | AP26: 351.09587 | AQ26: 1244.4656 | AR26: 469.41109 | AS26: 452.82518 | AT26: 1636.8739 | AU26: 1102.5124 | AV26: 833.63246 | AW26: 1087.7855 | AX26: 1186.8968 | AY26: 557.02694 | AZ26: 786.45962 | BA26: 714.06451 | BB26: 1416.849
A27: 25 | B27: M_Arecs | C27: 01.d | D27: 01.25 | E27: Areca nuts, market of | F27: Meuro | G27: 972.99841 | H27: 1113.6785 | I27: 821.38786 | L27: 857.67533 | M27: 746.52272 | N27: 2113.8602 | O27: 45.772262 | Q27: 953.62973 | R27: 687.37508 | T27: 1287.1298 | U27: 1222.1359 | V27: 3881.7949 | W27: 1277.1613 | X27: 1198.2979 | Z27: 1278.2796 | AA27: 4050.9118 | AB27: 1051.0936 | AC27: 922.47 | AD27: 1203.6221 | AE27: 1821.5276 | AF27: 4577.9576 | AI27: 971.15564 | AL27: 1014.5267 | AO27: 1147.5766 | AP27: 1039.9298 | AR27: 1065.977 | AU27: 996.99457 | AV27: 1463.6194 | AW27: 2110.8461 | AX27: 1407.4336 | AY27: 1033.8118 | AZ27: 2523.5839 | BA27: 1061.2016 | BB27: 1518.5803
A28: 26 | B28: M_Artis | C28: 01.d | D28: 01.13 | E28: Artichokes, market of | F28: Meuro | G28: 617.01687 | I28: 952.06218 | J28: 606.14746 | L28: 393.28931 | M28: 783.79196 | N28: 412.4277 | O28: 847.20992 | P28: 622.9346 | Q28: 683.98117 | R28: 570.32198 | S28: 818.92704 | T28: 462.31794 | U28: 857.5924 | V28: 979.92301 | W28: 860.50931 | X28: 288.00309 | Y28: 585.79123 | Z28: 639.28417 | AA28: 847.96863 | AB28: 778.27862 | AD28: 581.84925 | AE28: 416.43584 | AF28: 983.17139 | AG28: 2043.7967 | AH28: 923.67597 | AI28: 615.30774 | AJ28: 604.09384 | AK28: 1188.5193 | AL28: 936.2587 | AM28: 734.19341 | AN28: 882.49962 | AO28: 688.79571 | AP28: 558.31904 | AQ28: 836.16096 | AR28: 778.37965 | AS28: 603.00075 | AT28: 594.47829 | AU28: 547.36134 | AV28: 358.13557 | AW28: 607.58843 | AX28: 1493.004 | AY28: 411.50578 | AZ28: 965.35717 | BA28: 1258.2093 | BB28: 367.23929
A29: 27 | B29: M_Aspas | C29: 01.d | D29: 01.13 | E29: Asparagus, market of | F29: Meuro | G29: 311.61818 | H29: 438.4229 | I29: 441.81827 | J29: 445.118 | K29: 717.54997 | L29: 618.36616 | M29: 331.81387 | N29: 1123.6109 | O29: 400.96644 | P29: 451.54283 | Q29: 275.66169 | R29: 262.4776 | S29: 463.51788 | T29: 396.4459 | U29: 457.74415 | V29: 303.16353 | W29: 306.00889 | X29: 180.26399 | Y29: 286.75633 | Z29: 554.3042 | AA29: 451.34824 | AB29: 247.55803 | AC29: 393.22794 | AD29: 292.84156 | AE29: 291.16405 | AF29: 488.29841 | AG29: 258.69625 | AH29: 312.23603 | AI29: 335.38977 | AJ29: 471.44684 | AK29: 477.26132 | AL29: 558.34594 | AM29: 388.43167 | AN29: 344.95326 | AO29: 342.55942 | AP29: 504.93648 | AQ29: 377.96689 | AR29: 344.48377 | AS29: 287.77253 | AT29: 334.42493 | AU29: 552.40838 | AV29: 590.09197 | AW29: 333.34214 | AX29: 501.19224 | AY29: 251.83966 | AZ29: 654.8312 | BA29: 315.65086 | BB29: 273.24408
A30: 28 | B30: M_Avocs | C30: 01.d | D30: 01.22 | E30: Avocados, market of | F30: Meuro | G30: 467.54946 | H30: 523.46364 | I30: 438.46284 | J30: 634.71458 | K30: 361.19935 | L30: 764.67024 | M30: 535.22146 | N30: 1178.4882 | O30: 806.8228 | P30: 456.49142 | Q30: 544.71712 | R30: 311.73694 | S30: 411.44289 | T30: 540.34988 | U30: 426.9849 | V30: 524.00105 | W30: 946.83894 | X30: 659.13692 | Y30: 438.78361 | Z30: 439.52177 | AA30: 1025.9061 | AB30: 394.01978 | AC30: 638.14223 | AD30: 382.02266 | AE30: 1068.4698 | AF30: 648.94769 | AG30: 416.57529 | AH30: 360.53383 | AI30: 378.00963 | AJ30: 451.84624 | AK30: 1310.2652 | AL30: 1218.9971 | AM30: 386.35192 | AN30: 457.06677 | AO30: 375.02825 | AP30: 651.78486 | AQ30: 537.74407 | AR30: 381.96011 | AS30: 343.73071 | AT30: 443.5369 | AU30: 902.35827 | AV30: 993.57534 | AW30: 1386.0215 | AX30: 1015.8794 | AY30: 938.11066 | AZ30: 1027.5699 | BA30: 428.34181 | BB30: 2221.2359
A31: 29 | B31: M_Bambs | C31: 01.d | D31: 01.25 | E31: Bambara beans, market of | F31: Meuro | G31: 50.530405 | I31: 21.620818 | J31: 19.745417 | L31: 137.34228 | M31: 22.866254 | N31: 1683.7055 | O31: 46.249322 | P31: 48.597678 | Q31: 6.6054001 | R31: 17.48428 | S31: 799.90263 | T31: 1441.5262 | U31: 67.061137 | V31: 41.37616 | W31: 804.32489 | X31: 9.0481424 | Y31: 4.3913278 | Z31: 23.459628 | AA31: 109.97918 | AD31: 35.423143 | AF31: 7.465189 | AH31: 15.629361 | AI31: 18.770713 | AJ31: 51.162746 | AL31: 44.483601 | AM31: 14.289253 | AN31: 80.915203 | AO31: 7.0838129 | AP31: 23.349153 | AR31: 18.623941 | AS31: 1.9806567 | AT31: 5.1849326 | AU31: 14.691787 | AV31: 78.810114 | AW31: 41.725547 | AY31: 1671.1083 | AZ31: 232.1163 | BA31: 153.4825 | BB31: 25.243931
A32: 30 | B32: M_Banas | C32: 01.d | D32: 01.22 | E32: Bananas, market of | F32: Meuro | G32: 571.44921 | H32: 863.38806 | I32: 1231.4825 | J32: 784.28275 | K32: 836.35471 | L32: 392.53065 | M32: 1233.7474 | N32: 817.15264 | O32: 1642.5661 | P32: 570.48165 | Q32: 1294.8412 | R32: 903.53147 | S32: 612.68876 | T32: 879.25404 | U32: 1262.5212 | V32: 983.40143 | W32: 1254.3648 | X32: 1171.0726 | Y32: 1223.4804 | Z32: 607.50559 | AA32: 409.01566 | AB32: 1081.8958 | AC32: 479.85384 | AD32: 1269.6838 | AE32: 1078.1341 | AF32: 1211.6692 | AG32: 1259.4621 | AH32: 1053.8355 | AI32: 1357.295 | AJ32: 1100.3111 | AK32: 1237.5263 | AL32: 1309.6473 | AM32: 1093.5731 | AN32: 1183.5539 | AO32: 988.48977 | AP32: 683.59399 | AQ32: 1370.9874 | AR32: 1101.8432 | AS32: 1297.8377 | AT32: 558.37994 | AU32: 826.87476 | AV32: 1315.2599 | AW32: 1082.5993 | AX32: 1296.8176 | AY32: 962.23552 | AZ32: 1018.7168 | BA32: 984.11623 | BB32: 2068.765
A33: 31 | B33: M_Beann | C33: 01.d | D33: 01.25 | E33: Beans, green, market of | F33: Meuro | G33: 302.51631 | H33: 410.20119 | I33: 330.50189 | J33: 1295.4963 | K33: 2203.2603 | L33: 1500.028 | M33: 605.33216 | N33: 462.41473 | O33: 170.12686 | P33: 441.63782 | Q33: 339.32211 | R33: 301.39074 | S33: 409.46572 | T33: 359.09367 | U33: 671.68094 | V33: 808.34788 | W33: 297.14125 | X33: 227.80821 | Y33: 702.15841 | Z33: 1245.6504 | AA33: 789.73636 | AB33: 179.70791 | AC33: 674.68783 | AD33: 340.16488 | AE33: 580.09618 | AF33: 2283.5977 | AG33: 1330.2198 | AH33: 427.12374 | AI33: 653.71643 | AJ33: 294.79113 | AK33: 1341.9456 | AL33: 413.78944 | AM33: 740.52031 | AN33: 404.9872 | AO33: 256.72719 | AP33: 432.55043 | AQ33: 529.05409 | AR33: 364.8289 | AS33: 387.99481 | AT33: 443.73543 | AU33: 317.71116 | AV33: 1579.5204 | AW33: 542.00864 | AX33: 2195.1737 | AY33: 180.81843 | AZ33: 869.78183 | BA33: 611.35975 | BB33: 2263.9409
A34: 32 | B34: M_Beany | C34: 01.d | D34: 01.25 | E34: Beans, dry, market of | F34: Meuro | G34: 2538.121 | H34: 3791.9754 | I34: 1596.069 | J34: 1013.1053 | K34: 2156.4568 | L34: 3003.6715 | M34: 2220.1666 | N34: 1906.0134 | O34: 674.99381 | P34: 1242.6965 | Q34: 1788.841 | R34: 1397.1583 | S34: 7051.493 | T34: 806.74245 | U34: 1875.7809 | V34: 1473.1672 | W34: 2959.6656 | X34: 699.59982 | Y34: 1369.4279 | Z34: 2275.4979 | AA34: 3462.2828 | AB34: 2473.0052 | AC34: 2915.181 | AD34: 1236.4225 | AE34: 1256.3715 | AF34: 2009.3977 | AG34: 5539.1068 | AH34: 3197.4327 | AI34: 7741.0424 | AJ34: 955.4095 | AK34: 6728.4787 | AL34: 1737.5488 | AM34: 1458.5459 | AN34: 2043.5236 | AO34: 810.36481 | AP34: 1148.5427 | AQ34: 1050.1688 | AR34: 1192.5433 | AS34: 1168.184 | AT34: 1782.3992 | AU34: 840.09536 | AV34: 3251.3289 | AW34: 731.33245 | AX34: 1204.89 | AY34: 1038.0262 | AZ34: 589.40796 | BA34: 883.76917 | BB34: 2244.3977
A35: 33 | B35: M_Berrs | C35: 01.d | D35: 01.25 | E35: Berries nes, market of | F35: Meuro | G35: 477.82763 | H35: 1119.0436 | I35: 729.21882 | J35: 2026.7288 | K35: 721.13501 | L35: 1008.1725 | M35: 349.34448 | N35: 919.98243 | O35: 804.67339 | P35: 1352.4845 | Q35: 387.49856 | R35: 469.78997 | S35: 4441.37 | T35: 446.50416 | U35: 2876.4484 | V35: 528.97639 | W35: 567.05672 | X35: 556.60708 | Y35: 3371.9452 | Z35: 575.52858 | AA35: 697.54271 | AB35: 556.27184 | AC35: 430.3264 | AD35: 620.82629 | AE35: 367.7009 | AG35: 2482.041 | AH35: 649.33777 | AI35: 2690.1485 | AJ35: 297.60477 | AK35: 410.95705 | AL35: 695.47861 | AM35: 940.32138 | AN35: 870.55567 | AO35: 357.59953 | AP35: 367.56911 | AQ35: 615.90653 | AR35: 2335.4329 | AS35: 875.16559 | AT35: 502.79915 | AU35: 527.04944 | AV35: 629.28788 | AW35: 517.18049 | AX35: 1081.3193 | AY35: 394.74342 | AZ35: 954.10856 | BA35: 723.58666 | BB35: 447.71049
A36: 34 | B36: M_Blues | C36: 01.d | D36: 01.25 | E36: Blueberries, market of | F36: Meuro | G36: 351.13272 | H36: 387.18547 | I36: 260.95634 | J36: 263.56857 | K36: 163.8129 | L36: 785.63973 | M36: 224.84779 | N36: 825.93859 | O36: 340.3337 | P36: 301.79549 | Q36: 235.4786 | R36: 238.27364 | S36: 1252.2326 | T36: 141.27117 | U36: 435.76368 | V36: 236.41702 | W36: 272.81468 | X36: 268.54853 | Y36: 221.84282 | Z36: 281.80384 | AA36: 341.50783 | AB36: 195.46247 | AC36: 349.91938 | AD36: 197.81566 | AE36: 324.3759 | AF36: 317.36756 | AG36: 823.18521 | AH36: 279.7495 | AI36: 897.19478 | AJ36: 247.22367 | AK36: 285.1499 | AL36: 360.08324 | AM36: 322.02308 | AN36: 418.021 | AO36: 159.50718 | AP36: 282.05623 | AQ36: 313.91676 | AR36: 296.52917 | AS36: 206.46711 | AT36: 301.11709 | AU36: 321.52677 | AV36: 401.17887 | AW36: 199.72635 | AX36: 339.82119 | AY36: 191.97754 | AZ36: 501.45039 | BA36: 405.84652 | BB36: 300.01915
A37: 35 | B37: M_Brazl | C37: 01.d | D37: 01.25 | E37: Brazil nuts, with shell, market of | F37: Meuro | G37: 386.69863 | H37: 142.03125 | I37: 23.287946 | J37: 190.27665 | K37: 83.203922 | L37: 201.01011 | M37: 383.81852 | N37: 98.930885 | O37: 67.420091 | P37: 523.09286 | Q37: 437.74949 | R37: 339.58182 | S37: 328.47468 | T37: 35.4222 | V37: 301.21999 | W37: 318.82674 | X37: 317.48095 | AB37: 195.18001 | AC37: 129.44558 | AD37: 353.30456 | AE37: 113.69734 | AF37: 216.15817 | AG37: 330.50271 | AH37: 25.9424 | AI37: 323.41266 | AJ37: 349.14542 | AK37: 117.2916 | AL37: 543.37707 | AM37: 408.62692 | AN37: 390.39527 | AO37: 337.49189 | AP37: 345.99214 | AR37: 283.58764 | AS37: 339.62608 | AT37: 534.79181 | AV37: 153.57774 | AW37: 112.30107 | AX37: 101.70354 | AY37: 115.63192 | AZ37: 505.34208 | BA37: 231.50587 | BB37: 497.04935
A38: 36 | B38: M_Broay | C38: 01.d | D38: 01.25 | E38: Broad beans, horse beans, dry, market of | F38: Meuro | G38: 7113.8187 | H38: 5814.673 | I38: 3011.8585 | J38: 4296.114 | K38: 36219.997 | L38: 2530.4921 | M38: 3179.4107 | N38: 2167.114 | O38: 966.63573 | P38: 9892.165 | Q38: 2578.5598 | R38: 2382.136 | S38: 3537.9799 | T38: 9627.2093 | U38: 2563.2556 | V38: 9085.6109 | W38: 2621.7981 | X38: 812.00241 | Y38: 3497.496 | Z38: 2543.6477 | AA38: 4917.198 | AB38: 2556.9588 | AC38: 5525.474 | AD38: 4716.9416 | AE38: 2370.405 | AG38: 4599.3123 | AH38: 4782.5515 | AI38: 2644.9453 | AJ38: 1965.6587 | AK38: 3295.4736 | AL38: 3353.535 | AM38: 7405.2214 | AN38: 8031.6438 | AO38: 3403.6173 | AP38: 8798.8071 | AQ38: 5258.0977 | AR38: 2656.4033 | AS38: 4992.3765 | AT38: 7023.8245 | AU38: 1605.524 | AV38: 2625.4926 | AW38: 1902.1115 | AX38: 1622.3074 | AY38: 1078.5599 | AZ38: 2034.009 | BA38: 2805.313 | BB38: 1825.3745
A39: 37 | B39: M_Cabbs | C39: 01.d | D39: 01.13 | E39: Cabbages and other brassicas, market of | F39: Meuro | G39: 484.07587 | H39: 730.51139 | I39: 297.08919 | J39: 1311.7697 | L39: 756.85355 | M39: 290.4187 | N39: 1278.9047 | O39: 566.81802 | P39: 712.61397 | Q39: 490.21608 | R39: 434.14427 | S39: 305.41711 | T39: 321.80549 | U39: 777.415 | V39: 423.90208 | W39: 630.0409 | X39: 414.04297 | Y39: 1300.0031 | Z39: 809.25214 | AA39: 858.51167 | AB39: 539.03052 | AC39: 509.00542 | AD39: 355.62656 | AE39: 744.44605 | AF39: 538.23887 | AG39: 858.55256 | AH39: 373.54045 | AI39: 984.7808 | AJ39: 1545.0701 | AK39: 2376.494 | AL39: 1139.4048 | AM39: 577.87448 | AN39: 763.33087 | AO39: 776.43733 | AP39: 574.53525 | AQ39: 1088.2632 | AR39: 426.77913 | AS39: 905.75192 | AT39: 678.37378 | AU39: 818.20673 | AV39: 727.57183 | AW39: 653.31316 | AX39: 1329.6604 | AY39: 535.77834 | AZ39: 762.42017 | BA39: 994.01949 | BB39: 1267.9974
A40: 38 | B40: M_Carrs | C40: 01.d | D40: 01.13 | E40: Carrots and turnips, market of | F40: Meuro | G40: 342.54646 | H40: 860.40745 | I40: 409.77067 | J40: 749.87583 | K40: 590.37207 | L40: 917.12391 | M40: 511.31606 | N40: 697.28886 | O40: 579.55508 | P40: 785.4906 | Q40: 574.27536 | R40: 225.1784 | S40: 411.94467 | T40: 340.00857 | U40: 422.51915 | V40: 686.57967 | W40: 334.31575 | X40: 359.00558 | Y40: 1120.4379 | Z40: 703.61183 | AA40: 670.83558 | AB40: 356.8332 | AC40: 525.83045 | AD40: 426.6749 | AE40: 479.61772 | AF40: 498.56886 | AG40: 855.32444 | AH40: 421.24898 | AI40: 933.5526 | AJ40: 544.6308 | AK40: 2142.6065 | AL40: 1375.4774 | AM40: 618.51148 | AN40: 1546.0555 | AO40: 958.9467 | AP40: 524.96737 | AQ40: 1125.5702 | AR40: 376.83863 | AS40: 661.41199 | AT40: 816.10308 | AU40: 414.0619 | AV40: 673.2257 | AW40: 414.32234 | AX40: 1304.4211 | AY40: 438.77416 | AZ40: 931.32407 | BA40: 759.42403 | BB40: 1463.4712
A41: 39 | B41: M_Cashe | C41: 01.d | D41: 01.22 | E41: Cashewapple, market of | F41: Meuro | K41: 6439.1795 | AY41: 2345.8838 | AZ41: 2089.2812
A42: 40 | B42: M_Cashl | C42: 01.d | D42: 01.25 | E42: Cashew nuts, with shell, market of | F42: Meuro | G42: 3563.6402 | H42: 1548.9612 | I42: 6296.6573 | K42: 21055.696 | L42: 5940.3081 | M42: 2731.8545 | N42: 6012.6251 | O42: 6096.3331 | P42: 3535.9809 | Q42: 5303.6379 | R42: 4415.9578 | S42: 4093.4145 | T42: 3728.0778 | U42: 3394.3636 | V42: 6283.035 | W42: 2822.195 | Z42: 3620.618 | AA42: 17169.752 | AB42: 2992.6771 | AC42: 2645.8416 | AD42: 5591.8952 | AE42: 1512.5864 | AF42: 1566.9871 | AG42: 6193.7474 | AH42: 6299.6834 | AI42: 6241.1454 | AJ42: 3838.7089 | AK42: 6754.204 | AL42: 6280.7903 | AM42: 3445.978 | AN42: 6045.119 | AO42: 3896.0966 | AP42: 4534.0211 | AQ42: 1592.0637 | AR42: 5341.3301 | AS42: 4367.7473 | AT42: 2959.4749 | AU42: 5232.9643 | AV42: 6317.6886 | AW42: 3864.4269 | AX42: 6790.2619 | AY42: 6507.1979 | AZ42: 20335.265 | BA42: 5841.9828 | BB42: 5296.0529
A43: 41 | B43: M_Cassa | C43: 01.d | D43: 01.13 | E43: Cassava, market of | F43: Meuro | K43: 3897.8175 | N43: 3032.8786 | AA43: 1280.5052 | AC43: 1236.5711 | AK43: 2779.9333 | AW43: 1623.5569 | AY43: 954.53872 | AZ43: 1160.4301
A44: 42 | B44: M_Casss | C44: 01.d | D44: 01.13 | E44: Cassava leaves | F44: Meuro | AY44: 597.19501
A45: 43 | B45: M_Cauli | C45: 01.d | D45: 01.13 | E45: Cauliflowers and broccoli, market of | F45: Meuro | G45: 458.76485 | H45: 1080.3409 | I45: 386.9878 | J45: 551.13608 | K45: 798.11229 | L45: 513.61287 | M45: 370.96824 | N45: 1147.8787 | O45: 531.49486 | P45: 586.19668 | Q45: 525.17363 | R45: 380.90398 | S45: 516.85376 | T45: 432.94699 | U45: 826.61124 | V45: 1110.4995 | W45: 648.97132 | X45: 271.4152 | Y45: 604.11634 | Z45: 530.83339 | AA45: 946.86145 | AB45: 561.94411 | AC45: 532.1184 | AD45: 367.67895 | AE45: 1478.7207 | AF45: 1185.4106 | AG45: 643.00246 | AH45: 502.4519 | AI45: 656.80218 | AJ45: 822.3115 | AK45: 2261.0137 | AL45: 628.09646 | AM45: 581.23481 | AN45: 841.65254 | AO45: 702.67066 | AP45: 338.93224 | AQ45: 678.72483 | AR45: 479.0337 | AS45: 447.60667 | AT45: 640.63454 | AU45: 634.37847 | AV45: 467.05516 | AW45: 430.3099 | AX45: 650.69443 | AY45: 259.55595 | AZ45: 1491.2179 | BA45: 626.27513 | BB45: 2138.0046
A46: 44 | B46: M_Cherr | C46: 01.d | D46: 01.24 | E46: Cherries, sour, market of | F46: Meuro | G46: 997.94193 | H46: 1256.0346 | I46: 1034.6189 | J46: 3050.9098 | K46: 1198.2879 | L46: 1458.1299 | M46: 262.88388 | N46: 937.12272 | O46: 755.73697 | P46: 2173.2305 | Q46: 519.06339 | R46: 3406.807 | S46: 1565.4325 | T46: 525.76285 | U46: 369.24925 | V46: 551.29806 | W46: 650.21277 | X46: 364.75927 | Y46: 3934.7037 | Z46: 1587.5303 | AA46: 1136.6559 | AB46: 1539.1943 | AC46: 1076.729 | AD46: 342.26155 | AE46: 1121.2034 | AF46: 1257.6862 | AG46: 1281.4413 | AH46: 499.87042 | AI46: 1922.6426 | AJ46: 381.8283 | AK46: 1284.0121 | AL46: 985.94402 | AM46: 1008.3414 | AN46: 2317.3267 | AO46: 1223.9835 | AP46: 2039.3485 | AQ46: 712.85788 | AR46: 371.7414 | AS46: 783.08206 | AT46: 2181.9292 | AU46: 1071.9405 | AV46: 1238.8453 | AW46: 1024.6827 | AX46: 1134.7006 | AY46: 438.94546 | AZ46: 414.14174 | BA46: 765.40991
A47: 45 | B47: M_Chers | C47: 01.d | D47: 01.24 | E47: Cherries, market of | F47: Meuro | G47: 393.79014 | H47: 267.13933 | I47: 727.97313 | J47: 1537.3929 | K47: 679.82791 | L47: 408.15665 | M47: 274.59558 | N47: 795.08176 | O47: 462.53285 | P47: 1093.3943 | Q47: 419.46673 | R47: 378.3955 | S47: 1312.0394 | T47: 524.66689 | U47: 883.63221 | V47: 430.74878 | W47: 538.33386 | X47: 294.43421 | Y47: 1142.5359 | Z47: 938.54997 | AA47: 308.05823 | AB47: 568.5929 | AC47: 1809.0014 | AD47: 386.048 | AE47: 239.57841 | AF47: 364.98181 | AG47: 775.53832 | AH47: 473.20617 | AI47: 919.27999 | AJ47: 729.00614 | AK47: 449.27058 | AL47: 538.10487 | AM47: 383.91834 | AN47: 980.01132 | AO47: 632.77155 | AP47: 244.40216 | AQ47: 881.66985 | AR47: 534.65999 | AS47: 210.52472 | AT47: 667.16632 | AU47: 667.24527 | AV47: 402.7451 | AW47: 910.72251 | AX47: 965.44967 | AY47: 562.37262 | AZ47: 635.27746 | BA47: 605.60142 | BB47: 736.93907
A48: 46 | B48: M_Chest | C48: 01.d | D48: 01.25 | E48: Chestnut, market of | F48: Meuro | G48: 565.79598 | H48: 795.22442 | I48: 839.46306 | J48: 668.38648 | K48: 2323.6302 | L48: 1018.0604 | M48: 531.34992 | N48: 780.15588 | O48: 650.51521 | P48: 581.64247 | Q48: 687.37322 | R48: 832.6916 | S48: 688.31169 | T48: 3352.554 | U48: 510.6121 | V48: 1248.4459 | W48: 621.20442 | X48: 399.15942 | Y48: 725.8362 | Z48: 2113.6679 | AA48: 818.99569 | AB48: 543.86881 | AC48: 1029.3119 | AD48: 860.03186 | AE48: 945.70897 | AF48: 1444.3705 | AG48: 599.72261 | AH48: 1344.4941 | AI48: 577.32949 | AJ48: 641.16238 | AK48: 524.49408 | AL48: 836.83572 | AM48: 890.11286 | AN48: 907.535 | AO48: 2497.918 | AP48: 731.42536 | AQ48: 810.13413 | AR48: 594.67638 | AS48: 637.17203 | AT48: 485.3275 | AU48: 862.52122 | AV48: 796.66572 | AW48: 999.95203 | AX48: 1925.1757 | AY48: 1562.4005 | AZ48: 2650.2608 | BA48: 836.96044 | BB48: 1513.4394
A49: 47 | B49: M_Chick | C49: 01.d | D49: 01.11 | E49: Chick peas, market of | F49: Meuro | G49: 2190.6223 | H49: 5104.121 | I49: 2183.2243 | J49: 2119.3432 | K49: 1671.5727 | L49: 3198.4857 | M49: 2070.6674 | N49: 756.29381 | O49: 828.07474 | P49: 1865.6837 | Q49: 1965.2861 | R49: 1568.9477 | S49: 1949.6177 | T49: 3055.3599 | U49: 1801.6603 | V49: 2481.1509 | W49: 3339.4839 | X49: 722.25945 | Y49: 2073.5011 | Z49: 1711.7916 | AA49: 1408.6434 | AB49: 2524.9982 | AC49: 2357.1387 | AD49: 1933.9193 | AE49: 2909.707 | AF49: 3443.4407 | AG49: 1390.3802 | AH49: 3176.7467 | AI49: 3081.8276 | AJ49: 1895.6615 | AK49: 2795.3181 | AL49: 1904.6566 | AM49: 1471.6269 | AN49: 1770.911 | AO49: 2318.1845 | AP49: 1367.7479 | AQ49: 3311.3801 | AR49: 1725.5565 | AS49: 1946.7199 | AT49: 2614.8126 | AU49: 1811.1136 | AV49: 3572.6775 | AW49: 2122.9216 | AX49: 1056.4024 | AY49: 958.15764 | AZ49: 1113.7926 | BA49: 1839.3084 | BB49: 2933.7061
A50: 48 | B50: M_Chics | C50: 01.d | D50: 01.13 | E50: Chicory roots, market of | F50: Meuro | G50: 953.54809 | H50: 881.95688 | I50: 661.99177 | L50: 717.71132 | M50: 1812.0127 | N50: 870.19708 | P50: 6526.0578 | Q50: 1928.2241 | R50: 1328.3048 | T50: 403.3427 | V50: 623.26697 | W50: 1769.8254 | Y50: 882.01252 | Z50: 1283.8456 | AD50: 1306.0408 | AG50: 6364.374 | AH50: 1783.491 | AI50: 5624.6883 | AK50: 704.11745 | AL50: 1783.2996 | AM50: 492.50669 | AN50: 6374.2295 | AO50: 369.77869 | AP50: 8111.8372 | AQ50: 6931.8982 | AR50: 1614.5945 | AS50: 1332.4499 | AT50: 2949.1361 | AV50: 700.61445 | AW50: 526.46341 | AX50: 673.00696 | AY50: 200.45461 | AZ50: 975.47029 | BA50: 782.04437 | BB50: 10428.462
A51: 49 | B51: M_Clovs | C51: 01.d | D51: 01.28 | E51: Cloves, market of | F51: Meuro | G51: 1476.692 | H51: 3089.6021 | I51: 3180.7566 | J51: 2991.5973 | K51: 6199.3342 | L51: 3560.3181 | M51: 1303.2407 | N51: 1214.7508 | O51: 1200.1975 | P51: 2320.0873 | Q51: 2647.0101 | R51: 1917.305 | S51: 2392.0421 | T51: 3607.6532 | U51: 1671.3024 | V51: 3738.2506 | W51: 1951.2112 | X51: 2454.2306 | Y51: 2753.0707 | Z51: 3303.4757 | AA51: 6230.5591 | AB51: 1376.422 | AC51: 3098.2191 | AD51: 3205.3822 | AE51: 1031.4769 | AF51: 3846.1158 | AG51: 2796.7601 | AH51: 3649.1701 | AI51: 3016.8431 | AJ51: 2605.3059 | AK51: 2402.2867 | AL51: 2878.0314 | AM51: 2100.1015 | AN51: 3315.1675 | AO51: 3221.8977 | AP51: 4390.8669 | AQ51: 2811.7117 | AR51: 1004.9244 | AS51: 2821.38 | AT51: 4452.3172 | AU51: 4472.7797 | AV51: 3058.4439 | AW51: 2093.1062 | AX51: 3020.1437 | AY51: 2399.4522 | AZ51: 1775.926 | BA51: 3694.0756 | BB51: 1376.9902
A52: 50 | B52: M_Cocon | C52: 01.d | D52: 01.26 | E52: Coconuts, market of | F52: Meuro | G52: 3044.2474 | H52: 3235.5059 | I52: 2100.8681 | J52: 1236.7346 | K52: 1339.3055 | L52: 2887.6968 | M52: 1941.8953 | N52: 1293.726 | O52: 3257.8947 | P52: 1567.3006 | Q52: 1020.247 | R52: 1003.1542 | S52: 2286.0558 | T52: 2033.8617 | U52: 2640.7003 | V52: 944.0227 | W52: 1049.691 | X52: 711.38891 | Y52: 2424.5966 | Z52: 754.42837 | AA52: 4219.6415 | AB52: 898.74578 | AC52: 869.78817 | AD52: 1460.7612 | AE52: 2969.9122 | AF52: 3483.621 | AG52: 727.09792 | AH52: 773.4464 | AI52: 2225.0852 | AJ52: 1760.1972 | AK52: 11535.416 | AL52: 3200.1179 | AM52: 2708.5892 | AN52: 762.89462 | AO52: 1807.4639 | AP52: 2763.5764 | AQ52: 1691.6052 | AR52: 2478.6951 | AS52: 792.77027 | AT52: 773.34068 | AU52: 1796.3042 | AV52: 4817.9508 | AW52: 3141.9582 | AX52: 3230.8765 | AY52: 4394.0931 | AZ52: 1382.3482 | BA52: 1035.5757 | BB52: 1154.3544
A53: 51 | B53: M_Coirr | C53: 01.d | D53: 01.26 | E53: Production of crude petroleum and services related to crude oil extraction, excluding surveying, market of | F53: Meuro | G53: 49.87623 | H53: 71.183846 | I53: 20.580687 | J53: 18.836185 | K53: 9.8277405 | L53: 129.27935 | M53: 21.878838 | N53: 24.875028 | O53: 45.772262 | P53: 48.587811 | Q53: 5.5056116 | R53: 16.760848 | S53: 21.691437 | T53: 19.585232 | U53: 66.089746 | V53: 38.417428 | W53: 6.7099073 | X53: 8.048011 | Y53: 3.2948765 | Z53: 22.586733 | AA53: 109.16879 | AB53: 10.185108 | AC53: 49.86022 | AD53: 35.371716 | AE53: 43.76882 | AF53: 6.8475341 | AG53: 29.198035 | AI53: 17.742209 | AJ53: 50.147973 | AK53: 36.069689 | AL53: 43.992588 | AM53: 13.878719 | AN53: 79.911106 | AO53: 6.0113861 | AP53: 22.648323 | AQ53: 8.881351 | AS53: 1.4488663 | AU53: 14.091464 | AV53: 77.855409 | AW53: 40.424586 | AX53: 28.439398 | AY53: 36.768624 | AZ53: 232.09368 | BA53: 148.15179 | BB53: 24.270072
A54: 52 | B54: M_Cowpea | C54: 01.d | D54: 01.11 | E54: Cow peas, dry, market of | F54: Meuro | G54: 4654.4456 | H54: 4996.0199 | I54: 5086.4756 | J54: 2848.6133 | K54: 4613.0188 | L54: 4326.652 | M54: 4472.3097 | N54: 10560.56 | O54: 692.25013 | P54: 4530.1947 | Q54: 4786.6709 | R54: 3100.0709 | S54: 5053.9081 | T54: 4714.2506 | U54: 4655.2906 | V54: 4294.4582 | W54: 4549.6407 | X54: 4272.8195 | Y54: 2928.4505 | Z54: 3286.0386 | AA54: 2104.6189 | AB54: 3785.6005 | AC54: 2747.5575 | AD54: 4578.5246 | AE54: 9264.8511 | AF54: 5205.5123 | AG54: 2627.931 | AH54: 4909.8851 | AI54: 2651.6397 | AJ54: 4414.852 | AK54: 5334.5915 | AL54: 5171.2973 | AM54: 3414.0736 | AO54: 4618.6964 | AP54: 3926.1009 | AQ54: 4770.4465 | AR54: 4163.9804 | AT54: 4822.3794 | AU54: 3583.7783 | AV54: 4988.2133 | AW54: 1314.8216 | AX54: 2350.4257 | AY54: 2759.7383 | AZ54: 2985.8374 | BA54: 1849.3546 | BB54: 11041.767
A55: 53 | B55: M_Crans | C55: 01.d | D55: 01.25 | E55: Cranberries, market of | F55: Meuro | G55: 131.27888 | H55: 71.183846 | I55: 181.08034 | J55: 1653.3634 | K55: 19.163618 | L55: 609.71232 | M55: 216.87142 | N55: 28.205896 | O55: 728.84492 | P55: 427.04622 | Q55: 95.501452 | R55: 72.736767 | S55: 352.02218 | T55: 101.70376 | U55: 125.06599 | V55: 151.41671 | W55: 88.082863 | X55: 768.04888 | Y55: 88.168955 | Z55: 83.487885 | AA55: 109.16879 | AB55: 78.63215 | AC55: 128.06747 | AD55: 124.67202 | AE55: 116.07003 | AF55: 25.26357 | AG55: 421.5353 | AH55: 86.860124 | AI55: 1147.0452 | AJ55: 60.052164 | AK55: 643.20539 | AL55: 122.7979 | AM55: 77.829819 | AN55: 348.18925 | AO55: 16.2069 | AP55: 398.63616 | AQ55: 162.31392 | AR55: 272.20678 | AS55: 70.28296 | AT55: 91.641397 | AU55: 211.25893 | AV55: 345.80562 | AW55: 342.71805 | AX55: 246.27867 | AY55: 160.25633 | AZ55: 588.47421 | BA55: 301.0204
A56: 54 | B56: M_Cucus | C56: 01.d | D56: 01.13 | E56: Cucumbers and gherkins, market of | F56: Meuro | G56: 284.16102 | H56: 286.19041 | I56: 412.1567 | J56: 337.64633 | L56: 868.57717 | M56: 242.96627 | N56: 969.46959 | O56: 422.66584 | P56: 377.01517 | Q56: 335.33772 | R56: 176.87217 | S56: 239.35289 | T56: 209.82513 | U56: 249.54596 | V56: 331.83079 | W56: 308.19359 | X56: 219.02322 | Y56: 413.72226 | Z56: 311.83702 | AA56: 1716.575 | AB56: 205.03977 | AC56: 867.45118 | AD56: 278.27994 | AE56: 306.15177 | AF56: 239.10507 | AG56: 343.06713 | AH56: 374.58331 | AI56: 162.59126 | AJ56: 316.12956 | AK56: 1209.1472 | AL56: 521.65663 | AM56: 263.5065 | AN56: 536.92182 | AO56: 459.03203 | AP56: 422.87136 | AQ56: 241.4171 | AR56: 215.36162 | AS56: 408.95358 | AT56: 339.38467 | AU56: 634.6536 | AV56: 1047.3124 | AW56: 515.01263 | AX56: 450.1614 | AY56: 1118.275 | AZ56: 757.31125 | BA56: 566.15935 | BB56: 2014.011
A57: 55 | B57: M_Currs | C57: 01.d | D57: 01.25 | E57: Currants, market of | F57: Meuro | G57: 558.09915 | H57: 1821.4192 | I57: 469.32479 | J57: 606.01336 | L57: 397.90905 | M57: 276.25489 | N57: 274.76391 | O57: 2057.2513 | P57: 3469.3062 | Q57: 430.26069 | R57: 2610.9516 | S57: 1644.127 | T57: 116.28007 | U57: 1619.6999 | V57: 352.83518 | W57: 295.0496 | X57: 253.82866 | Y57: 137.46038 | Z57: 2148.5324 | AB57: 399.36764 | AC57: 291.42592 | AD57: 269.07559 | AE57: 3564.2373 | AG57: 514.30287 | AH57: 384.51526 | AI57: 5790.7159 | AJ57: 415.01882 | AL57: 366.10163 | AM57: 1295.0878 | AN57: 3771.9194 | AO57: 124.37354 | AP57: 2093.3632 | AQ57: 673.33831 | AR57: 1874.0865 | AS57: 150.41066 | AT57: 7714.1523 | AU57: 386.91613 | AV57: 340.85106 | AW57: 829.66433 | AX57: 2218.1051 | AY57: 194.32365 | AZ57: 373.18392 | BA57: 409.8915
A58: 56 | B58: M_Dates | C58: 01.d | D58: 01.22 | E58: Dates, market of | F58: Meuro | G58: 394.14297 | H58: 612.49351 | I58: 250.5267 | J58: 455.97546 | K58: 235.84601 | L58: 523.48784 | M58: 369.17685 | N58: 623.31435 | O58: 428.58851 | P58: 555.4353 | Q58: 293.61186 | R58: 382.61103 | S58: 458.41584 | T58: 290.32037 | U58: 667.84985 | V58: 279.20971 | W58: 505.65143 | X58: 265.92706 | Y58: 281.32682 | Z58: 315.29283 | AA58: 526.21411 | AB58: 249.77508 | AC58: 663.75553 | AD58: 294.29485 | AE58: 547.18141 | AF58: 525.89174 | AG58: 612.93144 | AH58: 288.93533 | AI58: 452.48518 | AJ58: 459.75732 | AK58: 512.09887 | AL58: 447.01123 | AM58: 415.85943 | AN58: 578.83215 | AO58: 264.08625 | AP58: 636.82261 | AQ58: 408.21698 | AR58: 409.69326 | AS58: 615.10067 | AT58: 290.02251 | AU58: 667.73439 | AV58: 482.35969 | AW58: 595.22631 | AX58: 737.78426 | AY58: 262.48615 | AZ58: 687.37749 | BA58: 692.13879 | BB58: 424.30267
A59: 57 | B59: M_Eggpl | C59: 01.d | D59: 01.13 | E59: Eggplants (aubergines), market of | F59: Meuro | G59: 470.15104 | H59: 878.19712 | I59: 380.62301 | J59: 1089.5154 | L59: 492.58127 | M59: 419.69504 | N59: 1398.7519 | O59: 1616.3066 | P59: 579.86819 | Q59: 579.62063 | R59: 502.51191 | S59: 610.80963 | T59: 484.92526 | U59: 750.10844 | V59: 404.65588 | W59: 645.00679 | X59: 294.05695 | Y59: 478.85935 | Z59: 580.98157 | AA59: 1591.1737 | AB59: 596.41895 | AC59: 446.54778 | AD59: 468.96659 | AE59: 469.30791 | AF59: 475.15291 | AG59: 1572.469 | AH59: 326.64888 | AI59: 571.95661 | AJ59: 668.53788 | AK59: 1331.2871 | AL59: 790.85449 | AM59: 635.66778 | AN59: 725.31347 | AO59: 603.87753 | AP59: 691.59576 | AQ59: 994.03892 | AR59: 625.69519 | AS59: 446.48142 | AT59: 597.16357 | AU59: 1045.9428 | AV59: 612.77519 | AW59: 806.65745 | AX59: 1120.6381 | AY59: 371.46318 | AZ59: 1160.9885 | BA59: 1271.7236 | BB59: 330.55101
A60: 58 | B60: M_Figss | C60: 01.d | D60: 01.22 | E60: Figs, market of | F60: Meuro | G60: 581.69251 | H60: 3119.583 | I60: 383.27465 | J60: 350.51965 | K60: 181.89658 | L60: 780.6906 | M60: 289.74901 | N60: 479.77368 | O60: 456.31557 | P60: 589.3267 | Q60: 395.83276 | R60: 342.35861 | S60: 679.44811 | T60: 659.25676 | U60: 281.67459 | V60: 333.70642 | W60: 436.18699 | X60: 282.1488 | Y60: 723.63077 | Z60: 580.83047 | AA60: 1206.3968 | AB60: 231.96312 | AC60: 323.48107 | AD60: 598.85614 | AE60: 1500.7527 | AG60: 554.26021 | AH60: 244.11082 | AI60: 524.19565 | AJ60: 462.2066 | AK60: 2773.781 | AL60: 300.23658 | AM60: 428.84919 | AN60: 622.08358 | AO60: 1750.0535 | AP60: 408.76602 | AQ60: 791.54913 | AR60: 660.97041 | AS60: 683.1067 | AT60: 572.30427 | AU60: 856.92124 | AV60: 724.05048 | AW60: 1385.7764 | AX60: 902.63206 | AY60: 1236.2614 | AZ60: 1229.9139 | BA60: 1187.9493 | BB60: 1396.0857
A61: 59 | B61: M_frtrop_nes | C61: 01.d | D61: 01.22 | E61: Fruit, tropical fresh nes, market of | F61: Meuro | G61: 451.28332 | H61: 480.89635 | I61: 1253.8898 | K61: 1160.5069 | L61: 573.47811 | M61: 392.81112 | N61: 2131.2001 | O61: 3538.9706 | P61: 405.54797 | Q61: 1034.9537 | R61: 387.64742 | S61: 1073.9457 | T61: 724.22463 | U61: 411.91568 | V61: 980.22346 | W61: 1205.8097 | X61: 597.02087 | Z61: 646.07436 | AA61: 1060.9815 | AB61: 336.91472 | AC61: 839.22944 | AD61: 696.85439 | AE61: 416.13243 | AF61: 442.43641 | AG61: 744.14769 | AH61: 494.79131 | AI61: 755.72999 | AJ61: 647.78527 | AK61: 2312.7734 | AL61: 1116.2129 | AM61: 358.36593 | AN61: 428.43061 | AO61: 637.5587 | AP61: 668.90379 | AQ61: 1780.5658 | AR61: 819.80423 | AS61: 885.62678 | AT61: 659.35623 | AU61: 431.4837 | AV61: 490.77947 | AW61: 427.37557 | AX61: 529.71698 | AY61: 1007.4055 | AZ61: 1306.8584 | BA61: 462.04492 | BB61: 407.62832
A62: 60 | B62: M_Gooss | C62: 01.d | D62: 01.25 | E62: Gooseberries, market of | F62: Meuro | G62: 1150.7828 | I62: 357.29253 | J62: 3121.0176 | M62: 159.41399 | P62: 1435.5218 | Q62: 284.34719 | S62: 1568.5211 | T62: 1034.6904 | U62: 678.9579 | W62: 177.92029 | Z62: 1419.7088 | AA62: 350.94537 | AB62: 2466.3422 | AG62: 2878.6308 | AI62: 3469.325 | AL62: 2983.8424 | AN62: 2899.3675 | AQ62: 308.46599 | AT62: 3126.5926 | AW62: 290.48358 | AX62: 627.68501
A63: 61 | B63: M_Grapf | C63: 01.d | D63: 01.21 | E63: Grapefruit (inc. pomelos), market of | F63: Meuro | G63: 1568.0312 | H63: 865.83764 | I63: 840.95492 | J63: 1419.7634 | K63: 899.80289 | L63: 1232.0869 | M63: 769.48257 | N63: 611.44643 | O63: 2325.3662 | P63: 1920.1945 | Q63: 1309.2299 | R63: 674.32652 | S63: 2164.1102 | T63: 1118.3694 | U63: 1025.6121 | V63: 1104.795 | W63: 1193.4806 | X63: 942.44848 | Y63: 1222.417 | Z63: 1459.0199 | AA63: 676.58218 | AB63: 1086.9125 | AC63: 574.77995 | AD63: 1050.2168 | AE63: 1369.8443 | AF63: 1566.4329 | AG63: 676.59126 | AH63: 486.05547 | AI63: 799.50404 | AJ63: 872.29003 | AK63: 3646.2172 | AL63: 929.35266 | AM63: 993.29221 | AN63: 1318.9262 | AO63: 1721.3254 | AP63: 869.86077 | AQ63: 838.26124 | AR63: 964.83733 | AS63: 849.28924 | AT63: 1877.2977 | AU63: 1412.3276 | AV63: 1544.57 | AW63: 618.03646 | AX63: 949.51436 | AY63: 1552.9521 | AZ63: 1029.0233 | BA63: 714.10919 | BB63: 1691.6943
A64: 62 | B64: M_Graps | C64: 01.d | D64: 01.21 | E64: Grapes, market of | F64: Meuro | G64: 827.63188 | H64: 1434.2948 | I64: 598.05775 | J64: 2513.2586 | K64: 276.89594 | L64: 688.80271 | M64: 261.49339 | N64: 515.88047 | O64: 3429.7668 | P64: 1026.5942 | Q64: 350.10917 | R64: 441.60692 | S64: 589.19547 | T64: 849.19887 | U64: 630.1217 | V64: 346.75489 | W64: 845.15224 | X64: 454.44824 | Y64: 1274.1657 | Z64: 460.44683 | AA64: 714.49139 | AB64: 707.13907 | AC64: 312.88052 | AD64: 505.90791 | AE64: 309.86928 | AF64: 225.35164 | AG64: 664.44048 | AH64: 565.63172 | AI64: 711.47293 | AJ64: 1118.811 | AK64: 838.85593 | AL64: 811.34238 | AM64: 618.41018 | AN64: 618.937 | AO64: 1792.6584 | AP64: 1066.9809 | AQ64: 1239.7966 | AR64: 562.07851 | AS64: 1482.8331 | AT64: 929.88567 | AU64: 1239.6625 | AV64: 641.77161 | AW64: 1007.0349 | AX64: 1662.6357 | AY64: 487.82487 | AZ64: 642.95688 | BA64: 910.26692 | BB64: 1733.3056
A65: 63 | B65: M_Hazel | C65: 01.d | D65: 01.25 | E65: Hazelnuts, with shell, market of | F65: Meuro | G65: 939.66401 | H65: 639.3802 | I65: 805.71549 | J65: 2821.8979 | K65: 1589.1525 | L65: 656.60958 | M65: 863.8747 | N65: 1044.6431 | O65: 1289.7764 | P65: 700.7755 | Q65: 871.49911 | R65: 631.96193 | S65: 1112.269 | T65: 1416.841 | U65: 838.3167 | V65: 893.07708 | W65: 808.64616 | X65: 412.38665 | Y65: 3111.6253 | Z65: 1700.6948 | AB65: 875.20539 | AD65: 826.93624 | AE65: 782.56947 | AF65: 841.02769 | AG65: 959.48909 | AH65: 934.22683 | AI65: 1733.1888 | AJ65: 823.10187 | AK65: 783.7957 | AL65: 838.18109 | AM65: 685.20514 | AN65: 998.76426 | AO65: 1899.1494 | AP65: 932.83555 | AQ65: 2112.0975 | AR65: 663.48622 | AS65: 857.11785 | AT65: 716.35034 | AU65: 1538.5694 | AV65: 634.51837 | AW65: 1568.8434 | AX65: 808.49233 | AY65: 952.67901 | AZ65: 1305.3236 | BA65: 559.08865 | BB65: 1424.5812
A66: 64 | B66: M_Jute | C66: 01.d | D66: 01.16 | E66: Jute, market of | F66: Meuro | G66: 1344.939 | H66: 1616.9732 | I66: 1336.6005 | J66: 1334.5144 | K66: 1751.4577 | L66: 1348.3482 | M66: 915.41387 | N66: 570.06288 | O66: 1329.6936 | P66: 1333.7751 | Q66: 1325.5614 | R66: 931.57584 | S66: 1322.7766 | T66: 837.85332 | U66: 1287.1607 | V66: 1338.7388 | W66: 1346.8658 | X66: 906.63031 | Y66: 1382.6467 | Z66: 1297.1826 | AA66: 1001.2742 | AB66: 1117.5641 | AC66: 1727.9165 | AD66: 1335.0478 | AE66: 950.34407 | AF66: 1385.9094 | AG66: 1289.0272 | AH66: 1347.0765 | AI66: 1294.9163 | AJ66: 1334.7126 | AK66: 1413.2093 | AL66: 981.21041 | AM66: 1122.6244 | AN66: 1340.2664 | AO66: 1006.8033 | AP66: 1401.0635 | AQ66: 1408.2976 | AR66: 1131.5084 | AS66: 1387.2731 | AT66: 1402.6944 | AU66: 1349.8229 | AV66: 1361.8381 | AW66: 1273.0564 | AX66: 1378.8239 | AY66: 743.50624 | AZ66: 948.07028 | BA66: 654.15703 | BB66: 1223.5967
A67: 65 | B67: M_Kapol | C67: 01.d | D67: 01.29 | E67: Kapokseed in shell | F67: Meuro | AA67: 11743.408 | AW67: 2317.2058
